{"metadata": {"dataVersion": "2", "matchId": "EUW1_7445155073", "participants": ["jvm-IlRENUlgRW0ipxlMAtWqJQmr55n0qz5UwUeaJUq65KuNlbGwWUMuONGbi8ZRnqBIulGN0kBTEQ", "D183BhYdbK4K68t8CF5NO6TLr2r3IhIK0hSih62NJf78Ilnp-Qs1-fwr7rdX89fDhgXfhXwv65K4BQ", "noItxThf9QlTIggMRqxcVJxCwsDCDm6mfZ4lNcFulm4LMTS5AhagGhgqiHiEWKI7RQspHenaST3Sdg", "t2KgqlvfVHzwo3NoBMIppPSoHTZw6Hq4E5uVTjICjQotBZZMKs_aHYtPbeKu-o2T1xGFbtvyJD0OXA", "Mm9VpIbV4XqW1v6C-NsYyEh_Y0l4VKWU1R5vFC8HlPksI5YynSKPzZUFfvCWaXO9_scFMpWWfdYNOA", "Tx82aBZJRl12ZyCHpg-TLaLgcacTA1o5Q9T0EvZEIINZAJcwuA0Y5aUsvDoddqiF0JYOgp-Ms_6ddg", "MKm3XcJLSjD4t3G4Ek0unUs3aexUmBw_yF5nvmRqVIQPdhiXjM_FbJGYWSZaKmLmV-O4aauSr6KVGA", "L_5f66Q9jH8msK7HgBT4UpzBepLKtlFxdy84nxxyHL5GSqYMRUm8xRjXlk78hzHSMGvzNPnEQAVN4Q", "Te9fjeEmED0mdBZArju3ElCSmEzHrELGpjtS8Yyq5aOBBzU3rxSVeL4xpl6J2neXY_A6V14kRIW0hA", "FQ3LeA3YRDWrqQXZwoMu_WQ-1C1QwWH5n9fPJ72gK1qiERrQDhnwfCD-e4yBXRGrVYjXRtJs6m6MAA"]}, "info": {"endOfGameResult": "GameComplete", "gameCreation": 1751051912749, "gameDuration": 1415, "gameEndTimestamp": 1751053351188, "gameId": 7445155073, "gameMode": "ARAM", "gameModeMutators": [], "gameName": "teambuilder-match-7445155073", "gameStartTimestamp": 1751051935481, "gameType": "MATCHED_GAME", "gameVersion": "15.13.693.1306", "mapId": 12, "participants": [{"PlayerScore0": 0, "PlayerScore1": 0, "PlayerScore10": 0, "PlayerScore11": 0, "PlayerScore2": 0, "PlayerScore3": 0, "PlayerScore4": 0, "PlayerScore5": 0, "PlayerScore6": 0, "PlayerScore7": 0, "PlayerScore8": 0, "PlayerScore9": 0, "allInPings": 0, "assistMePings": 0, "assists": 31, "baronKills": 0, "basicPings": 0, "challenges": {"12AssistStreakCount": 1, "HealFromMapSources": 631.263427734375, "InfernalScalePickup": 0, "SWARM_DefeatAatrox": 0, "SWARM_DefeatBriar": 0, "SWARM_DefeatMiniBosses": 0, "SWARM_EvolveWeapon": 0, "SWARM_Have3Passives": 0, "SWARM_KillEnemy": 0, "SWARM_PickupGold": 0, "SWARM_ReachLevel50": 0, "SWARM_Survive15Min": 0, "SWARM_WinWith5EvolvedWeapons": 0, "abilityUses": 233, "acesBefore15Minutes": 1, "alliedJungleMonsterKills": 0, "baronTakedowns": 0, "blastConeOppositeOpponentCount": 0, "bountyGold": 144.34645080566406, "buffsStolen": 0, "completeSupportQuestInTime": 0, "controlWardsPlaced": 0, "damagePerMinute": 2440.120514387625, "damageTakenOnTeamPercentage": 0.1695634430824423, "dancedWithRiftHerald": 0, "deathsByEnemyChamps": 10, "dodgeSkillShotsSmallWindow": 0, "doubleAces": 0, "dragonTakedowns": 0, "effectiveHealAndShielding": 0, "elderDragonKillsWithOpposingSoul": 0, "elderDragonMultikills": 0, "enemyChampionImmobilizations": 16, "enemyJungleMonsterKills": 0, "epicMonsterKillsNearEnemyJungler": 0, "epicMonsterKillsWithin30SecondsOfSpawn": 0, "epicMonsterSteals": 0, "epicMonsterStolenWithoutSmite": 0, "firstTurretKilled": 1, "firstTurretKilledTime": 400.257850964, "fistBumpParticipation": 0, "flawlessAces": 1, "fullTeamTakedown": 18, "gameLength": 1416.0476315110002, "getTakedownsInAllLanesEarlyJungleAsLaner": 0, "goldPerMinute": 663.4155150187844, "hadOpenNexus": 0, "immobilizeAndKillWithAlly": 9, "initialBuffCount": 0, "initialCrabCount": 0, "jungleCsBefore10Minutes": 0, "junglerTakedownsNearDamagedEpicMonster": 0, "kTurretsDestroyedBeforePlatesFall": 2, "kda": 4.3, "killAfterHiddenWithAlly": 15, "killParticipation": 0.7049180327868853, "killedChampTookFullTeamDamageSurvived": 0, "killingSprees": 1, "killsNearEnemyTurret": 0, "killsOnOtherLanesEarlyJungleAsLaner": 0, "killsOnRecentlyHealedByAramPack": 2, "killsUnderOwnTurret": 4, "killsWithHelpFromEpicMonster": 0, "knockEnemyIntoTeamAndKill": 0, "landSkillShotsEarlyGame": 17, "laneMinionsFirst10Minutes": 23, "legendaryCount": 0, "legendaryItemUsed": [6672, 3032, 3153, 3036], "lostAnInhibitor": 1, "maxKillDeficit": 7, "mejaisFullStackInTime": 0, "moreEnemyJungleThanOpponent": 0, "multiKillOneSpell": 0, "multiTurretRiftHeraldCount": 0, "multikills": 3, "multikillsAfterAggressiveFlash": 0, "outerTurretExecutesBefore10Minutes": 0, "outnumberedKills": 1, "outnumberedNexusKill": 0, "perfectDragonSoulsTaken": 0, "perfectGame": 0, "pickKillWithAlly": 33, "poroExplosions": 6, "quickCleanse": 0, "quickFirstTurret": 1, "quickSoloKills": 0, "riftHeraldTakedowns": 0, "saveAllyFromDeath": 0, "scuttleCrabKills": 0, "shortestTimeToAceFromFirstTakedown": 18.820033285000022, "skillshotsDodged": 24, "skillshotsHit": 106, "snowballsHit": 0, "soloBaronKills": 0, "soloKills": 0, "stealthWardsPlaced": 0, "survivedSingleDigitHpCount": 0, "survivedThreeImmobilizesInFight": 1, "takedownOnFirstTurret": 0, "takedowns": 43, "takedownsAfterGainingLevelAdvantage": 0, "takedownsBeforeJungleMinionSpawn": 3, "takedownsFirstXMinutes": 33, "takedownsInAlcove": 0, "takedownsInEnemyFountain": 0, "teamBaronKills": 0, "teamDamagePercentage": 0.22801157042034823, "teamElderDragonKills": 0, "teamRiftHeraldKills": 0, "tookLargeDamageSurvived": 0, "turretPlatesTaken": 0, "turretTakedowns": 2, "turretsTakenWithRiftHerald": 0, "twentyMinionsIn3SecondsCount": 0, "twoWardsOneSweeperCount": 0, "unseenRecalls": 0, "visionScorePerMinute": 0, "voidMonsterKill": 0, "wardTakedowns": 0, "wardTakedownsBefore20M": 0, "wardsGuarded": 0}, "champExperience": 21691, "champLevel": 18, "championId": 523, "championName": "Aphelios", "championTransform": 0, "commandPings": 0, "consumablesPurchased": 2, "damageDealtToBuildings": 2578, "damageDealtToObjectives": 2578, "damageDealtToTurrets": 2578, "damageSelfMitigated": 21320, "dangerPings": 0, "deaths": 10, "detectorWardsPlaced": 0, "doubleKills": 3, "dragonKills": 0, "eligibleForProgression": true, "enemyMissingPings": 3, "enemyVisionPings": 0, "firstBloodAssist": true, "firstBloodKill": false, "firstTowerAssist": true, "firstTowerKill": false, "gameEndedInEarlySurrender": false, "gameEndedInSurrender": true, "getBackPings": 0, "goldEarned": 15657, "goldSpent": 13400, "holdPings": 0, "individualPosition": "Invalid", "inhibitorKills": 0, "inhibitorTakedowns": 1, "inhibitorsLost": 1, "item0": 3153, "item1": 3036, "item2": 3144, "item3": 3006, "item4": 6672, "item5": 1053, "item6": 0, "itemsPurchased": 17, "killingSprees": 3, "kills": 12, "lane": "TOP", "largestCriticalStrike": 469, "largestKillingSpree": 4, "largestMultiKill": 2, "longestTimeSpentLiving": 274, "magicDamageDealt": 1687, "magicDamageDealtToChampions": 1576, "magicDamageTaken": 6597, "missions": {"playerScore0": 0, "playerScore1": 0, "playerScore2": 0, "playerScore3": 0, "playerScore4": 0, "playerScore5": 0, "playerScore6": 0, "playerScore7": 0, "playerScore8": 0, "playerScore9": 0, "playerScore10": 0, "playerScore11": 0}, "needVisionPings": 0, "neutralMinionsKilled": 0, "nexusKills": 0, "nexusLost": 0, "nexusTakedowns": 0, "objectivesStolen": 0, "objectivesStolenAssists": 0, "onMyWayPings": 0, "participantId": 1, "pentaKills": 0, "perks": {"statPerks": {"defense": 5001, "flex": 5008, "offense": 5005}, "styles": [{"description": "primaryStyle", "selections": [{"perk": 8008, "var1": 1269, "var2": 1269, "var3": 0}, {"perk": 8009, "var1": 2400, "var2": 0, "var3": 0}, {"perk": 9103, "var1": 6, "var2": 20, "var3": 0}, {"perk": 8014, "var1": 1923, "var2": 0, "var3": 0}], "style": 8000}, {"description": "subStyle", "selections": [{"perk": 8139, "var1": 1356, "var2": 0, "var3": 0}, {"perk": 8140, "var1": 18, "var2": 0, "var3": 0}], "style": 8100}]}, "physicalDamageDealt": 96382, "physicalDamageDealtToChampions": 54610, "physicalDamageTaken": 21525, "placement": 0, "playerAugment1": 0, "playerAugment2": 0, "playerAugment3": 0, "playerAugment4": 0, "playerAugment5": 0, "playerAugment6": 0, "playerSubteamId": 0, "profileIcon": 5953, "pushPings": 0, "puuid": "jvm-IlRENUlgRW0ipxlMAtWqJQmr55n0qz5UwUeaJUq65KuNlbGwWUMuONGbi8ZRnqBIulGN0kBTEQ", "quadraKills": 0, "retreatPings": 0, "riotIdGameName": "mlkati", "riotIdTagline": "EUW", "role": "SUPPORT", "sightWardsBoughtInGame": 0, "spell1Casts": 52, "spell2Casts": 175, "spell3Casts": 0, "spell4Casts": 6, "subteamPlacement": 0, "summoner1Casts": 5, "summoner1Id": 21, "summoner2Casts": 6, "summoner2Id": 4, "summonerId": "oYvJUJSJrhr20zQX_SqbTxwHoxNo59affmot8ZGWSph-XP0", "summonerLevel": 623, "summonerName": "", "teamEarlySurrendered": false, "teamId": 100, "teamPosition": "", "timeCCingOthers": 27, "timePlayed": 1415, "totalAllyJungleMinionsKilled": 0, "totalDamageDealt": 99472, "totalDamageDealtToChampions": 57588, "totalDamageShieldedOnTeammates": 0, "totalDamageTaken": 29396, "totalEnemyJungleMinionsKilled": 0, "totalHeal": 9818, "totalHealsOnTeammates": 0, "totalMinionsKilled": 52, "totalTimeCCDealt": 194, "totalTimeSpentDead": 267, "totalUnitsHealed": 1, "tripleKills": 0, "trueDamageDealt": 1401, "trueDamageDealtToChampions": 1401, "trueDamageTaken": 1273, "turretKills": 1, "turretTakedowns": 2, "turretsLost": 2, "unrealKills": 0, "visionClearedPings": 0, "visionScore": 0, "visionWardsBoughtInGame": 0, "wardsKilled": 0, "wardsPlaced": 0, "win": true}, {"PlayerScore0": 0, "PlayerScore1": 0, "PlayerScore10": 0, "PlayerScore11": 0, "PlayerScore2": 0, "PlayerScore3": 0, "PlayerScore4": 0, "PlayerScore5": 0, "PlayerScore6": 0, "PlayerScore7": 0, "PlayerScore8": 0, "PlayerScore9": 0, "allInPings": 0, "assistMePings": 0, "assists": 40, "baronKills": 0, "basicPings": 0, "challenges": {"12AssistStreakCount": 0, "HealFromMapSources": 1544.4630165100098, "InfernalScalePickup": 0, "SWARM_DefeatAatrox": 0, "SWARM_DefeatBriar": 0, "SWARM_DefeatMiniBosses": 0, "SWARM_EvolveWeapon": 0, "SWARM_Have3Passives": 0, "SWARM_KillEnemy": 0, "SWARM_PickupGold": 0, "SWARM_ReachLevel50": 0, "SWARM_Survive15Min": 0, "SWARM_WinWith5EvolvedWeapons": 0, "abilityUses": 205, "acesBefore15Minutes": 1, "alliedJungleMonsterKills": 0, "baronTakedowns": 0, "blastConeOppositeOpponentCount": 0, "bountyGold": 306.9281005859375, "buffsStolen": 0, "completeSupportQuestInTime": 0, "controlWardsPlaced": 0, "damagePerMinute": 1214.3063458714187, "damageTakenOnTeamPercentage": 0.15834115921851608, "dancedWithRiftHerald": 0, "deathsByEnemyChamps": 11, "dodgeSkillShotsSmallWindow": 0, "doubleAces": 0, "dragonTakedowns": 0, "effectiveHealAndShielding": 4418.70263671875, "elderDragonKillsWithOpposingSoul": 0, "elderDragonMultikills": 0, "enemyChampionImmobilizations": 14, "enemyJungleMonsterKills": 0, "epicMonsterKillsNearEnemyJungler": 0, "epicMonsterKillsWithin30SecondsOfSpawn": 0, "epicMonsterSteals": 0, "epicMonsterStolenWithoutSmite": 0, "firstTurretKilled": 1, "firstTurretKilledTime": 400.257850964, "fistBumpParticipation": 0, "flawlessAces": 1, "fullTeamTakedown": 18, "gameLength": 1416.0476315110002, "getTakedownsInAllLanesEarlyJungleAsLaner": 0, "goldPerMinute": 624.4252514966557, "hadOpenNexus": 0, "immobilizeAndKillWithAlly": 5, "initialBuffCount": 0, "initialCrabCount": 0, "jungleCsBefore10Minutes": 0, "junglerTakedownsNearDamagedEpicMonster": 0, "kTurretsDestroyedBeforePlatesFall": 2, "kda": 4.454545454545454, "killAfterHiddenWithAlly": 6, "killParticipation": 0.8032786885245902, "killedChampTookFullTeamDamageSurvived": 0, "killingSprees": 1, "killsNearEnemyTurret": 2, "killsOnOtherLanesEarlyJungleAsLaner": 0, "killsOnRecentlyHealedByAramPack": 0, "killsUnderOwnTurret": 5, "killsWithHelpFromEpicMonster": 0, "knockEnemyIntoTeamAndKill": 0, "landSkillShotsEarlyGame": 6, "laneMinionsFirst10Minutes": 1, "legendaryCount": 0, "legendaryItemUsed": [3118, 6655, 4645, 4646], "lostAnInhibitor": 1, "maxKillDeficit": 7, "mejaisFullStackInTime": 0, "moreEnemyJungleThanOpponent": 0, "multiKillOneSpell": 0, "multiTurretRiftHeraldCount": 0, "multikills": 0, "multikillsAfterAggressiveFlash": 0, "outerTurretExecutesBefore10Minutes": 0, "outnumberedKills": 0, "outnumberedNexusKill": 0, "perfectDragonSoulsTaken": 0, "perfectGame": 0, "pickKillWithAlly": 37, "poroExplosions": 6, "quickCleanse": 0, "quickFirstTurret": 1, "quickSoloKills": 0, "riftHeraldTakedowns": 0, "saveAllyFromDeath": 0, "scuttleCrabKills": 0, "shortestTimeToAceFromFirstTakedown": 18.820033285000022, "skillshotsDodged": 28, "skillshotsHit": 56, "snowballsHit": 0, "soloBaronKills": 0, "soloKills": 1, "stealthWardsPlaced": 0, "survivedSingleDigitHpCount": 0, "survivedThreeImmobilizesInFight": 2, "takedownOnFirstTurret": 1, "takedowns": 49, "takedownsAfterGainingLevelAdvantage": 0, "takedownsBeforeJungleMinionSpawn": 3, "takedownsFirstXMinutes": 37, "takedownsInAlcove": 0, "takedownsInEnemyFountain": 0, "teamBaronKills": 0, "teamDamagePercentage": 0.11346812391478205, "teamElderDragonKills": 0, "teamRiftHeraldKills": 0, "tookLargeDamageSurvived": 0, "turretPlatesTaken": 0, "turretTakedowns": 2, "turretsTakenWithRiftHerald": 0, "twentyMinionsIn3SecondsCount": 0, "twoWardsOneSweeperCount": 0, "unseenRecalls": 0, "visionScorePerMinute": 0, "voidMonsterKill": 0, "wardTakedowns": 0, "wardTakedownsBefore20M": 0, "wardsGuarded": 0}, "champExperience": 22369, "champLevel": 18, "championId": 43, "championName": "Karma", "championTransform": 0, "commandPings": 0, "consumablesPurchased": 0, "damageDealtToBuildings": 889, "damageDealtToObjectives": 889, "damageDealtToTurrets": 889, "damageSelfMitigated": 24895, "dangerPings": 0, "deaths": 11, "detectorWardsPlaced": 0, "doubleKills": 0, "dragonKills": 0, "eligibleForProgression": true, "enemyMissingPings": 0, "enemyVisionPings": 0, "firstBloodAssist": true, "firstBloodKill": false, "firstTowerAssist": false, "firstTowerKill": true, "gameEndedInEarlySurrender": false, "gameEndedInSurrender": true, "getBackPings": 0, "goldEarned": 14736, "goldSpent": 13100, "holdPings": 0, "individualPosition": "Invalid", "inhibitorKills": 1, "inhibitorTakedowns": 1, "inhibitorsLost": 1, "item0": 3118, "item1": 4646, "item2": 3020, "item3": 6655, "item4": 4645, "item5": 1052, "item6": 2052, "itemsPurchased": 16, "killingSprees": 1, "kills": 9, "lane": "BOTTOM", "largestCriticalStrike": 0, "largestKillingSpree": 3, "largestMultiKill": 1, "longestTimeSpentLiving": 153, "magicDamageDealt": 36521, "magicDamageDealtToChampions": 25355, "magicDamageTaken": 6359, "missions": {"playerScore0": 0, "playerScore1": 0, "playerScore2": 0, "playerScore3": 0, "playerScore4": 0, "playerScore5": 0, "playerScore6": 0, "playerScore7": 0, "playerScore8": 0, "playerScore9": 0, "playerScore10": 0, "playerScore11": 0}, "needVisionPings": 0, "neutralMinionsKilled": 0, "nexusKills": 0, "nexusLost": 0, "nexusTakedowns": 0, "objectivesStolen": 0, "objectivesStolenAssists": 0, "onMyWayPings": 0, "participantId": 2, "pentaKills": 0, "perks": {"statPerks": {"defense": 5001, "flex": 5008, "offense": 5008}, "styles": [{"description": "primaryStyle", "selections": [{"perk": 8128, "var1": 2648, "var2": 32, "var3": 0}, {"perk": 8126, "var1": 1432, "var2": 0, "var3": 0}, {"perk": 8140, "var1": 18, "var2": 0, "var3": 0}, {"perk": 8106, "var1": 5, "var2": 31, "var3": 0}], "style": 8100}, {"description": "subStyle", "selections": [{"perk": 8014, "var1": 944, "var2": 0, "var3": 0}, {"perk": 8009, "var1": 5103, "var2": 0, "var3": 0}], "style": 8000}]}, "physicalDamageDealt": 3184, "physicalDamageDealtToChampions": 1153, "physicalDamageTaken": 19869, "placement": 0, "playerAugment1": 0, "playerAugment2": 0, "playerAugment3": 0, "playerAugment4": 0, "playerAugment5": 0, "playerAugment6": 0, "playerSubteamId": 0, "profileIcon": 6868, "pushPings": 0, "puuid": "D183BhYdbK4K68t8CF5NO6TLr2r3IhIK0hSih62NJf78Ilnp-Qs1-fwr7rdX89fDhgXfhXwv65K4BQ", "quadraKills": 0, "retreatPings": 0, "riotIdGameName": "BardMitzvah", "riotIdTagline": "4545", "role": "SOLO", "sightWardsBoughtInGame": 0, "spell1Casts": 72, "spell2Casts": 36, "spell3Casts": 56, "spell4Casts": 41, "subteamPlacement": 0, "summoner1Casts": 7, "summoner1Id": 4, "summoner2Casts": 8, "summoner2Id": 3, "summonerId": "uVO4aQmXmDCSaKqxVZEeOLEKEAXl4NdhmVdI4wwOHuY5qj0", "summonerLevel": 364, "summonerName": "", "teamEarlySurrendered": false, "teamId": 100, "teamPosition": "", "timeCCingOthers": 30, "timePlayed": 1415, "totalAllyJungleMinionsKilled": 0, "totalDamageDealt": 41856, "totalDamageDealtToChampions": 28658, "totalDamageShieldedOnTeammates": 4418, "totalDamageTaken": 27450, "totalEnemyJungleMinionsKilled": 0, "totalHeal": 1662, "totalHealsOnTeammates": 0, "totalMinionsKilled": 9, "totalTimeCCDealt": 130, "totalTimeSpentDead": 313, "totalUnitsHealed": 1, "tripleKills": 0, "trueDamageDealt": 2149, "trueDamageDealtToChampions": 2149, "trueDamageTaken": 1221, "turretKills": 1, "turretTakedowns": 2, "turretsLost": 2, "unrealKills": 0, "visionClearedPings": 0, "visionScore": 0, "visionWardsBoughtInGame": 0, "wardsKilled": 0, "wardsPlaced": 0, "win": true}, {"PlayerScore0": 0, "PlayerScore1": 0, "PlayerScore10": 0, "PlayerScore11": 0, "PlayerScore2": 0, "PlayerScore3": 0, "PlayerScore4": 0, "PlayerScore5": 0, "PlayerScore6": 0, "PlayerScore7": 0, "PlayerScore8": 0, "PlayerScore9": 0, "allInPings": 0, "assistMePings": 0, "assists": 35, "baronKills": 0, "basicPings": 0, "challenges": {"12AssistStreakCount": 0, "HealFromMapSources": 1973.4187355041504, "InfernalScalePickup": 0, "SWARM_DefeatAatrox": 0, "SWARM_DefeatBriar": 0, "SWARM_DefeatMiniBosses": 0, "SWARM_EvolveWeapon": 0, "SWARM_Have3Passives": 0, "SWARM_KillEnemy": 0, "SWARM_PickupGold": 0, "SWARM_ReachLevel50": 0, "SWARM_Survive15Min": 0, "SWARM_WinWith5EvolvedWeapons": 0, "abilityUses": 360, "acesBefore15Minutes": 1, "alliedJungleMonsterKills": 0, "baronTakedowns": 0, "blastConeOppositeOpponentCount": 0, "bountyGold": 852.3838348388672, "buffsStolen": 0, "completeSupportQuestInTime": 0, "controlWardsPlaced": 0, "damagePerMinute": 3044.031939907605, "damageTakenOnTeamPercentage": 0.18605781071522487, "dancedWithRiftHerald": 0, "deathsByEnemyChamps": 12, "dodgeSkillShotsSmallWindow": 0, "doubleAces": 0, "dragonTakedowns": 0, "effectiveHealAndShielding": 0, "elderDragonKillsWithOpposingSoul": 0, "elderDragonMultikills": 0, "enemyChampionImmobilizations": 87, "enemyJungleMonsterKills": 0, "epicMonsterKillsNearEnemyJungler": 0, "epicMonsterKillsWithin30SecondsOfSpawn": 0, "epicMonsterSteals": 0, "epicMonsterStolenWithoutSmite": 0, "firstTurretKilled": 1, "firstTurretKilledTime": 400.257850964, "fistBumpParticipation": 0, "flawlessAces": 1, "fullTeamTakedown": 18, "gameLength": 1416.0476315110002, "getTakedownsInAllLanesEarlyJungleAsLaner": 0, "goldPerMinute": 786.2124635504194, "hadOpenNexus": 0, "highestCrowdControlScore": 1, "immobilizeAndKillWithAlly": 19, "initialBuffCount": 0, "initialCrabCount": 0, "jungleCsBefore10Minutes": 0, "junglerTakedownsNearDamagedEpicMonster": 0, "kTurretsDestroyedBeforePlatesFall": 2, "kda": 4.083333333333333, "killAfterHiddenWithAlly": 1, "killParticipation": 0.8032786885245902, "killedChampTookFullTeamDamageSurvived": 0, "killingSprees": 3, "killsNearEnemyTurret": 0, "killsOnOtherLanesEarlyJungleAsLaner": 0, "killsOnRecentlyHealedByAramPack": 0, "killsUnderOwnTurret": 11, "killsWithHelpFromEpicMonster": 0, "knockEnemyIntoTeamAndKill": 19, "landSkillShotsEarlyGame": 136, "laneMinionsFirst10Minutes": 19, "legendaryCount": 0, "legendaryItemUsed": [6653, 3116, 3003, 3040, 8010, 3089], "lostAnInhibitor": 1, "maxKillDeficit": 7, "mejaisFullStackInTime": 0, "moreEnemyJungleThanOpponent": 0, "multiKillOneSpell": 0, "multiTurretRiftHeraldCount": 0, "multikills": 5, "multikillsAfterAggressiveFlash": 0, "outerTurretExecutesBefore10Minutes": 0, "outnumberedKills": 3, "outnumberedNexusKill": 0, "perfectDragonSoulsTaken": 0, "perfectGame": 0, "pickKillWithAlly": 39, "poroExplosions": 6, "quickCleanse": 0, "quickFirstTurret": 1, "quickSoloKills": 0, "riftHeraldTakedowns": 0, "saveAllyFromDeath": 0, "scuttleCrabKills": 0, "shortestTimeToAceFromFirstTakedown": 18.820033285000022, "skillshotsDodged": 30, "skillshotsHit": 565, "snowballsHit": 0, "soloBaronKills": 0, "soloKills": 1, "stealthWardsPlaced": 0, "survivedSingleDigitHpCount": 0, "survivedThreeImmobilizesInFight": 3, "takedownOnFirstTurret": 0, "takedowns": 49, "takedownsAfterGainingLevelAdvantage": 1, "takedownsBeforeJungleMinionSpawn": 2, "takedownsFirstXMinutes": 36, "takedownsInAlcove": 0, "takedownsInEnemyFountain": 0, "teamBaronKills": 0, "teamDamagePercentage": 0.28444271458543835, "teamElderDragonKills": 0, "teamRiftHeraldKills": 0, "tookLargeDamageSurvived": 0, "turretPlatesTaken": 0, "turretTakedowns": 2, "turretsTakenWithRiftHerald": 0, "twentyMinionsIn3SecondsCount": 0, "twoWardsOneSweeperCount": 0, "unseenRecalls": 0, "visionScorePerMinute": 0, "voidMonsterKill": 0, "wardTakedowns": 0, "wardTakedownsBefore20M": 0, "wardsGuarded": 0}, "champExperience": 24087, "champLevel": 18, "championId": 163, "championName": "Taliyah", "championTransform": 0, "commandPings": 0, "consumablesPurchased": 0, "damageDealtToBuildings": 1164, "damageDealtToObjectives": 1164, "damageDealtToTurrets": 1164, "damageSelfMitigated": 20602, "dangerPings": 0, "deaths": 12, "detectorWardsPlaced": 0, "doubleKills": 3, "dragonKills": 0, "eligibleForProgression": true, "enemyMissingPings": 0, "enemyVisionPings": 0, "firstBloodAssist": true, "firstBloodKill": false, "firstTowerAssist": true, "firstTowerKill": false, "gameEndedInEarlySurrender": false, "gameEndedInSurrender": true, "getBackPings": 0, "goldEarned": 18555, "goldSpent": 17450, "holdPings": 0, "individualPosition": "Invalid", "inhibitorKills": 0, "inhibitorTakedowns": 0, "inhibitorsLost": 1, "item0": 3040, "item1": 6653, "item2": 3116, "item3": 3158, "item4": 8010, "item5": 3089, "item6": 2052, "itemsPurchased": 20, "killingSprees": 3, "kills": 14, "lane": "TOP", "largestCriticalStrike": 0, "largestKillingSpree": 4, "largestMultiKill": 4, "longestTimeSpentLiving": 193, "magicDamageDealt": 103932, "magicDamageDealtToChampions": 67269, "magicDamageTaken": 9764, "missions": {"playerScore0": 0, "playerScore1": 0, "playerScore2": 0, "playerScore3": 0, "playerScore4": 0, "playerScore5": 0, "playerScore6": 0, "playerScore7": 0, "playerScore8": 0, "playerScore9": 0, "playerScore10": 0, "playerScore11": 0}, "needVisionPings": 0, "neutralMinionsKilled": 0, "nexusKills": 0, "nexusLost": 0, "nexusTakedowns": 0, "objectivesStolen": 0, "objectivesStolenAssists": 0, "onMyWayPings": 0, "participantId": 3, "pentaKills": 0, "perks": {"statPerks": {"defense": 5001, "flex": 5008, "offense": 5005}, "styles": [{"description": "primaryStyle", "selections": [{"perk": 8369, "var1": 1762, "var2": 1512, "var3": 0}, {"perk": 8304, "var1": 4, "var2": 3, "var3": 0}, {"perk": 8345, "var1": 3, "var2": 0, "var3": 206}, {"perk": 8347, "var1": 0, "var2": 0, "var3": 0}], "style": 8300}, {"description": "subStyle", "selections": [{"perk": 8226, "var1": 250, "var2": 1770, "var3": 0}, {"perk": 8210, "var1": 26, "var2": 0, "var3": 0}], "style": 8200}]}, "physicalDamageDealt": 2263, "physicalDamageDealtToChampions": 996, "physicalDamageTaken": 19797, "placement": 0, "playerAugment1": 0, "playerAugment2": 0, "playerAugment3": 0, "playerAugment4": 0, "playerAugment5": 0, "playerAugment6": 0, "playerSubteamId": 0, "profileIcon": 4555, "pushPings": 0, "puuid": "noItxThf9QlTIggMRqxcVJxCwsDCDm6mfZ4lNcFulm4LMTS5AhagGhgqiHiEWKI7RQspHenaST3Sdg", "quadraKills": 1, "retreatPings": 0, "riotIdGameName": "unitato", "riotIdTagline": "6294", "role": "SUPPORT", "sightWardsBoughtInGame": 0, "spell1Casts": 223, "spell2Casts": 47, "spell3Casts": 77, "spell4Casts": 13, "subteamPlacement": 0, "summoner1Casts": 7, "summoner1Id": 4, "summoner2Casts": 7, "summoner2Id": 3, "summonerId": "tQG2POI2N0JMfbiSJtMEQ1GdlmstAIGjkQYbhrWP7W0NZJn4KU2JnArYUg", "summonerLevel": 461, "summonerName": "", "teamEarlySurrendered": false, "teamId": 100, "teamPosition": "", "timeCCingOthers": 119, "timePlayed": 1415, "totalAllyJungleMinionsKilled": 0, "totalDamageDealt": 109771, "totalDamageDealtToChampions": 71841, "totalDamageShieldedOnTeammates": 0, "totalDamageTaken": 32255, "totalEnemyJungleMinionsKilled": 0, "totalHeal": 1964, "totalHealsOnTeammates": 0, "totalMinionsKilled": 44, "totalTimeCCDealt": 864, "totalTimeSpentDead": 312, "totalUnitsHealed": 1, "tripleKills": 1, "trueDamageDealt": 3575, "trueDamageDealtToChampions": 3575, "trueDamageTaken": 2693, "turretKills": 0, "turretTakedowns": 2, "turretsLost": 2, "unrealKills": 0, "visionClearedPings": 0, "visionScore": 0, "visionWardsBoughtInGame": 0, "wardsKilled": 0, "wardsPlaced": 0, "win": true}, {"PlayerScore0": 0, "PlayerScore1": 0, "PlayerScore10": 0, "PlayerScore11": 0, "PlayerScore2": 0, "PlayerScore3": 0, "PlayerScore4": 0, "PlayerScore5": 0, "PlayerScore6": 0, "PlayerScore7": 0, "PlayerScore8": 0, "PlayerScore9": 0, "allInPings": 0, "assistMePings": 0, "assists": 27, "baronKills": 0, "basicPings": 0, "challenges": {"12AssistStreakCount": 1, "HealFromMapSources": 204.32088661193848, "InfernalScalePickup": 0, "SWARM_DefeatAatrox": 0, "SWARM_DefeatBriar": 0, "SWARM_DefeatMiniBosses": 0, "SWARM_EvolveWeapon": 0, "SWARM_Have3Passives": 0, "SWARM_KillEnemy": 0, "SWARM_PickupGold": 0, "SWARM_ReachLevel50": 0, "SWARM_Survive15Min": 0, "SWARM_WinWith5EvolvedWeapons": 0, "abilityUses": 336, "acesBefore15Minutes": 1, "alliedJungleMonsterKills": 0, "baronTakedowns": 0, "blastConeOppositeOpponentCount": 0, "bountyGold": 0, "buffsStolen": 0, "completeSupportQuestInTime": 0, "controlWardsPlaced": 0, "damagePerMinute": 946.7565037038695, "damageTakenOnTeamPercentage": 0.12085452233266744, "dancedWithRiftHerald": 0, "deathsByEnemyChamps": 10, "dodgeSkillShotsSmallWindow": 0, "doubleAces": 0, "dragonTakedowns": 0, "effectiveHealAndShielding": 0, "elderDragonKillsWithOpposingSoul": 0, "elderDragonMultikills": 0, "enemyChampionImmobilizations": 9, "enemyJungleMonsterKills": 0, "epicMonsterKillsNearEnemyJungler": 0, "epicMonsterKillsWithin30SecondsOfSpawn": 0, "epicMonsterSteals": 0, "epicMonsterStolenWithoutSmite": 0, "firstTurretKilled": 1, "firstTurretKilledTime": 400.257850964, "fistBumpParticipation": 0, "flawlessAces": 1, "fullTeamTakedown": 18, "gameLength": 1416.0476315110002, "getTakedownsInAllLanesEarlyJungleAsLaner": 0, "goldPerMinute": 595.0407708529149, "hadOpenNexus": 0, "immobilizeAndKillWithAlly": 1, "initialBuffCount": 0, "initialCrabCount": 0, "jungleCsBefore10Minutes": 0, "junglerTakedownsNearDamagedEpicMonster": 0, "kTurretsDestroyedBeforePlatesFall": 2, "kda": 3.2, "killAfterHiddenWithAlly": 9, "killParticipation": 0.5245901639344263, "killedChampTookFullTeamDamageSurvived": 0, "killingSprees": 0, "killsNearEnemyTurret": 0, "killsOnOtherLanesEarlyJungleAsLaner": 0, "killsOnRecentlyHealedByAramPack": 0, "killsUnderOwnTurret": 1, "killsWithHelpFromEpicMonster": 0, "knockEnemyIntoTeamAndKill": 0, "landSkillShotsEarlyGame": 0, "laneMinionsFirst10Minutes": 17, "legendaryCount": 0, "legendaryItemUsed": [3003, 3040, 2503, 3116], "lostAnInhibitor": 1, "maxKillDeficit": 7, "mejaisFullStackInTime": 0, "moreEnemyJungleThanOpponent": 0, "multiKillOneSpell": 1, "multiTurretRiftHeraldCount": 0, "multikills": 0, "multikillsAfterAggressiveFlash": 0, "outerTurretExecutesBefore10Minutes": 0, "outnumberedKills": 0, "outnumberedNexusKill": 0, "perfectDragonSoulsTaken": 0, "perfectGame": 0, "pickKillWithAlly": 25, "poroExplosions": 6, "quickCleanse": 0, "quickFirstTurret": 1, "quickSoloKills": 0, "riftHeraldTakedowns": 0, "saveAllyFromDeath": 0, "scuttleCrabKills": 0, "shortestTimeToAceFromFirstTakedown": 18.820033285000022, "skillshotsDodged": 9, "skillshotsHit": 0, "snowballsHit": 0, "soloBaronKills": 0, "soloKills": 0, "stealthWardsPlaced": 0, "survivedSingleDigitHpCount": 0, "survivedThreeImmobilizesInFight": 1, "takedownOnFirstTurret": 0, "takedowns": 32, "takedownsAfterGainingLevelAdvantage": 0, "takedownsBeforeJungleMinionSpawn": 3, "takedownsFirstXMinutes": 21, "takedownsInAlcove": 0, "takedownsInEnemyFountain": 0, "teamBaronKills": 0, "teamDamagePercentage": 0.08846753098560496, "teamElderDragonKills": 0, "teamRiftHeraldKills": 0, "tookLargeDamageSurvived": 0, "turretPlatesTaken": 0, "turretTakedowns": 2, "turretsTakenWithRiftHerald": 0, "twentyMinionsIn3SecondsCount": 0, "twoWardsOneSweeperCount": 0, "unseenRecalls": 0, "visionScorePerMinute": 0, "voidMonsterKill": 0, "wardTakedowns": 0, "wardTakedownsBefore20M": 0, "wardsGuarded": 0}, "champExperience": 22878, "champLevel": 18, "championId": 90, "championName": "Malzahar", "championTransform": 0, "commandPings": 0, "consumablesPurchased": 0, "damageDealtToBuildings": 1231, "damageDealtToObjectives": 1231, "damageDealtToTurrets": 1231, "damageSelfMitigated": 19616, "dangerPings": 0, "deaths": 10, "detectorWardsPlaced": 0, "doubleKills": 0, "dragonKills": 0, "eligibleForProgression": true, "enemyMissingPings": 0, "enemyVisionPings": 0, "firstBloodAssist": true, "firstBloodKill": false, "firstTowerAssist": true, "firstTowerKill": false, "gameEndedInEarlySurrender": false, "gameEndedInSurrender": true, "getBackPings": 0, "goldEarned": 14043, "goldSpent": 11050, "holdPings": 0, "individualPosition": "Invalid", "inhibitorKills": 0, "inhibitorTakedowns": 1, "inhibitorsLost": 1, "item0": 3040, "item1": 3020, "item2": 2503, "item3": 3116, "item4": 3916, "item5": 1026, "item6": 2052, "itemsPurchased": 16, "killingSprees": 2, "kills": 5, "lane": "MIDDLE", "largestCriticalStrike": 0, "largestKillingSpree": 2, "largestMultiKill": 1, "longestTimeSpentLiving": 152, "magicDamageDealt": 47163, "magicDamageDealtToChampions": 19322, "magicDamageTaken": 5746, "missions": {"playerScore0": 0, "playerScore1": 0, "playerScore2": 0, "playerScore3": 0, "playerScore4": 0, "playerScore5": 0, "playerScore6": 0, "playerScore7": 0, "playerScore8": 0, "playerScore9": 0, "playerScore10": 0, "playerScore11": 0}, "needVisionPings": 0, "neutralMinionsKilled": 0, "nexusKills": 0, "nexusLost": 0, "nexusTakedowns": 0, "objectivesStolen": 0, "objectivesStolenAssists": 0, "onMyWayPings": 0, "participantId": 4, "pentaKills": 0, "perks": {"statPerks": {"defense": 5001, "flex": 5008, "offense": 5008}, "styles": [{"description": "primaryStyle", "selections": [{"perk": 8128, "var1": 1790, "var2": 34, "var3": 0}, {"perk": 8126, "var1": 1269, "var2": 0, "var3": 0}, {"perk": 8140, "var1": 18, "var2": 0, "var3": 0}, {"perk": 8106, "var1": 5, "var2": 31, "var3": 0}], "style": 8100}, {"description": "subStyle", "selections": [{"perk": 8014, "var1": 1114, "var2": 0, "var3": 0}, {"perk": 8009, "var1": 4905, "var2": 0, "var3": 0}], "style": 8000}]}, "physicalDamageDealt": 1833, "physicalDamageDealtToChampions": 728, "physicalDamageTaken": 14064, "placement": 0, "playerAugment1": 0, "playerAugment2": 0, "playerAugment3": 0, "playerAugment4": 0, "playerAugment5": 0, "playerAugment6": 0, "playerSubteamId": 0, "profileIcon": 4030, "pushPings": 0, "puuid": "t2KgqlvfVHzwo3NoBMIppPSoHTZw6Hq4E5uVTjICjQotBZZMKs_aHYtPbeKu-o2T1xGFbtvyJD0OXA", "quadraKills": 0, "retreatPings": 0, "riotIdGameName": "saturah", "riotIdTagline": "EUW", "role": "SOLO", "sightWardsBoughtInGame": 0, "spell1Casts": 101, "spell2Casts": 131, "spell3Casts": 95, "spell4Casts": 9, "subteamPlacement": 0, "summoner1Casts": 7, "summoner1Id": 3, "summoner2Casts": 7, "summoner2Id": 4, "summonerId": "C7lDcsGw_KT59GGYqzBEP5xTBsfXu9ugWQnp8jK7X_NDMMQ", "summonerLevel": 187, "summonerName": "", "teamEarlySurrendered": false, "teamId": 100, "teamPosition": "", "timeCCingOthers": 93, "timePlayed": 1415, "totalAllyJungleMinionsKilled": 0, "totalDamageDealt": 51291, "totalDamageDealtToChampions": 22344, "totalDamageShieldedOnTeammates": 0, "totalDamageTaken": 20951, "totalEnemyJungleMinionsKilled": 0, "totalHeal": 202, "totalHealsOnTeammates": 0, "totalMinionsKilled": 50, "totalTimeCCDealt": 417, "totalTimeSpentDead": 256, "totalUnitsHealed": 1, "tripleKills": 0, "trueDamageDealt": 2293, "trueDamageDealtToChampions": 2293, "trueDamageTaken": 1141, "turretKills": 0, "turretTakedowns": 2, "turretsLost": 2, "unrealKills": 0, "visionClearedPings": 0, "visionScore": 0, "visionWardsBoughtInGame": 0, "wardsKilled": 0, "wardsPlaced": 0, "win": true}, {"PlayerScore0": 0, "PlayerScore1": 0, "PlayerScore10": 0, "PlayerScore11": 0, "PlayerScore2": 0, "PlayerScore3": 0, "PlayerScore4": 0, "PlayerScore5": 0, "PlayerScore6": 0, "PlayerScore7": 0, "PlayerScore8": 0, "PlayerScore9": 0, "allInPings": 0, "assistMePings": 1, "assists": 22, "baronKills": 0, "basicPings": 0, "challenges": {"12AssistStreakCount": 0, "HealFromMapSources": 952.1556457579136, "InfernalScalePickup": 0, "SWARM_DefeatAatrox": 0, "SWARM_DefeatBriar": 0, "SWARM_DefeatMiniBosses": 0, "SWARM_EvolveWeapon": 0, "SWARM_Have3Passives": 0, "SWARM_KillEnemy": 0, "SWARM_PickupGold": 0, "SWARM_ReachLevel50": 0, "SWARM_Survive15Min": 0, "SWARM_WinWith5EvolvedWeapons": 0, "abilityUses": 220, "acesBefore15Minutes": 1, "alliedJungleMonsterKills": 0, "baronTakedowns": 0, "blastConeOppositeOpponentCount": 0, "bountyGold": 446.516357421875, "buffsStolen": 0, "completeSupportQuestInTime": 0, "controlWardsPlaced": 0, "damagePerMinute": 3056.5245678788297, "damageTakenOnTeamPercentage": 0.3651830646511493, "dancedWithRiftHerald": 0, "deathsByEnemyChamps": 12, "dodgeSkillShotsSmallWindow": 0, "doubleAces": 0, "dragonTakedowns": 0, "effectiveHealAndShielding": 0, "elderDragonKillsWithOpposingSoul": 0, "elderDragonMultikills": 0, "enemyChampionImmobilizations": 0, "enemyJungleMonsterKills": 0, "epicMonsterKillsNearEnemyJungler": 0, "epicMonsterKillsWithin30SecondsOfSpawn": 0, "epicMonsterSteals": 0, "epicMonsterStolenWithoutSmite": 0, "firstTurretKilled": 1, "firstTurretKilledTime": 400.257850964, "fistBumpParticipation": 0, "flawlessAces": 1, "fullTeamTakedown": 18, "gameLength": 1416.0476315110002, "getTakedownsInAllLanesEarlyJungleAsLaner": 0, "goldPerMinute": 791.3655608669367, "hadOpenNexus": 0, "highestChampionDamage": 1, "immobilizeAndKillWithAlly": 0, "initialBuffCount": 0, "initialCrabCount": 0, "jungleCsBefore10Minutes": 0, "junglerTakedownsNearDamagedEpicMonster": 0, "kTurretsDestroyedBeforePlatesFall": 1, "kda": 3.3076923076923075, "killAfterHiddenWithAlly": 12, "killParticipation": 0.7049180327868853, "killedChampTookFullTeamDamageSurvived": 0, "killingSprees": 3, "killsNearEnemyTurret": 7, "killsOnOtherLanesEarlyJungleAsLaner": 0, "killsOnRecentlyHealedByAramPack": 0, "killsUnderOwnTurret": 2, "killsWithHelpFromEpicMonster": 0, "knockEnemyIntoTeamAndKill": 0, "landSkillShotsEarlyGame": 32, "laneMinionsFirst10Minutes": 43, "legendaryCount": 0, "legendaryItemUsed": [6610, 6631, 3073, 3073, 3053, 3075], "lostAnInhibitor": 1, "maxKillDeficit": 7, "mejaisFullStackInTime": 0, "moreEnemyJungleThanOpponent": 0, "multiKillOneSpell": 0, "multiTurretRiftHeraldCount": 0, "multikills": 5, "multikillsAfterAggressiveFlash": 3, "outerTurretExecutesBefore10Minutes": 1, "outnumberedKills": 5, "outnumberedNexusKill": 0, "perfectDragonSoulsTaken": 0, "perfectGame": 0, "pickKillWithAlly": 32, "poroExplosions": 6, "quickCleanse": 0, "quickFirstTurret": 1, "quickSoloKills": 0, "riftHeraldTakedowns": 0, "saveAllyFromDeath": 0, "scuttleCrabKills": 0, "shortestTimeToAceFromFirstTakedown": 18.820033285000022, "skillshotsDodged": 24, "skillshotsHit": 78, "snowballsHit": 0, "soloBaronKills": 0, "soloKills": 3, "stealthWardsPlaced": 0, "survivedSingleDigitHpCount": 0, "survivedThreeImmobilizesInFight": 8, "takedownOnFirstTurret": 0, "takedowns": 43, "takedownsAfterGainingLevelAdvantage": 0, "takedownsBeforeJungleMinionSpawn": 3, "takedownsFirstXMinutes": 28, "takedownsInAlcove": 0, "takedownsInEnemyFountain": 0, "teamBaronKills": 0, "teamDamagePercentage": 0.2856100600938264, "teamElderDragonKills": 0, "teamRiftHeraldKills": 0, "tookLargeDamageSurvived": 1, "turretPlatesTaken": 0, "turretTakedowns": 3, "turretsTakenWithRiftHerald": 0, "twentyMinionsIn3SecondsCount": 0, "twoWardsOneSweeperCount": 0, "unseenRecalls": 0, "visionScorePerMinute": 0, "voidMonsterKill": 0, "wardTakedowns": 0, "wardTakedownsBefore20M": 0, "wardsGuarded": 0}, "champExperience": 24528, "champLevel": 18, "championId": 2, "championName": "Olaf", "championTransform": 0, "commandPings": 0, "consumablesPurchased": 1, "damageDealtToBuildings": 5502, "damageDealtToObjectives": 5502, "damageDealtToTurrets": 5502, "damageSelfMitigated": 79266, "dangerPings": 0, "deaths": 13, "detectorWardsPlaced": 0, "doubleKills": 4, "dragonKills": 0, "eligibleForProgression": true, "enemyMissingPings": 0, "enemyVisionPings": 0, "firstBloodAssist": false, "firstBloodKill": true, "firstTowerAssist": true, "firstTowerKill": false, "gameEndedInEarlySurrender": false, "gameEndedInSurrender": true, "getBackPings": 0, "goldEarned": 18676, "goldSpent": 16450, "holdPings": 0, "individualPosition": "Invalid", "inhibitorKills": 1, "inhibitorTakedowns": 2, "inhibitorsLost": 1, "item0": 6610, "item1": 6631, "item2": 3047, "item3": 3073, "item4": 3053, "item5": 3075, "item6": 2052, "itemsPurchased": 23, "killingSprees": 6, "kills": 21, "lane": "TOP", "largestCriticalStrike": 435, "largestKillingSpree": 6, "largestMultiKill": 3, "longestTimeSpentLiving": 146, "magicDamageDealt": 1558, "magicDamageDealtToChampions": 609, "magicDamageTaken": 19564, "missions": {"playerScore0": 0, "playerScore1": 0, "playerScore2": 0, "playerScore3": 0, "playerScore4": 0, "playerScore5": 0, "playerScore6": 0, "playerScore7": 0, "playerScore8": 0, "playerScore9": 0, "playerScore10": 0, "playerScore11": 0}, "needVisionPings": 0, "neutralMinionsKilled": 0, "nexusKills": 0, "nexusLost": 0, "nexusTakedowns": 0, "objectivesStolen": 0, "objectivesStolenAssists": 0, "onMyWayPings": 0, "participantId": 5, "pentaKills": 0, "perks": {"statPerks": {"defense": 5001, "flex": 5008, "offense": 5007}, "styles": [{"description": "primaryStyle", "selections": [{"perk": 8010, "var1": 3557, "var2": 0, "var3": 0}, {"perk": 9111, "var1": 3074, "var2": 430, "var3": 0}, {"perk": 9104, "var1": 5, "var2": 30, "var3": 0}, {"perk": 8299, "var1": 4065, "var2": 0, "var3": 0}], "style": 8000}, {"description": "subStyle", "selections": [{"perk": 8410, "var1": 192, "var2": 0, "var3": 0}, {"perk": 8304, "var1": 4, "var2": 3, "var3": 0}], "style": 8300}]}, "physicalDamageDealt": 147377, "physicalDamageDealtToChampions": 53563, "physicalDamageTaken": 36850, "placement": 0, "playerAugment1": 0, "playerAugment2": 0, "playerAugment3": 0, "playerAugment4": 0, "playerAugment5": 0, "playerAugment6": 0, "playerSubteamId": 0, "profileIcon": 4030, "pushPings": 0, "puuid": "Mm9VpIbV4XqW1v6C-NsYyEh_Y0l4VKWU1R5vFC8HlPksI5YynSKPzZUFfvCWaXO9_scFMpWWfdYNOA", "quadraKills": 0, "retreatPings": 0, "riotIdGameName": "Curling Captain", "riotIdTagline": "EUW", "role": "DUO", "sightWardsBoughtInGame": 0, "spell1Casts": 90, "spell2Casts": 38, "spell3Casts": 79, "spell4Casts": 13, "subteamPlacement": 0, "summoner1Casts": 7, "summoner1Id": 4, "summoner2Casts": 8, "summoner2Id": 6, "summonerId": "oU6d1m9jIQ8WFtTy1y2Cqdofa7Wmfwe9NDvnhy7pPSDChp0", "summonerLevel": 781, "summonerName": "", "teamEarlySurrendered": false, "teamId": 100, "teamPosition": "", "timeCCingOthers": 25, "timePlayed": 1415, "totalAllyJungleMinionsKilled": 0, "totalDamageDealt": 172817, "totalDamageDealtToChampions": 72136, "totalDamageShieldedOnTeammates": 0, "totalDamageTaken": 63309, "totalEnemyJungleMinionsKilled": 0, "totalHeal": 25362, "totalHealsOnTeammates": 0, "totalMinionsKilled": 118, "totalTimeCCDealt": 368, "totalTimeSpentDead": 362, "totalUnitsHealed": 1, "tripleKills": 1, "trueDamageDealt": 23881, "trueDamageDealtToChampions": 17963, "trueDamageTaken": 6894, "turretKills": 2, "turretTakedowns": 3, "turretsLost": 2, "unrealKills": 0, "visionClearedPings": 0, "visionScore": 0, "visionWardsBoughtInGame": 0, "wardsKilled": 0, "wardsPlaced": 0, "win": true}, {"PlayerScore0": 0, "PlayerScore1": 0, "PlayerScore10": 0, "PlayerScore11": 0, "PlayerScore2": 0, "PlayerScore3": 0, "PlayerScore4": 0, "PlayerScore5": 0, "PlayerScore6": 0, "PlayerScore7": 0, "PlayerScore8": 0, "PlayerScore9": 0, "allInPings": 0, "assistMePings": 0, "assists": 19, "baronKills": 0, "basicPings": 0, "challenges": {"12AssistStreakCount": 0, "HealFromMapSources": 2295.703041434288, "InfernalScalePickup": 0, "SWARM_DefeatAatrox": 0, "SWARM_DefeatBriar": 0, "SWARM_DefeatMiniBosses": 0, "SWARM_EvolveWeapon": 0, "SWARM_Have3Passives": 0, "SWARM_KillEnemy": 0, "SWARM_PickupGold": 0, "SWARM_ReachLevel50": 0, "SWARM_Survive15Min": 0, "SWARM_WinWith5EvolvedWeapons": 0, "abilityUses": 141, "acesBefore15Minutes": 2, "alliedJungleMonsterKills": 0, "baronTakedowns": 0, "blastConeOppositeOpponentCount": 0, "bountyGold": 488.095947265625, "buffsStolen": 0, "completeSupportQuestInTime": 0, "controlWardsPlaced": 0, "damagePerMinute": 873.7984010676889, "damageTakenOnTeamPercentage": 0.19403217911978834, "dancedWithRiftHerald": 0, "deathsByEnemyChamps": 11, "dodgeSkillShotsSmallWindow": 13, "doubleAces": 0, "dragonTakedowns": 0, "effectiveHealAndShielding": 279.99993896484375, "elderDragonKillsWithOpposingSoul": 0, "elderDragonMultikills": 0, "enemyChampionImmobilizations": 72, "enemyJungleMonsterKills": 0, "epicMonsterKillsNearEnemyJungler": 0, "epicMonsterKillsWithin30SecondsOfSpawn": 0, "epicMonsterSteals": 0, "epicMonsterStolenWithoutSmite": 0, "firstTurretKilled": 0, "fistBumpParticipation": 0, "flawlessAces": 3, "fullTeamTakedown": 5, "gameLength": 1416.0476315110002, "getTakedownsInAllLanesEarlyJungleAsLaner": 0, "goldPerMinute": 593.3050307758829, "hadOpenNexus": 0, "immobilizeAndKillWithAlly": 17, "initialBuffCount": 0, "initialCrabCount": 0, "jungleCsBefore10Minutes": 0, "junglerTakedownsNearDamagedEpicMonster": 0, "kTurretsDestroyedBeforePlatesFall": 1, "kda": 2.3636363636363638, "killAfterHiddenWithAlly": 1, "killParticipation": 0.4727272727272727, "killedChampTookFullTeamDamageSurvived": 0, "killingSprees": 2, "killsNearEnemyTurret": 2, "killsOnOtherLanesEarlyJungleAsLaner": 0, "killsOnRecentlyHealedByAramPack": 0, "killsUnderOwnTurret": 0, "killsWithHelpFromEpicMonster": 0, "knockEnemyIntoTeamAndKill": 13, "landSkillShotsEarlyGame": 10, "laneMinionsFirst10Minutes": 5, "legendaryCount": 0, "legendaryItemUsed": [3084, 3084, 3119, 3121, 3083, 3075], "lostAnInhibitor": 0, "maxKillDeficit": 0, "mejaisFullStackInTime": 0, "moreEnemyJungleThanOpponent": 0, "multiKillOneSpell": 0, "multiTurretRiftHeraldCount": 0, "multikills": 2, "multikillsAfterAggressiveFlash": 0, "outerTurretExecutesBefore10Minutes": 0, "outnumberedKills": 4, "outnumberedNexusKill": 0, "perfectDragonSoulsTaken": 0, "perfectGame": 0, "pickKillWithAlly": 20, "poroExplosions": 6, "quickCleanse": 0, "quickFirstTurret": 0, "quickSoloKills": 0, "riftHeraldTakedowns": 0, "saveAllyFromDeath": 0, "scuttleCrabKills": 0, "shortestTimeToAceFromFirstTakedown": 12.960056000000122, "skillshotsDodged": 131, "skillshotsHit": 24, "snowballsHit": 10, "soloBaronKills": 0, "soloKills": 0, "stealthWardsPlaced": 0, "survivedSingleDigitHpCount": 0, "survivedThreeImmobilizesInFight": 0, "takedownOnFirstTurret": 0, "takedowns": 26, "takedownsAfterGainingLevelAdvantage": 1, "takedownsBeforeJungleMinionSpawn": 1, "takedownsFirstXMinutes": 17, "takedownsInAlcove": 0, "takedownsInEnemyFountain": 0, "teamBaronKills": 0, "teamDamagePercentage": 0.12262441270154913, "teamElderDragonKills": 0, "teamRiftHeraldKills": 0, "tookLargeDamageSurvived": 0, "turretPlatesTaken": 0, "turretTakedowns": 2, "turretsTakenWithRiftHerald": 0, "twentyMinionsIn3SecondsCount": 0, "twoWardsOneSweeperCount": 0, "unseenRecalls": 0, "visionScorePerMinute": 0, "voidMonsterKill": 0, "wardTakedowns": 0, "wardTakedownsBefore20M": 0, "wardsGuarded": 0}, "champExperience": 21528, "champLevel": 18, "championId": 53, "championName": "Blitzcrank", "championTransform": 0, "commandPings": 3, "consumablesPurchased": 0, "damageDealtToBuildings": 523, "damageDealtToObjectives": 523, "damageDealtToTurrets": 523, "damageSelfMitigated": 56556, "dangerPings": 0, "deaths": 11, "detectorWardsPlaced": 0, "doubleKills": 1, "dragonKills": 0, "eligibleForProgression": true, "enemyMissingPings": 1, "enemyVisionPings": 0, "firstBloodAssist": false, "firstBloodKill": false, "firstTowerAssist": false, "firstTowerKill": false, "gameEndedInEarlySurrender": false, "gameEndedInSurrender": true, "getBackPings": 0, "goldEarned": 14002, "goldSpent": 12200, "holdPings": 0, "individualPosition": "Invalid", "inhibitorKills": 0, "inhibitorTakedowns": 1, "inhibitorsLost": 2, "item0": 3084, "item1": 3121, "item2": 3111, "item3": 3083, "item4": 3075, "item5": 0, "item6": 2052, "itemsPurchased": 20, "killingSprees": 2, "kills": 7, "lane": "MIDDLE", "largestCriticalStrike": 6, "largestKillingSpree": 3, "largestMultiKill": 3, "longestTimeSpentLiving": 270, "magicDamageDealt": 25695, "magicDamageDealtToChampions": 12793, "magicDamageTaken": 21749, "missions": {"playerScore0": 0, "playerScore1": 0, "playerScore2": 0, "playerScore3": 0, "playerScore4": 0, "playerScore5": 0, "playerScore6": 0, "playerScore7": 0, "playerScore8": 0, "playerScore9": 0, "playerScore10": 0, "playerScore11": 0}, "needVisionPings": 0, "neutralMinionsKilled": 0, "nexusKills": 0, "nexusLost": 1, "nexusTakedowns": 0, "objectivesStolen": 0, "objectivesStolenAssists": 0, "onMyWayPings": 0, "participantId": 6, "pentaKills": 0, "perks": {"statPerks": {"defense": 5001, "flex": 5001, "offense": 5007}, "styles": [{"description": "primaryStyle", "selections": [{"perk": 8439, "var1": 1642, "var2": 3433, "var3": 0}, {"perk": 8463, "var1": 1387, "var2": 0, "var3": 0}, {"perk": 8429, "var1": 66, "var2": 14, "var3": 11}, {"perk": 8451, "var1": 450, "var2": 0, "var3": 0}], "style": 8400}, {"description": "subStyle", "selections": [{"perk": 8009, "var1": 3064, "var2": 0, "var3": 0}, {"perk": 9105, "var1": 5, "var2": 40, "var3": 0}], "style": 8000}]}, "physicalDamageDealt": 12388, "physicalDamageDealtToChampions": 6993, "physicalDamageTaken": 30331, "placement": 0, "playerAugment1": 0, "playerAugment2": 0, "playerAugment3": 0, "playerAugment4": 0, "playerAugment5": 0, "playerAugment6": 0, "playerSubteamId": 0, "profileIcon": 3175, "pushPings": 0, "puuid": "Tx82aBZJRl12ZyCHpg-TLaLgcacTA1o5Q9T0EvZEIINZAJcwuA0Y5aUsvDoddqiF0JYOgp-Ms_6ddg", "quadraKills": 0, "retreatPings": 0, "riotIdGameName": "Jeymid", "riotIdTagline": "EUW", "role": "SUPPORT", "sightWardsBoughtInGame": 0, "spell1Casts": 38, "spell2Casts": 37, "spell3Casts": 48, "spell4Casts": 18, "subteamPlacement": 0, "summoner1Casts": 6, "summoner1Id": 4, "summoner2Casts": 27, "summoner2Id": 32, "summonerId": "xRIVg7s8aOfTTk2B5-3j0zOLBT-ulWotzHhhfZPdCI-Aw2c", "summonerLevel": 455, "summonerName": "", "teamEarlySurrendered": false, "teamId": 200, "teamPosition": "", "timeCCingOthers": 52, "timePlayed": 1415, "totalAllyJungleMinionsKilled": 0, "totalDamageDealt": 39319, "totalDamageDealtToChampions": 20622, "totalDamageShieldedOnTeammates": 0, "totalDamageTaken": 56701, "totalEnemyJungleMinionsKilled": 0, "totalHeal": 3187, "totalHealsOnTeammates": 279, "totalMinionsKilled": 13, "totalTimeCCDealt": 154, "totalTimeSpentDead": 239, "totalUnitsHealed": 5, "tripleKills": 1, "trueDamageDealt": 1235, "trueDamageDealtToChampions": 835, "trueDamageTaken": 4620, "turretKills": 1, "turretTakedowns": 2, "turretsLost": 4, "unrealKills": 0, "visionClearedPings": 0, "visionScore": 0, "visionWardsBoughtInGame": 0, "wardsKilled": 0, "wardsPlaced": 0, "win": false}, {"PlayerScore0": 0, "PlayerScore1": 0, "PlayerScore10": 0, "PlayerScore11": 0, "PlayerScore2": 0, "PlayerScore3": 0, "PlayerScore4": 0, "PlayerScore5": 0, "PlayerScore6": 0, "PlayerScore7": 0, "PlayerScore8": 0, "PlayerScore9": 0, "allInPings": 0, "assistMePings": 8, "assists": 18, "baronKills": 0, "basicPings": 0, "challenges": {"12AssistStreakCount": 0, "HealFromMapSources": 4523.603843212128, "InfernalScalePickup": 0, "SWARM_DefeatAatrox": 0, "SWARM_DefeatBriar": 0, "SWARM_DefeatMiniBosses": 0, "SWARM_EvolveWeapon": 0, "SWARM_Have3Passives": 0, "SWARM_KillEnemy": 0, "SWARM_PickupGold": 0, "SWARM_ReachLevel50": 0, "SWARM_Survive15Min": 0, "SWARM_WinWith5EvolvedWeapons": 0, "abilityUses": 503, "acesBefore15Minutes": 2, "alliedJungleMonsterKills": 0, "baronTakedowns": 0, "blastConeOppositeOpponentCount": 0, "bountyGold": 438.48622131347656, "buffsStolen": 0, "completeSupportQuestInTime": 0, "controlWardsPlaced": 0, "damagePerMinute": 2464.319581203926, "damageTakenOnTeamPercentage": 0.16940079278142664, "dancedWithRiftHerald": 0, "deathsByEnemyChamps": 12, "dodgeSkillShotsSmallWindow": 14, "doubleAces": 0, "dragonTakedowns": 0, "effectiveHealAndShielding": 0, "elderDragonKillsWithOpposingSoul": 0, "elderDragonMultikills": 0, "enemyChampionImmobilizations": 68, "enemyJungleMonsterKills": 0, "epicMonsterKillsNearEnemyJungler": 0, "epicMonsterKillsWithin30SecondsOfSpawn": 0, "epicMonsterSteals": 0, "epicMonsterStolenWithoutSmite": 0, "firstTurretKilled": 0, "fistBumpParticipation": 1, "flawlessAces": 3, "fullTeamTakedown": 5, "gameLength": 1416.0476315110002, "getTakedownsInAllLanesEarlyJungleAsLaner": 0, "goldPerMinute": 875.1580117154224, "hadOpenNexus": 0, "immobilizeAndKillWithAlly": 28, "initialBuffCount": 0, "initialCrabCount": 0, "jungleCsBefore10Minutes": 0, "junglerTakedownsNearDamagedEpicMonster": 0, "kTurretsDestroyedBeforePlatesFall": 1, "kda": 3.8333333333333335, "killAfterHiddenWithAlly": 1, "killParticipation": 0.8363636363636363, "killedChampTookFullTeamDamageSurvived": 0, "killingSprees": 6, "killsNearEnemyTurret": 9, "killsOnOtherLanesEarlyJungleAsLaner": 0, "killsOnRecentlyHealedByAramPack": 0, "killsUnderOwnTurret": 0, "killsWithHelpFromEpicMonster": 0, "knockEnemyIntoTeamAndKill": 11, "landSkillShotsEarlyGame": 5, "laneMinionsFirst10Minutes": 37, "legendaryCount": 0, "legendaryItemUsed": [6692, 6610, 6333, 3071, 3053], "lostAnInhibitor": 0, "maxKillDeficit": 0, "mejaisFullStackInTime": 0, "moreEnemyJungleThanOpponent": 0, "multiKillOneSpell": 0, "multiTurretRiftHeraldCount": 0, "multikills": 12, "multikillsAfterAggressiveFlash": 3, "outerTurretExecutesBefore10Minutes": 0, "outnumberedKills": 15, "outnumberedNexusKill": 0, "perfectDragonSoulsTaken": 0, "perfectGame": 0, "pickKillWithAlly": 29, "poroExplosions": 6, "quickCleanse": 0, "quickFirstTurret": 0, "quickSoloKills": 1, "riftHeraldTakedowns": 0, "saveAllyFromDeath": 0, "scuttleCrabKills": 0, "shortestTimeToAceFromFirstTakedown": 16.19148210100002, "skillshotsDodged": 151, "skillshotsHit": 23, "snowballsHit": 15, "soloBaronKills": 0, "soloKills": 5, "stealthWardsPlaced": 0, "survivedSingleDigitHpCount": 1, "survivedThreeImmobilizesInFight": 4, "takedownOnFirstTurret": 1, "takedowns": 46, "takedownsAfterGainingLevelAdvantage": 0, "takedownsBeforeJungleMinionSpawn": 1, "takedownsFirstXMinutes": 32, "takedownsInAlcove": 0, "takedownsInEnemyFountain": 0, "teamBaronKills": 0, "teamDamagePercentage": 0.3458300461351498, "teamElderDragonKills": 0, "teamRiftHeraldKills": 0, "tookLargeDamageSurvived": 4, "turretPlatesTaken": 0, "turretTakedowns": 2, "turretsTakenWithRiftHerald": 0, "twentyMinionsIn3SecondsCount": 0, "twoWardsOneSweeperCount": 0, "unseenRecalls": 0, "visionScorePerMinute": 0, "voidMonsterKill": 0, "wardTakedowns": 0, "wardTakedownsBefore20M": 0, "wardsGuarded": 0}, "champExperience": 25113, "champLevel": 18, "championId": 92, "championName": "Riven", "championTransform": 0, "commandPings": 9, "consumablesPurchased": 0, "damageDealtToBuildings": 2578, "damageDealtToObjectives": 2578, "damageDealtToTurrets": 2578, "damageSelfMitigated": 121860, "dangerPings": 0, "deaths": 12, "detectorWardsPlaced": 0, "doubleKills": 5, "dragonKills": 0, "eligibleForProgression": true, "enemyMissingPings": 11, "enemyVisionPings": 4, "firstBloodAssist": false, "firstBloodKill": false, "firstTowerAssist": false, "firstTowerKill": false, "gameEndedInEarlySurrender": false, "gameEndedInSurrender": true, "getBackPings": 0, "goldEarned": 20654, "goldSpent": 18100, "holdPings": 0, "individualPosition": "Invalid", "inhibitorKills": 0, "inhibitorTakedowns": 1, "inhibitorsLost": 2, "item0": 6333, "item1": 6692, "item2": 6610, "item3": 3111, "item4": 3071, "item5": 3053, "item6": 2052, "itemsPurchased": 21, "killingSprees": 7, "kills": 28, "lane": "MIDDLE", "largestCriticalStrike": 554, "largestKillingSpree": 4, "largestMultiKill": 4, "longestTimeSpentLiving": 195, "magicDamageDealt": 0, "magicDamageDealtToChampions": 0, "magicDamageTaken": 18844, "missions": {"playerScore0": 0, "playerScore1": 0, "playerScore2": 0, "playerScore3": 0, "playerScore4": 0, "playerScore5": 0, "playerScore6": 0, "playerScore7": 0, "playerScore8": 0, "playerScore9": 0, "playerScore10": 0, "playerScore11": 0}, "needVisionPings": 0, "neutralMinionsKilled": 0, "nexusKills": 0, "nexusLost": 1, "nexusTakedowns": 0, "objectivesStolen": 0, "objectivesStolenAssists": 0, "onMyWayPings": 13, "participantId": 7, "pentaKills": 0, "perks": {"statPerks": {"defense": 5001, "flex": 5008, "offense": 5008}, "styles": [{"description": "primaryStyle", "selections": [{"perk": 8010, "var1": 1600, "var2": 0, "var3": 0}, {"perk": 9111, "var1": 3069, "var2": 460, "var3": 0}, {"perk": 9105, "var1": 3, "var2": 20, "var3": 0}, {"perk": 8299, "var1": 2845, "var2": 0, "var3": 0}], "style": 8000}, {"description": "subStyle", "selections": [{"perk": 8143, "var1": 2135, "var2": 0, "var3": 0}, {"perk": 8135, "var1": 450, "var2": 5, "var3": 0}], "style": 8100}]}, "physicalDamageDealt": 142906, "physicalDamageDealtToChampions": 54397, "physicalDamageTaken": 21356, "placement": 0, "playerAugment1": 0, "playerAugment2": 0, "playerAugment3": 0, "playerAugment4": 0, "playerAugment5": 0, "playerAugment6": 0, "playerSubteamId": 0, "profileIcon": 1625, "pushPings": 2, "puuid": "MKm3XcJLSjD4t3G4Ek0unUs3aexUmBw_yF5nvmRqVIQPdhiXjM_FbJGYWSZaKmLmV-O4aauSr6KVGA", "quadraKills": 3, "retreatPings": 7, "riotIdGameName": "SAKU", "riotIdTagline": "VANA", "role": "DUO", "sightWardsBoughtInGame": 0, "spell1Casts": 291, "spell2Casts": 55, "spell3Casts": 135, "spell4Casts": 22, "subteamPlacement": 0, "summoner1Casts": 39, "summoner1Id": 32, "summoner2Casts": 6, "summoner2Id": 4, "summonerId": "dm2FibLEbKcQRSbcHT27btBxrPZkU8Tx9hbVXxguo1dtOKzr", "summonerLevel": 349, "summonerName": "", "teamEarlySurrendered": false, "teamId": 200, "teamPosition": "", "timeCCingOthers": 45, "timePlayed": 1415, "totalAllyJungleMinionsKilled": 0, "totalDamageDealt": 146713, "totalDamageDealtToChampions": 58159, "totalDamageShieldedOnTeammates": 0, "totalDamageTaken": 49503, "totalEnemyJungleMinionsKilled": 0, "totalHeal": 19668, "totalHealsOnTeammates": 0, "totalMinionsKilled": 101, "totalTimeCCDealt": 212, "totalTimeSpentDead": 279, "totalUnitsHealed": 1, "tripleKills": 4, "trueDamageDealt": 3807, "trueDamageDealtToChampions": 3762, "trueDamageTaken": 9302, "turretKills": 0, "turretTakedowns": 2, "turretsLost": 4, "unrealKills": 0, "visionClearedPings": 0, "visionScore": 0, "visionWardsBoughtInGame": 0, "wardsKilled": 0, "wardsPlaced": 0, "win": false}, {"PlayerScore0": 0, "PlayerScore1": 0, "PlayerScore10": 0, "PlayerScore11": 0, "PlayerScore2": 0, "PlayerScore3": 0, "PlayerScore4": 0, "PlayerScore5": 0, "PlayerScore6": 0, "PlayerScore7": 0, "PlayerScore8": 0, "PlayerScore9": 0, "allInPings": 0, "assistMePings": 0, "assists": 27, "baronKills": 0, "basicPings": 0, "challenges": {"12AssistStreakCount": 1, "HealFromMapSources": 3015.3873558044434, "InfernalScalePickup": 0, "SWARM_DefeatAatrox": 0, "SWARM_DefeatBriar": 0, "SWARM_DefeatMiniBosses": 0, "SWARM_EvolveWeapon": 0, "SWARM_Have3Passives": 0, "SWARM_KillEnemy": 0, "SWARM_PickupGold": 0, "SWARM_ReachLevel50": 0, "SWARM_Survive15Min": 0, "SWARM_WinWith5EvolvedWeapons": 0, "abilityUses": 144, "acesBefore15Minutes": 2, "alliedJungleMonsterKills": 0, "baronTakedowns": 0, "blastConeOppositeOpponentCount": 0, "bountyGold": 153.92587280273438, "buffsStolen": 0, "completeSupportQuestInTime": 0, "controlWardsPlaced": 0, "damagePerMinute": 912.0964043750578, "damageTakenOnTeamPercentage": 0.2278217299597447, "dancedWithRiftHerald": 0, "deathsByEnemyChamps": 11, "dodgeSkillShotsSmallWindow": 16, "doubleAces": 0, "dragonTakedowns": 0, "effectiveHealAndShielding": 2279.769287109375, "elderDragonKillsWithOpposingSoul": 0, "elderDragonMultikills": 0, "enemyChampionImmobilizations": 18, "enemyJungleMonsterKills": 0, "epicMonsterKillsNearEnemyJungler": 0, "epicMonsterKillsWithin30SecondsOfSpawn": 0, "epicMonsterSteals": 0, "epicMonsterStolenWithoutSmite": 0, "firstTurretKilled": 0, "fistBumpParticipation": 1, "flawlessAces": 3, "fullTeamTakedown": 5, "gameLength": 1416.0476315110002, "getTakedownsInAllLanesEarlyJungleAsLaner": 0, "goldPerMinute": 586.3331469835873, "hadOpenNexus": 0, "immobilizeAndKillWithAlly": 4, "initialBuffCount": 0, "initialCrabCount": 0, "jungleCsBefore10Minutes": 0, "junglerTakedownsNearDamagedEpicMonster": 0, "kTurretsDestroyedBeforePlatesFall": 1, "kda": 2.8181818181818183, "killAfterHiddenWithAlly": 4, "killParticipation": 0.5636363636363636, "killedChampTookFullTeamDamageSurvived": 0, "killingSprees": 0, "killsNearEnemyTurret": 1, "killsOnOtherLanesEarlyJungleAsLaner": 0, "killsOnRecentlyHealedByAramPack": 0, "killsUnderOwnTurret": 1, "killsWithHelpFromEpicMonster": 0, "knockEnemyIntoTeamAndKill": 0, "landSkillShotsEarlyGame": 13, "laneMinionsFirst10Minutes": 4, "legendaryCount": 0, "legendaryItemUsed": [3084, 2502, 3075, 3065], "lostAnInhibitor": 0, "maxKillDeficit": 0, "mejaisFullStackInTime": 0, "moreEnemyJungleThanOpponent": 0, "multiKillOneSpell": 0, "multiTurretRiftHeraldCount": 0, "multikills": 0, "multikillsAfterAggressiveFlash": 0, "outerTurretExecutesBefore10Minutes": 0, "outnumberedKills": 1, "outnumberedNexusKill": 0, "perfectDragonSoulsTaken": 0, "perfectGame": 0, "pickKillWithAlly": 22, "poroExplosions": 6, "quickCleanse": 0, "quickFirstTurret": 0, "quickSoloKills": 0, "riftHeraldTakedowns": 0, "saveAllyFromDeath": 0, "scuttleCrabKills": 0, "shortestTimeToAceFromFirstTakedown": 16.19148210100002, "skillshotsDodged": 135, "skillshotsHit": 45, "snowballsHit": 11, "soloBaronKills": 0, "soloKills": 0, "stealthWardsPlaced": 0, "survivedSingleDigitHpCount": 0, "survivedThreeImmobilizesInFight": 2, "takedownOnFirstTurret": 1, "takedowns": 31, "takedownsAfterGainingLevelAdvantage": 0, "takedownsBeforeJungleMinionSpawn": 0, "takedownsFirstXMinutes": 22, "takedownsInAlcove": 0, "takedownsInEnemyFountain": 0, "teamBaronKills": 0, "teamDamagePercentage": 0.12799895923021035, "teamElderDragonKills": 0, "teamRiftHeraldKills": 0, "tookLargeDamageSurvived": 0, "turretPlatesTaken": 0, "turretTakedowns": 2, "turretsTakenWithRiftHerald": 0, "twentyMinionsIn3SecondsCount": 0, "twoWardsOneSweeperCount": 0, "unseenRecalls": 0, "visionScorePerMinute": 0, "voidMonsterKill": 0, "wardTakedowns": 0, "wardTakedownsBefore20M": 0, "wardsGuarded": 0}, "champExperience": 22205, "champLevel": 18, "championId": 223, "championName": "TahmKench", "championTransform": 0, "commandPings": 9, "consumablesPurchased": 2, "damageDealtToBuildings": 856, "damageDealtToObjectives": 856, "damageDealtToTurrets": 856, "damageSelfMitigated": 85612, "dangerPings": 0, "deaths": 11, "detectorWardsPlaced": 0, "doubleKills": 0, "dragonKills": 0, "eligibleForProgression": true, "enemyMissingPings": 2, "enemyVisionPings": 11, "firstBloodAssist": false, "firstBloodKill": false, "firstTowerAssist": false, "firstTowerKill": false, "gameEndedInEarlySurrender": false, "gameEndedInSurrender": true, "getBackPings": 1, "goldEarned": 13837, "goldSpent": 12700, "holdPings": 0, "individualPosition": "Invalid", "inhibitorKills": 0, "inhibitorTakedowns": 1, "inhibitorsLost": 2, "item0": 3084, "item1": 3070, "item2": 2502, "item3": 3111, "item4": 3075, "item5": 3065, "item6": 2052, "itemsPurchased": 19, "killingSprees": 1, "kills": 4, "lane": "MIDDLE", "largestCriticalStrike": 19, "largestKillingSpree": 2, "largestMultiKill": 1, "longestTimeSpentLiving": 169, "magicDamageDealt": 31734, "magicDamageDealtToChampions": 14938, "magicDamageTaken": 29407, "missions": {"playerScore0": 0, "playerScore1": 0, "playerScore2": 0, "playerScore3": 0, "playerScore4": 0, "playerScore5": 0, "playerScore6": 0, "playerScore7": 0, "playerScore8": 0, "playerScore9": 0, "playerScore10": 0, "playerScore11": 0}, "needVisionPings": 0, "neutralMinionsKilled": 0, "nexusKills": 0, "nexusLost": 1, "nexusTakedowns": 0, "objectivesStolen": 0, "objectivesStolenAssists": 0, "onMyWayPings": 2, "participantId": 8, "pentaKills": 0, "perks": {"statPerks": {"defense": 5001, "flex": 5001, "offense": 5005}, "styles": [{"description": "primaryStyle", "selections": [{"perk": 8437, "var1": 1707, "var2": 1081, "var3": 0}, {"perk": 8401, "var1": 706, "var2": 0, "var3": 0}, {"perk": 8444, "var1": 3073, "var2": 0, "var3": 0}, {"perk": 8451, "var1": 412, "var2": 0, "var3": 0}], "style": 8400}, {"description": "subStyle", "selections": [{"perk": 9105, "var1": 5, "var2": 30, "var3": 0}, {"perk": 9111, "var1": 2530, "var2": 310, "var3": 0}], "style": 8000}]}, "physicalDamageDealt": 11111, "physicalDamageDealtToChampions": 5555, "physicalDamageTaken": 32691, "placement": 0, "playerAugment1": 0, "playerAugment2": 0, "playerAugment3": 0, "playerAugment4": 0, "playerAugment5": 0, "playerAugment6": 0, "playerSubteamId": 0, "profileIcon": 6878, "pushPings": 0, "puuid": "L_5f66Q9jH8msK7HgBT4UpzBepLKtlFxdy84nxxyHL5GSqYMRUm8xRjXlk78hzHSMGvzNPnEQAVN4Q", "quadraKills": 0, "retreatPings": 1, "riotIdGameName": "VANA", "riotIdTagline": "SAKU", "role": "SUPPORT", "sightWardsBoughtInGame": 0, "spell1Casts": 82, "spell2Casts": 34, "spell3Casts": 21, "spell4Casts": 7, "subteamPlacement": 0, "summoner1Casts": 4, "summoner1Id": 4, "summoner2Casts": 30, "summoner2Id": 32, "summonerId": "wYLSnXI0E0I70GoN6IkQXdEX7FLAnkHDclVa9brrnIFmS6Tc", "summonerLevel": 458, "summonerName": "", "teamEarlySurrendered": false, "teamId": 200, "teamPosition": "", "timeCCingOthers": 19, "timePlayed": 1415, "totalAllyJungleMinionsKilled": 0, "totalDamageDealt": 44206, "totalDamageDealtToChampions": 21526, "totalDamageShieldedOnTeammates": 2279, "totalDamageTaken": 66575, "totalEnemyJungleMinionsKilled": 0, "totalHeal": 19444, "totalHealsOnTeammates": 0, "totalMinionsKilled": 13, "totalTimeCCDealt": 183, "totalTimeSpentDead": 277, "totalUnitsHealed": 1, "tripleKills": 0, "trueDamageDealt": 1361, "trueDamageDealtToChampions": 1031, "trueDamageTaken": 4476, "turretKills": 0, "turretTakedowns": 2, "turretsLost": 4, "unrealKills": 0, "visionClearedPings": 0, "visionScore": 0, "visionWardsBoughtInGame": 0, "wardsKilled": 0, "wardsPlaced": 0, "win": false}, {"PlayerScore0": 0, "PlayerScore1": 0, "PlayerScore10": 0, "PlayerScore11": 0, "PlayerScore2": 0, "PlayerScore3": 0, "PlayerScore4": 0, "PlayerScore5": 0, "PlayerScore6": 0, "PlayerScore7": 0, "PlayerScore8": 0, "PlayerScore9": 0, "allInPings": 0, "assistMePings": 0, "assists": 17, "baronKills": 0, "basicPings": 0, "challenges": {"12AssistStreakCount": 0, "HealFromMapSources": 1590.2771320343018, "InfernalScalePickup": 0, "SWARM_DefeatAatrox": 0, "SWARM_DefeatBriar": 0, "SWARM_DefeatMiniBosses": 0, "SWARM_EvolveWeapon": 0, "SWARM_Have3Passives": 0, "SWARM_KillEnemy": 0, "SWARM_PickupGold": 0, "SWARM_ReachLevel50": 0, "SWARM_Survive15Min": 0, "SWARM_WinWith5EvolvedWeapons": 0, "abilityUses": 209, "acesBefore15Minutes": 2, "alliedJungleMonsterKills": 0, "baronTakedowns": 0, "blastConeOppositeOpponentCount": 0, "bountyGold": 424.1259307861328, "buffsStolen": 0, "completeSupportQuestInTime": 0, "controlWardsPlaced": 0, "damagePerMinute": 1582.5920903936706, "damageTakenOnTeamPercentage": 0.0970441672047881, "dancedWithRiftHerald": 0, "deathsByEnemyChamps": 14, "dodgeSkillShotsSmallWindow": 4, "doubleAces": 0, "dragonTakedowns": 0, "effectiveHealAndShielding": 0, "elderDragonKillsWithOpposingSoul": 0, "elderDragonMultikills": 0, "enemyChampionImmobilizations": 0, "enemyJungleMonsterKills": 0, "epicMonsterKillsNearEnemyJungler": 0, "epicMonsterKillsWithin30SecondsOfSpawn": 0, "epicMonsterSteals": 0, "epicMonsterStolenWithoutSmite": 0, "firstTurretKilled": 0, "fistBumpParticipation": 1, "flawlessAces": 3, "fullTeamTakedown": 5, "gameLength": 1416.0476315110002, "getTakedownsInAllLanesEarlyJungleAsLaner": 0, "goldPerMinute": 705.6211265533535, "hadOpenNexus": 0, "immobilizeAndKillWithAlly": 0, "initialBuffCount": 0, "initialCrabCount": 0, "jungleCsBefore10Minutes": 0, "junglerTakedownsNearDamagedEpicMonster": 0, "kTurretsDestroyedBeforePlatesFall": 0, "kda": 1.9285714285714286, "killAfterHiddenWithAlly": 2, "killParticipation": 0.4909090909090909, "killedChampTookFullTeamDamageSurvived": 0, "killingSprees": 0, "killsNearEnemyTurret": 3, "killsOnOtherLanesEarlyJungleAsLaner": 0, "killsOnRecentlyHealedByAramPack": 2, "killsUnderOwnTurret": 1, "killsWithHelpFromEpicMonster": 0, "knockEnemyIntoTeamAndKill": 0, "landSkillShotsEarlyGame": 7, "laneMinionsFirst10Minutes": 29, "legendaryCount": 0, "legendaryItemUsed": [3508, 6676, 3031, 6675], "lostAnInhibitor": 0, "maxKillDeficit": 0, "mejaisFullStackInTime": 0, "moreEnemyJungleThanOpponent": 0, "multiKillOneSpell": 0, "multiTurretRiftHeraldCount": 0, "multikills": 3, "multikillsAfterAggressiveFlash": 1, "outerTurretExecutesBefore10Minutes": 0, "outnumberedKills": 2, "outnumberedNexusKill": 0, "perfectDragonSoulsTaken": 0, "perfectGame": 0, "pickKillWithAlly": 21, "poroExplosions": 6, "quickCleanse": 0, "quickFirstTurret": 0, "quickSoloKills": 0, "riftHeraldTakedowns": 0, "saveAllyFromDeath": 0, "scuttleCrabKills": 0, "shortestTimeToAceFromFirstTakedown": 12.960056000000122, "skillshotsDodged": 61, "skillshotsHit": 28, "snowballsHit": 0, "soloBaronKills": 0, "soloKills": 0, "stealthWardsPlaced": 0, "survivedSingleDigitHpCount": 0, "survivedThreeImmobilizesInFight": 0, "takedownOnFirstTurret": 0, "takedowns": 27, "takedownsAfterGainingLevelAdvantage": 0, "takedownsBeforeJungleMinionSpawn": 0, "takedownsFirstXMinutes": 19, "takedownsInAlcove": 0, "takedownsInEnemyFountain": 0, "teamBaronKills": 0, "teamDamagePercentage": 0.22209290540416948, "teamElderDragonKills": 0, "teamRiftHeraldKills": 0, "tookLargeDamageSurvived": 0, "turretPlatesTaken": 0, "turretTakedowns": 1, "turretsTakenWithRiftHerald": 0, "twentyMinionsIn3SecondsCount": 0, "twoWardsOneSweeperCount": 0, "unseenRecalls": 0, "visionScorePerMinute": 0, "voidMonsterKill": 0, "wardTakedowns": 0, "wardTakedownsBefore20M": 0, "wardsGuarded": 0}, "champExperience": 21140, "champLevel": 18, "championId": 236, "championName": "Lucian", "championTransform": 0, "commandPings": 0, "consumablesPurchased": 0, "damageDealtToBuildings": 1751, "damageDealtToObjectives": 1751, "damageDealtToTurrets": 1751, "damageSelfMitigated": 14100, "dangerPings": 0, "deaths": 14, "detectorWardsPlaced": 0, "doubleKills": 3, "dragonKills": 0, "eligibleForProgression": true, "enemyMissingPings": 0, "enemyVisionPings": 0, "firstBloodAssist": false, "firstBloodKill": false, "firstTowerAssist": false, "firstTowerKill": false, "gameEndedInEarlySurrender": false, "gameEndedInSurrender": true, "getBackPings": 0, "goldEarned": 16653, "goldSpent": 14200, "holdPings": 0, "individualPosition": "Invalid", "inhibitorKills": 0, "inhibitorTakedowns": 0, "inhibitorsLost": 2, "item0": 3031, "item1": 6676, "item2": 3508, "item3": 3158, "item4": 6675, "item5": 1038, "item6": 2052, "itemsPurchased": 16, "killingSprees": 3, "kills": 10, "lane": "MIDDLE", "largestCriticalStrike": 708, "largestKillingSpree": 2, "largestMultiKill": 2, "longestTimeSpentLiving": 170, "magicDamageDealt": 11246, "magicDamageDealtToChampions": 3402, "magicDamageTaken": 13476, "missions": {"playerScore0": 0, "playerScore1": 0, "playerScore2": 0, "playerScore3": 0, "playerScore4": 0, "playerScore5": 0, "playerScore6": 0, "playerScore7": 0, "playerScore8": 0, "playerScore9": 0, "playerScore10": 0, "playerScore11": 0}, "needVisionPings": 0, "neutralMinionsKilled": 0, "nexusKills": 0, "nexusLost": 1, "nexusTakedowns": 0, "objectivesStolen": 0, "objectivesStolenAssists": 0, "onMyWayPings": 4, "participantId": 9, "pentaKills": 0, "perks": {"statPerks": {"defense": 5001, "flex": 5008, "offense": 5005}, "styles": [{"description": "primaryStyle", "selections": [{"perk": 8005, "var1": 1884, "var2": 1884, "var3": 0}, {"perk": 8009, "var1": 1842, "var2": 0, "var3": 0}, {"perk": 9104, "var1": 5, "var2": 40, "var3": 0}, {"perk": 8014, "var1": 857, "var2": 0, "var3": 0}], "style": 8000}, {"description": "subStyle", "selections": [{"perk": 8139, "var1": 1300, "var2": 0, "var3": 0}, {"perk": 8135, "var1": 450, "var2": 5, "var3": 0}], "style": 8100}]}, "physicalDamageDealt": 138214, "physicalDamageDealtToChampions": 33570, "physicalDamageTaken": 13065, "placement": 0, "playerAugment1": 0, "playerAugment2": 0, "playerAugment3": 0, "playerAugment4": 0, "playerAugment5": 0, "playerAugment6": 0, "playerSubteamId": 0, "profileIcon": 3150, "pushPings": 0, "puuid": "Te9fjeEmED0mdBZArju3ElCSmEzHrELGpjtS8Yyq5aOBBzU3rxSVeL4xpl6J2neXY_A6V14kRIW0hA", "quadraKills": 0, "retreatPings": 0, "riotIdGameName": "ValouPipop", "riotIdTagline": "6769", "role": "DUO", "sightWardsBoughtInGame": 0, "spell1Casts": 76, "spell2Casts": 62, "spell3Casts": 58, "spell4Casts": 13, "subteamPlacement": 0, "summoner1Casts": 5, "summoner1Id": 6, "summoner2Casts": 5, "summoner2Id": 4, "summonerId": "M3ap3AqIKe_5D6oBVYr_KPZ3sdOWoFzUVEiV1A2AeFtp9_KumesPakh5nw", "summonerLevel": 369, "summonerName": "", "teamEarlySurrendered": false, "teamId": 200, "teamPosition": "", "timeCCingOthers": 0, "timePlayed": 1415, "totalAllyJungleMinionsKilled": 0, "totalDamageDealt": 149837, "totalDamageDealtToChampions": 37350, "totalDamageShieldedOnTeammates": 0, "totalDamageTaken": 28359, "totalEnemyJungleMinionsKilled": 0, "totalHeal": 2715, "totalHealsOnTeammates": 0, "totalMinionsKilled": 107, "totalTimeCCDealt": 45, "totalTimeSpentDead": 328, "totalUnitsHealed": 1, "tripleKills": 0, "trueDamageDealt": 376, "trueDamageDealtToChampions": 376, "trueDamageTaken": 1817, "turretKills": 1, "turretTakedowns": 1, "turretsLost": 4, "unrealKills": 0, "visionClearedPings": 0, "visionScore": 0, "visionWardsBoughtInGame": 0, "wardsKilled": 0, "wardsPlaced": 0, "win": false}, {"PlayerScore0": 0, "PlayerScore1": 0, "PlayerScore10": 0, "PlayerScore11": 0, "PlayerScore2": 0, "PlayerScore3": 0, "PlayerScore4": 0, "PlayerScore5": 0, "PlayerScore6": 0, "PlayerScore7": 0, "PlayerScore8": 0, "PlayerScore9": 0, "allInPings": 0, "assistMePings": 0, "assists": 28, "baronKills": 0, "basicPings": 0, "challenges": {"12AssistStreakCount": 1, "HealFromMapSources": 7120.50332069397, "InfernalScalePickup": 0, "SWARM_DefeatAatrox": 0, "SWARM_DefeatBriar": 0, "SWARM_DefeatMiniBosses": 0, "SWARM_EvolveWeapon": 0, "SWARM_Have3Passives": 0, "SWARM_KillEnemy": 0, "SWARM_PickupGold": 0, "SWARM_ReachLevel50": 0, "SWARM_Survive15Min": 0, "SWARM_WinWith5EvolvedWeapons": 0, "abilityUses": 233, "acesBefore15Minutes": 2, "alliedJungleMonsterKills": 0, "baronTakedowns": 0, "blastConeOppositeOpponentCount": 0, "bountyGold": 0, "buffsStolen": 0, "completeSupportQuestInTime": 0, "controlWardsPlaced": 0, "damagePerMinute": 1293.0046222094732, "damageTakenOnTeamPercentage": 0.31170113093425217, "dancedWithRiftHerald": 0, "deathsByEnemyChamps": 13, "dodgeSkillShotsSmallWindow": 17, "doubleAces": 0, "dragonTakedowns": 0, "effectiveHealAndShielding": 326.7646179199219, "elderDragonKillsWithOpposingSoul": 0, "elderDragonMultikills": 0, "enemyChampionImmobilizations": 28, "enemyJungleMonsterKills": 0, "epicMonsterKillsNearEnemyJungler": 0, "epicMonsterKillsWithin30SecondsOfSpawn": 0, "epicMonsterSteals": 0, "epicMonsterStolenWithoutSmite": 0, "firstTurretKilled": 0, "fistBumpParticipation": 0, "flawlessAces": 3, "fullTeamTakedown": 5, "gameLength": 1416.0476315110002, "getTakedownsInAllLanesEarlyJungleAsLaner": 0, "goldPerMinute": 620.3198546366668, "hadOpenNexus": 0, "immobilizeAndKillWithAlly": 15, "initialBuffCount": 0, "initialCrabCount": 0, "jungleCsBefore10Minutes": 0, "junglerTakedownsNearDamagedEpicMonster": 0, "kTurretsDestroyedBeforePlatesFall": 0, "kda": 2.6153846153846154, "killAfterHiddenWithAlly": 6, "killParticipation": 0.6181818181818182, "killedChampTookFullTeamDamageSurvived": 0, "killingSprees": 0, "killsNearEnemyTurret": 0, "killsOnOtherLanesEarlyJungleAsLaner": 0, "killsOnRecentlyHealedByAramPack": 0, "killsUnderOwnTurret": 0, "killsWithHelpFromEpicMonster": 0, "knockEnemyIntoTeamAndKill": 0, "landSkillShotsEarlyGame": 0, "laneMinionsFirst10Minutes": 26, "legendaryCount": 0, "legendaryItemUsed": [3084, 3083, 2502, 2504], "lostAnInhibitor": 0, "maxKillDeficit": 0, "mejaisFullStackInTime": 0, "moreEnemyJungleThanOpponent": 0, "multiKillOneSpell": 0, "multiTurretRiftHeraldCount": 0, "multikills": 0, "multikillsAfterAggressiveFlash": 0, "outerTurretExecutesBefore10Minutes": 0, "outnumberedKills": 2, "outnumberedNexusKill": 0, "perfectDragonSoulsTaken": 0, "perfectGame": 0, "pickKillWithAlly": 25, "poroExplosions": 6, "quickCleanse": 0, "quickFirstTurret": 0, "quickSoloKills": 0, "riftHeraldTakedowns": 0, "saveAllyFromDeath": 0, "scuttleCrabKills": 0, "shortestTimeToAceFromFirstTakedown": 12.960056000000122, "skillshotsDodged": 154, "skillshotsHit": 0, "snowballsHit": 13, "soloBaronKills": 0, "soloKills": 0, "stealthWardsPlaced": 0, "survivedSingleDigitHpCount": 1, "survivedThreeImmobilizesInFight": 2, "takedownOnFirstTurret": 0, "takedowns": 34, "takedownsAfterGainingLevelAdvantage": 0, "takedownsBeforeJungleMinionSpawn": 1, "takedownsFirstXMinutes": 23, "takedownsInAlcove": 0, "takedownsInEnemyFountain": 0, "teamBaronKills": 0, "teamDamagePercentage": 0.18145367652892125, "teamElderDragonKills": 0, "teamRiftHeraldKills": 0, "tookLargeDamageSurvived": 2, "turretPlatesTaken": 0, "turretTakedowns": 1, "turretsTakenWithRiftHerald": 0, "twentyMinionsIn3SecondsCount": 0, "twoWardsOneSweeperCount": 0, "unseenRecalls": 0, "visionScorePerMinute": 0, "voidMonsterKill": 0, "wardTakedowns": 0, "wardTakedownsBefore20M": 0, "wardsGuarded": 0}, "champExperience": 24730, "champLevel": 18, "championId": 31, "championName": "Chogath", "championTransform": 0, "commandPings": 0, "consumablesPurchased": 0, "damageDealtToBuildings": 165, "damageDealtToObjectives": 165, "damageDealtToTurrets": 165, "damageSelfMitigated": 83674, "dangerPings": 0, "deaths": 13, "detectorWardsPlaced": 0, "doubleKills": 0, "dragonKills": 0, "eligibleForProgression": true, "enemyMissingPings": 0, "enemyVisionPings": 0, "firstBloodAssist": false, "firstBloodKill": false, "firstTowerAssist": false, "firstTowerKill": false, "gameEndedInEarlySurrender": false, "gameEndedInSurrender": true, "getBackPings": 0, "goldEarned": 14640, "goldSpent": 13850, "holdPings": 0, "individualPosition": "Invalid", "inhibitorKills": 1, "inhibitorTakedowns": 1, "inhibitorsLost": 2, "item0": 3084, "item1": 3111, "item2": 3083, "item3": 2502, "item4": 2504, "item5": 3076, "item6": 2052, "itemsPurchased": 21, "killingSprees": 1, "kills": 6, "lane": "TOP", "largestCriticalStrike": 0, "largestKillingSpree": 2, "largestMultiKill": 1, "longestTimeSpentLiving": 157, "magicDamageDealt": 62885, "magicDamageDealtToChampions": 16896, "magicDamageTaken": 30656, "missions": {"playerScore0": 0, "playerScore1": 0, "playerScore2": 0, "playerScore3": 0, "playerScore4": 0, "playerScore5": 0, "playerScore6": 0, "playerScore7": 0, "playerScore8": 0, "playerScore9": 0, "playerScore10": 0, "playerScore11": 0}, "needVisionPings": 0, "neutralMinionsKilled": 0, "nexusKills": 0, "nexusLost": 1, "nexusTakedowns": 0, "objectivesStolen": 0, "objectivesStolenAssists": 0, "onMyWayPings": 7, "participantId": 10, "pentaKills": 0, "perks": {"statPerks": {"defense": 5001, "flex": 5001, "offense": 5005}, "styles": [{"description": "primaryStyle", "selections": [{"perk": 8437, "var1": 2614, "var2": 1878, "var3": 0}, {"perk": 8463, "var1": 1472, "var2": 0, "var3": 0}, {"perk": 8429, "var1": 66, "var2": 13, "var3": 14}, {"perk": 8451, "var1": 516, "var2": 0, "var3": 0}], "style": 8400}, {"description": "subStyle", "selections": [{"perk": 8009, "var1": 3525, "var2": 0, "var3": 0}, {"perk": 9105, "var1": 2, "var2": 50, "var3": 0}], "style": 8000}]}, "physicalDamageDealt": 13331, "physicalDamageDealtToChampions": 6401, "physicalDamageTaken": 52142, "placement": 0, "playerAugment1": 0, "playerAugment2": 0, "playerAugment3": 0, "playerAugment4": 0, "playerAugment5": 0, "playerAugment6": 0, "playerSubteamId": 0, "profileIcon": 5176, "pushPings": 0, "puuid": "FQ3LeA3YRDWrqQXZwoMu_WQ-1C1QwWH5n9fPJ72gK1qiERrQDhnwfCD-e4yBXRGrVYjXRtJs6m6MAA", "quadraKills": 0, "retreatPings": 1, "riotIdGameName": "IntingAfelio", "riotIdTagline": "EUW", "role": "SOLO", "sightWardsBoughtInGame": 0, "spell1Casts": 100, "spell2Casts": 64, "spell3Casts": 51, "spell4Casts": 18, "subteamPlacement": 0, "summoner1Casts": 6, "summoner1Id": 4, "summoner2Casts": 37, "summoner2Id": 32, "summonerId": "I_S5eh7Rc7lf--RigVs88zLrbXW1Z_VFPhjH3h9ZCbdZpZg", "summonerLevel": 751, "summonerName": "", "teamEarlySurrendered": false, "teamId": 200, "teamPosition": "", "timeCCingOthers": 94, "timePlayed": 1415, "totalAllyJungleMinionsKilled": 0, "totalDamageDealt": 89649, "totalDamageDealtToChampions": 30515, "totalDamageShieldedOnTeammates": 0, "totalDamageTaken": 91087, "totalEnemyJungleMinionsKilled": 0, "totalHeal": 13242, "totalHealsOnTeammates": 326, "totalMinionsKilled": 46, "totalTimeCCDealt": 551, "totalTimeSpentDead": 305, "totalUnitsHealed": 5, "tripleKills": 0, "trueDamageDealt": 13433, "trueDamageDealtToChampions": 7217, "trueDamageTaken": 8288, "turretKills": 0, "turretTakedowns": 1, "turretsLost": 4, "unrealKills": 0, "visionClearedPings": 0, "visionScore": 0, "visionWardsBoughtInGame": 0, "wardsKilled": 0, "wardsPlaced": 0, "win": false}], "platformId": "EUW1", "queueId": 450, "teams": [{"bans": [], "feats": {"EPIC_MONSTER_KILL": {"featState": 0}, "FIRST_BLOOD": {"featState": 0}, "FIRST_TURRET": {"featState": 0}}, "objectives": {"atakhan": {"first": false, "kills": 0}, "baron": {"first": false, "kills": 0}, "champion": {"first": true, "kills": 61}, "dragon": {"first": false, "kills": 0}, "horde": {"first": false, "kills": 0}, "inhibitor": {"first": true, "kills": 2}, "riftHerald": {"first": false, "kills": 0}, "tower": {"first": true, "kills": 4}}, "teamId": 100, "win": true}, {"bans": [], "feats": {"EPIC_MONSTER_KILL": {"featState": 0}, "FIRST_BLOOD": {"featState": 0}, "FIRST_TURRET": {"featState": 0}}, "objectives": {"atakhan": {"first": false, "kills": 0}, "baron": {"first": false, "kills": 0}, "champion": {"first": false, "kills": 56}, "dragon": {"first": false, "kills": 0}, "horde": {"first": false, "kills": 0}, "inhibitor": {"first": false, "kills": 1}, "riftHerald": {"first": false, "kills": 0}, "tower": {"first": false, "kills": 2}}, "teamId": 200, "win": false}], "tournamentCode": ""}}