{"metadata": {"dataVersion": "2", "matchId": "EUW1_7537057995", "participants": ["ocud99N_tPrNpm91ZUdcT8dGBnmw9yRozFyvz-bOQv4eUeiOh59kq-ksnFL9iK1uE9vRf_Cm-asQ4Q", "VeOp5LOX1cXcVAcTSDj1KcHG26uVAKQ-IhtRcdUZFG65ahxCMb3GvIjkfjWZF3BwTfIF0kWAsrqPTQ", "7ryUBvQsJxNmEj0gaQPZNrT8w9SuMbuyV0YHTkODmMGKE8OPlf3zFs7skaLsv6i1dIfYXVGvH0BOvQ", "XPqCQDRzqrCoYYtERbi-u50g9bqO1Evdo7o5jRuZDU_U8qvCTllHH4rk1bpOXQBxXeqgXcgb27Brag", "g0JSrepvy1Htftm-j3Dewr1UoLf_IDxcQVTDnmr6A_hVGt9_arAPdT35V8q2NwsWVIAK73CKGtVf7A", "F2ZZk4IKZrMtIGmOngEo2AsWu5UBSgnmibqiUZSscE9Eca39vExkRW-tbqfYTZd6YGqIeEisAUIoRQ", "WNHwMTvZysb2c0kqMCLie9_WDwqmZ-Fjb_DVX6efItpah86pCih_7Hk96ngqc41Z9iL1dbtdSHGhQw", "Sn5PWtYnswgZSMwWlk8oWqREX44q8wAvpwhnF8Ot7rS8clgVuy7txbRoI94214hUUzVpSiv3C1pMdQ", "aGaeDIsXm3Uj0j38I3Oi4ekB5c3X2gZIEQzpnXqz2O8rNaKaHw72HxjZDeRjpw6Vt4U_c7fWoOBjkA", "iACkqLCsGK9PPWlheNqZ9L2S8iksZ-HNxoJarmwLCc6QkIT3c7uSK2_cgbHec4BN80Kdaq3UOPRwVw"]}, "info": {"endOfGameResult": "GameComplete", "gameCreation": 1758636359651, "gameDuration": 1653, "gameEndTimestamp": 1758638123615, "gameId": 7537057995, "gameMode": "CLASSIC", "gameName": "teambuilder-match-7537057995", "gameStartTimestamp": 1758636470880, "gameType": "MATCHED_GAME", "gameVersion": "15.18.710.2811", "mapId": 11, "participants": [{"PlayerScore0": 0, "PlayerScore1": 0, "PlayerScore10": 0, "PlayerScore11": 0, "PlayerScore2": 0, "PlayerScore3": 0, "PlayerScore4": 0, "PlayerScore5": 0, "PlayerScore6": 0, "PlayerScore7": 0, "PlayerScore8": 0, "PlayerScore9": 0, "allInPings": 0, "assistMePings": 0, "assists": 13, "baronKills": 0, "basicPings": 0, "challenges": {"12AssistStreakCount": 0, "HealFromMapSources": 0, "InfernalScalePickup": 0, "SWARM_DefeatAatrox": 0, "SWARM_DefeatBriar": 0, "SWARM_DefeatMiniBosses": 0, "SWARM_EvolveWeapon": 0, "SWARM_Have3Passives": 0, "SWARM_KillEnemy": 0, "SWARM_PickupGold": 0, "SWARM_ReachLevel50": 0, "SWARM_Survive15Min": 0, "SWARM_WinWith5EvolvedWeapons": 0, "abilityUses": 446, "acesBefore15Minutes": 0, "alliedJungleMonsterKills": 2, "baronTakedowns": 0, "blastConeOppositeOpponentCount": 0, "bountyGold": 0, "buffsStolen": 0, "completeSupportQuestInTime": 0, "controlWardTimeCoverageInRiverOrEnemyHalf": 0.5950935948975039, "controlWardsPlaced": 3, "damagePerMinute": 892.7070674463527, "damageTakenOnTeamPercentage": 0.1655224725358011, "dancedWithRiftHerald": 0, "deathsByEnemyChamps": 4, "dodgeSkillShotsSmallWindow": 6, "doubleAces": 0, "dragonTakedowns": 0, "earlyLaningPhaseGoldExpAdvantage": 0, "effectiveHealAndShielding": 0, "elderDragonKillsWithOpposingSoul": 0, "elderDragonMultikills": 0, "enemyChampionImmobilizations": 0, "enemyJungleMonsterKills": 0, "epicMonsterKillsNearEnemyJungler": 0, "epicMonsterKillsWithin30SecondsOfSpawn": 0, "epicMonsterSteals": 0, "epicMonsterStolenWithoutSmite": 0, "firstTurretKilled": 1, "firstTurretKilledTime": 662.635772793, "fistBumpParticipation": 0, "flawlessAces": 0, "fullTeamTakedown": 7, "gameLength": 1653.095853474, "getTakedownsInAllLanesEarlyJungleAsLaner": 0, "goldPerMinute": 395.7539412151454, "hadOpenNexus": 0, "immobilizeAndKillWithAlly": 0, "initialBuffCount": 0, "initialCrabCount": 0, "jungleCsBefore10Minutes": 0, "junglerTakedownsNearDamagedEpicMonster": 0, "kTurretsDestroyedBeforePlatesFall": 0, "kda": 4, "killAfterHiddenWithAlly": 1, "killParticipation": 0.6153846153846154, "killedChampTookFullTeamDamageSurvived": 0, "killingSprees": 0, "killsNearEnemyTurret": 1, "killsOnOtherLanesEarlyJungleAsLaner": 0, "killsOnRecentlyHealedByAramPack": 0, "killsUnderOwnTurret": 0, "killsWithHelpFromEpicMonster": 0, "knockEnemyIntoTeamAndKill": 0, "landSkillShotsEarlyGame": 18, "laneMinionsFirst10Minutes": 91, "laningPhaseGoldExpAdvantage": 0, "legendaryCount": 0, "legendaryItemUsed": [6653, 8010], "lostAnInhibitor": 0, "maxCsAdvantageOnLaneOpponent": 48, "maxKillDeficit": 5, "maxLevelLeadLaneOpponent": 1, "mejaisFullStackInTime": 0, "moreEnemyJungleThanOpponent": 0, "multiKillOneSpell": 0, "multiTurretRiftHeraldCount": 0, "multikills": 1, "multikillsAfterAggressiveFlash": 0, "outerTurretExecutesBefore10Minutes": 0, "outnumberedKills": 0, "outnumberedNexusKill": 0, "perfectDragonSoulsTaken": 0, "perfectGame": 0, "pickKillWithAlly": 11, "playedChampSelectPosition": 1, "poroExplosions": 0, "quickCleanse": 0, "quickFirstTurret": 0, "quickSoloKills": 0, "riftHeraldTakedowns": 0, "saveAllyFromDeath": 0, "scuttleCrabKills": 0, "skillshotsDodged": 74, "skillshotsHit": 76, "snowballsHit": 0, "soloBaronKills": 0, "soloKills": 0, "stealthWardsPlaced": 5, "survivedSingleDigitHpCount": 0, "survivedThreeImmobilizesInFight": 6, "takedownOnFirstTurret": 0, "takedowns": 16, "takedownsAfterGainingLevelAdvantage": 0, "takedownsBeforeJungleMinionSpawn": 0, "takedownsFirstXMinutes": 1, "takedownsInAlcove": 0, "takedownsInEnemyFountain": 0, "teamBaronKills": 0, "teamDamagePercentage": 0.2506021923658792, "teamElderDragonKills": 0, "teamRiftHeraldKills": 1, "tookLargeDamageSurvived": 0, "turretPlatesTaken": 3, "turretTakedowns": 4, "turretsTakenWithRiftHerald": 5, "twentyMinionsIn3SecondsCount": 0, "twoWardsOneSweeperCount": 0, "unseenRecalls": 0, "visionScoreAdvantageLaneOpponent": 0.6190171241760254, "visionScorePerMinute": 0.823787890770322, "voidMonsterKill": 0, "wardTakedowns": 0, "wardTakedownsBefore20M": 0, "wardsGuarded": 1}, "champExperience": 12701, "champLevel": 14, "championId": 68, "championName": "Rumble", "championTransform": 0, "commandPings": 4, "consumablesPurchased": 5, "damageDealtToBuildings": 3122, "damageDealtToObjectives": 9762, "damageDealtToTurrets": 3122, "damageSelfMitigated": 16167, "dangerPings": 0, "deaths": 4, "detectorWardsPlaced": 3, "doubleKills": 1, "dragonKills": 0, "eligibleForProgression": true, "enemyMissingPings": 0, "enemyVisionPings": 0, "firstBloodAssist": false, "firstBloodKill": false, "firstTowerAssist": false, "firstTowerKill": false, "gameEndedInEarlySurrender": false, "gameEndedInSurrender": false, "getBackPings": 0, "goldEarned": 10903, "goldSpent": 10075, "holdPings": 0, "individualPosition": "TOP", "inhibitorKills": 0, "inhibitorTakedowns": 1, "inhibitorsLost": 0, "item0": 1026, "item1": 3111, "item2": 1052, "item3": 6653, "item4": 3916, "item5": 8010, "item6": 3363, "itemsPurchased": 20, "killingSprees": 1, "kills": 3, "lane": "TOP", "largestCriticalStrike": 0, "largestKillingSpree": 2, "largestMultiKill": 2, "longestTimeSpentLiving": 417, "magicDamageDealt": 92908, "magicDamageDealtToChampions": 23133, "magicDamageTaken": 10576, "missions": {"playerScore0": 0, "playerScore1": 0, "playerScore2": 0, "playerScore3": 0, "playerScore4": 0, "playerScore5": 0, "playerScore6": 0, "playerScore7": 0, "playerScore8": 0, "playerScore9": 0, "playerScore10": 0, "playerScore11": 0}, "needVisionPings": 0, "neutralMinionsKilled": 4, "nexusKills": 0, "nexusLost": 0, "nexusTakedowns": 1, "objectivesStolen": 0, "objectivesStolenAssists": 0, "onMyWayPings": 11, "participantId": 1, "pentaKills": 0, "perks": {"statPerks": {"defense": 5011, "flex": 5008, "offense": 5007}, "styles": [{"description": "primaryStyle", "selections": [{"perk": 8369, "var1": 618, "var2": 479, "var3": 0}, {"perk": 8321, "var1": 354, "var2": 0, "var3": 0}, {"perk": 8313, "var1": 3, "var2": 0, "var3": 0}, {"perk": 8347, "var1": 0, "var2": 0, "var3": 0}], "style": 8300}, {"description": "subStyle", "selections": [{"perk": 8210, "var1": 7, "var2": 0, "var3": 0}, {"perk": 8237, "var1": 629, "var2": 0, "var3": 0}], "style": 8200}]}, "physicalDamageDealt": 12612, "physicalDamageDealtToChampions": 756, "physicalDamageTaken": 8688, "placement": 0, "playerAugment1": 0, "playerAugment2": 0, "playerAugment3": 0, "playerAugment4": 0, "playerAugment5": 0, "playerAugment6": 0, "playerSubteamId": 0, "profileIcon": 29, "pushPings": 0, "puuid": "ocud99N_tPrNpm91ZUdcT8dGBnmw9yRozFyvz-bOQv4eUeiOh59kq-ksnFL9iK1uE9vRf_Cm-asQ4Q", "quadraKills": 0, "retreatPings": 0, "riotIdGameName": "qweasdx", "riotIdTagline": "EUW", "role": "SOLO", "sightWardsBoughtInGame": 0, "spell1Casts": 127, "spell2Casts": 163, "spell3Casts": 147, "spell4Casts": 9, "subteamPlacement": 0, "summoner1Casts": 2, "summoner1Id": 12, "summoner2Casts": 4, "summoner2Id": 4, "summonerId": "LLev7t4MYussxCpRJsF4HmMijwzdpqRp8cy_f7N-2mI7y0fQZXtiA5bgiQ", "summonerLevel": 537, "summonerName": "", "teamEarlySurrendered": false, "teamId": 100, "teamPosition": "TOP", "timeCCingOthers": 15, "timePlayed": 1653, "totalAllyJungleMinionsKilled": 2, "totalDamageDealt": 109417, "totalDamageDealtToChampions": 24595, "totalDamageShieldedOnTeammates": 0, "totalDamageTaken": 19658, "totalEnemyJungleMinionsKilled": 0, "totalHeal": 1510, "totalHealsOnTeammates": 0, "totalMinionsKilled": 175, "totalTimeCCDealt": 262, "totalTimeSpentDead": 109, "totalUnitsHealed": 1, "tripleKills": 0, "trueDamageDealt": 3896, "trueDamageDealtToChampions": 705, "trueDamageTaken": 393, "turretKills": 1, "turretTakedowns": 4, "turretsLost": 3, "unrealKills": 0, "visionClearedPings": 0, "visionScore": 22, "visionWardsBoughtInGame": 3, "wardsKilled": 0, "wardsPlaced": 11, "win": true}, {"PlayerScore0": 0, "PlayerScore1": 0, "PlayerScore10": 0, "PlayerScore11": 0, "PlayerScore2": 0, "PlayerScore3": 0, "PlayerScore4": 0, "PlayerScore5": 0, "PlayerScore6": 0, "PlayerScore7": 0, "PlayerScore8": 0, "PlayerScore9": 0, "allInPings": 0, "assistMePings": 0, "assists": 12, "baronKills": 0, "basicPings": 0, "challenges": {"12AssistStreakCount": 0, "HealFromMapSources": 211.28311157226562, "InfernalScalePickup": 0, "SWARM_DefeatAatrox": 0, "SWARM_DefeatBriar": 0, "SWARM_DefeatMiniBosses": 0, "SWARM_EvolveWeapon": 0, "SWARM_Have3Passives": 0, "SWARM_KillEnemy": 0, "SWARM_PickupGold": 0, "SWARM_ReachLevel50": 0, "SWARM_Survive15Min": 0, "SWARM_WinWith5EvolvedWeapons": 0, "abilityUses": 430, "acesBefore15Minutes": 0, "alliedJungleMonsterKills": 85, "baronTakedowns": 0, "blastConeOppositeOpponentCount": 0, "bountyGold": 293.010009765625, "buffsStolen": 2, "completeSupportQuestInTime": 0, "controlWardTimeCoverageInRiverOrEnemyHalf": 0.4319867099099415, "controlWardsPlaced": 4, "damagePerMinute": 586.5876815459276, "damageTakenOnTeamPercentage": 0.3342343207918086, "dancedWithRiftHerald": 0, "deathsByEnemyChamps": 3, "dodgeSkillShotsSmallWindow": 9, "doubleAces": 0, "dragonTakedowns": 1, "earliestDragonTakedown": 1474.5282599280001, "earlyLaningPhaseGoldExpAdvantage": 0, "effectiveHealAndShielding": 214.5223388671875, "elderDragonKillsWithOpposingSoul": 0, "elderDragonMultikills": 0, "enemyChampionImmobilizations": 39, "enemyJungleMonsterKills": 10, "epicMonsterKillsNearEnemyJungler": 0, "epicMonsterKillsWithin30SecondsOfSpawn": 1, "epicMonsterSteals": 0, "epicMonsterStolenWithoutSmite": 0, "firstTurretKilled": 1, "firstTurretKilledTime": 662.635772793, "fistBumpParticipation": 0, "flawlessAces": 0, "fullTeamTakedown": 7, "gameLength": 1653.095853474, "goldPerMinute": 481.5429065158986, "hadOpenNexus": 0, "immobilizeAndKillWithAlly": 15, "initialBuffCount": 2, "initialCrabCount": 0, "jungleCsBefore10Minutes": 66.00000005960464, "junglerKillsEarlyJungle": 0, "junglerTakedownsNearDamagedEpicMonster": 0, "kTurretsDestroyedBeforePlatesFall": 0, "kda": 7, "killAfterHiddenWithAlly": 3, "killParticipation": 0.8076923076923077, "killedChampTookFullTeamDamageSurvived": 0, "killingSprees": 1, "killsNearEnemyTurret": 1, "killsOnLanersEarlyJungleAsJungler": 1, "killsOnRecentlyHealedByAramPack": 0, "killsUnderOwnTurret": 0, "killsWithHelpFromEpicMonster": 0, "knockEnemyIntoTeamAndKill": 0, "landSkillShotsEarlyGame": 1, "laneMinionsFirst10Minutes": 0, "laningPhaseGoldExpAdvantage": 0, "legendaryCount": 0, "legendaryItemUsed": [3152, 4633, 6695], "lostAnInhibitor": 0, "maxCsAdvantageOnLaneOpponent": 48.50000002980232, "maxKillDeficit": 5, "maxLevelLeadLaneOpponent": 3, "mejaisFullStackInTime": 0, "moreEnemyJungleThanOpponent": -47.50000008940697, "multiKillOneSpell": 0, "multiTurretRiftHeraldCount": 0, "multikills": 3, "multikillsAfterAggressiveFlash": 1, "outerTurretExecutesBefore10Minutes": 0, "outnumberedKills": 1, "outnumberedNexusKill": 0, "perfectDragonSoulsTaken": 0, "perfectGame": 0, "pickKillWithAlly": 16, "playedChampSelectPosition": 1, "poroExplosions": 0, "quickCleanse": 0, "quickFirstTurret": 0, "quickSoloKills": 0, "riftHeraldTakedowns": 1, "saveAllyFromDeath": 0, "scuttleCrabKills": 4, "skillshotsDodged": 85, "skillshotsHit": 14, "snowballsHit": 0, "soloBaronKills": 0, "soloKills": 0, "stealthWardsPlaced": 4, "survivedSingleDigitHpCount": 0, "survivedThreeImmobilizesInFight": 9, "takedownOnFirstTurret": 0, "takedowns": 21, "takedownsAfterGainingLevelAdvantage": 0, "takedownsBeforeJungleMinionSpawn": 0, "takedownsFirstXMinutes": 5, "takedownsInAlcove": 1, "takedownsInEnemyFountain": 0, "teamBaronKills": 0, "teamDamagePercentage": 0.16466785619915753, "teamElderDragonKills": 0, "teamRiftHeraldKills": 1, "tookLargeDamageSurvived": 0, "turretPlatesTaken": 3, "turretTakedowns": 4, "turretsTakenWithRiftHerald": 5, "twentyMinionsIn3SecondsCount": 0, "twoWardsOneSweeperCount": 0, "unseenRecalls": 0, "visionScoreAdvantageLaneOpponent": 0.10543680191040039, "visionScorePerMinute": 1.015019345129749, "voidMonsterKill": 5, "wardTakedowns": 4, "wardTakedownsBefore20M": 1, "wardsGuarded": 1}, "champExperience": 14842, "champLevel": 16, "championId": 517, "championName": "Sylas", "championTransform": 0, "commandPings": 8, "consumablesPurchased": 6, "damageDealtToBuildings": 2515, "damageDealtToObjectives": 34757, "damageDealtToTurrets": 2515, "damageSelfMitigated": 22591, "dangerPings": 0, "deaths": 3, "detectorWardsPlaced": 4, "doubleKills": 2, "dragonKills": 1, "eligibleForProgression": true, "enemyMissingPings": 6, "enemyVisionPings": 5, "firstBloodAssist": false, "firstBloodKill": false, "firstTowerAssist": false, "firstTowerKill": false, "gameEndedInEarlySurrender": false, "gameEndedInSurrender": false, "getBackPings": 7, "goldEarned": 13267, "goldSpent": 11600, "holdPings": 0, "individualPosition": "JUNGLE", "inhibitorKills": 0, "inhibitorTakedowns": 1, "inhibitorsLost": 0, "item0": 3152, "item1": 2421, "item2": 0, "item3": 4633, "item4": 6695, "item5": 3111, "item6": 3364, "itemsPurchased": 23, "killingSprees": 1, "kills": 9, "lane": "JUNGLE", "largestCriticalStrike": 0, "largestKillingSpree": 7, "largestMultiKill": 3, "longestTimeSpentLiving": 407, "magicDamageDealt": 155308, "magicDamageDealtToChampions": 15729, "magicDamageTaken": 13125, "missions": {"playerScore0": 0, "playerScore1": 0, "playerScore2": 0, "playerScore3": 0, "playerScore4": 0, "playerScore5": 0, "playerScore6": 0, "playerScore7": 0, "playerScore8": 0, "playerScore9": 0, "playerScore10": 0, "playerScore11": 0}, "needVisionPings": 0, "neutralMinionsKilled": 177, "nexusKills": 0, "nexusLost": 0, "nexusTakedowns": 1, "objectivesStolen": 0, "objectivesStolenAssists": 0, "onMyWayPings": 22, "participantId": 2, "pentaKills": 0, "perks": {"statPerks": {"defense": 5001, "flex": 5008, "offense": 5007}, "styles": [{"description": "primaryStyle", "selections": [{"perk": 8010, "var1": 432, "var2": 0, "var3": 0}, {"perk": 9111, "var1": 1849, "var2": 420, "var3": 0}, {"perk": 9105, "var1": 12, "var2": 10, "var3": 0}, {"perk": 8299, "var1": 465, "var2": 0, "var3": 0}], "style": 8000}, {"description": "subStyle", "selections": [{"perk": 8304, "var1": 10, "var2": 3, "var3": 0}, {"perk": 8347, "var1": 0, "var2": 0, "var3": 0}], "style": 8300}]}, "physicalDamageDealt": 10649, "physicalDamageDealtToChampions": 189, "physicalDamageTaken": 25300, "placement": 0, "playerAugment1": 0, "playerAugment2": 0, "playerAugment3": 0, "playerAugment4": 0, "playerAugment5": 0, "playerAugment6": 0, "playerSubteamId": 0, "profileIcon": 586, "pushPings": 0, "puuid": "VeOp5LOX1cXcVAcTSDj1KcHG26uVAKQ-IhtRcdUZFG65ahxCMb3GvIjkfjWZF3BwTfIF0kWAsrqPTQ", "quadraKills": 0, "retreatPings": 0, "riotIdGameName": "Jankos", "riotIdTagline": "MYBAD", "role": "NONE", "sightWardsBoughtInGame": 0, "spell1Casts": 81, "spell2Casts": 108, "spell3Casts": 214, "spell4Casts": 27, "subteamPlacement": 0, "summoner1Casts": 15, "summoner1Id": 11, "summoner2Casts": 4, "summoner2Id": 4, "summonerId": "BJXWpUn0itEWJdzlC_FNUui5Kn57Jo9t2yQ9noVVtAliWss", "summonerLevel": 1075, "summonerName": "", "teamEarlySurrendered": false, "teamId": 100, "teamPosition": "JUNGLE", "timeCCingOthers": 33, "timePlayed": 1653, "totalAllyJungleMinionsKilled": 116, "totalDamageDealt": 241253, "totalDamageDealtToChampions": 16161, "totalDamageShieldedOnTeammates": 214, "totalDamageTaken": 39696, "totalEnemyJungleMinionsKilled": 24, "totalHeal": 22702, "totalHealsOnTeammates": 0, "totalMinionsKilled": 10, "totalTimeCCDealt": 380, "totalTimeSpentDead": 62, "totalUnitsHealed": 1, "tripleKills": 1, "trueDamageDealt": 75296, "trueDamageDealtToChampions": 242, "trueDamageTaken": 1269, "turretKills": 1, "turretTakedowns": 4, "turretsLost": 3, "unrealKills": 0, "visionClearedPings": 0, "visionScore": 27, "visionWardsBoughtInGame": 4, "wardsKilled": 4, "wardsPlaced": 8, "win": true}, {"PlayerScore0": 0, "PlayerScore1": 0, "PlayerScore10": 0, "PlayerScore11": 0, "PlayerScore2": 0, "PlayerScore3": 0, "PlayerScore4": 0, "PlayerScore5": 0, "PlayerScore6": 0, "PlayerScore7": 0, "PlayerScore8": 0, "PlayerScore9": 0, "allInPings": 0, "assistMePings": 5, "assists": 11, "baronKills": 0, "basicPings": 0, "challenges": {"12AssistStreakCount": 0, "HealFromMapSources": 176, "InfernalScalePickup": 0, "SWARM_DefeatAatrox": 0, "SWARM_DefeatBriar": 0, "SWARM_DefeatMiniBosses": 0, "SWARM_EvolveWeapon": 0, "SWARM_Have3Passives": 0, "SWARM_KillEnemy": 0, "SWARM_PickupGold": 0, "SWARM_ReachLevel50": 0, "SWARM_Survive15Min": 0, "SWARM_WinWith5EvolvedWeapons": 0, "abilityUses": 154, "acesBefore15Minutes": 0, "alliedJungleMonsterKills": 0, "baronTakedowns": 0, "blastConeOppositeOpponentCount": 0, "bountyGold": 0, "buffsStolen": 0, "completeSupportQuestInTime": 0, "controlWardsPlaced": 1, "damagePerMinute": 919.5629284702025, "damageTakenOnTeamPercentage": 0.1863437461573062, "dancedWithRiftHerald": 0, "deathsByEnemyChamps": 3, "dodgeSkillShotsSmallWindow": 4, "doubleAces": 0, "dragonTakedowns": 1, "earliestDragonTakedown": 1474.5282599280001, "earlyLaningPhaseGoldExpAdvantage": 0, "effectiveHealAndShielding": 0, "elderDragonKillsWithOpposingSoul": 0, "elderDragonMultikills": 0, "enemyChampionImmobilizations": 10, "enemyJungleMonsterKills": 0, "epicMonsterKillsNearEnemyJungler": 0, "epicMonsterKillsWithin30SecondsOfSpawn": 0, "epicMonsterSteals": 0, "epicMonsterStolenWithoutSmite": 0, "firstTurretKilled": 1, "firstTurretKilledTime": 662.635772793, "fistBumpParticipation": 0, "flawlessAces": 0, "fullTeamTakedown": 7, "gameLength": 1653.095853474, "getTakedownsInAllLanesEarlyJungleAsLaner": 0, "goldPerMinute": 469.6599819776943, "hadOpenNexus": 0, "immobilizeAndKillWithAlly": 2, "initialBuffCount": 0, "initialCrabCount": 0, "jungleCsBefore10Minutes": 0, "junglerTakedownsNearDamagedEpicMonster": 0, "kTurretsDestroyedBeforePlatesFall": 1, "kda": 5.333333333333333, "killAfterHiddenWithAlly": 3, "killParticipation": 0.6153846153846154, "killedChampTookFullTeamDamageSurvived": 0, "killingSprees": 0, "killsNearEnemyTurret": 0, "killsOnOtherLanesEarlyJungleAsLaner": 0, "killsOnRecentlyHealedByAramPack": 0, "killsUnderOwnTurret": 0, "killsWithHelpFromEpicMonster": 0, "knockEnemyIntoTeamAndKill": 2, "landSkillShotsEarlyGame": 0, "laneMinionsFirst10Minutes": 90, "laningPhaseGoldExpAdvantage": 0, "legendaryCount": 0, "legendaryItemUsed": [3032, 6675, 3036], "lostAnInhibitor": 0, "maxCsAdvantageOnLaneOpponent": 51, "maxKillDeficit": 5, "maxLevelLeadLaneOpponent": 3, "mejaisFullStackInTime": 0, "moreEnemyJungleThanOpponent": 0, "multiKillOneSpell": 0, "multiTurretRiftHeraldCount": 0, "multikills": 0, "multikillsAfterAggressiveFlash": 0, "outerTurretExecutesBefore10Minutes": 0, "outnumberedKills": 1, "outnumberedNexusKill": 0, "perfectDragonSoulsTaken": 0, "perfectGame": 0, "pickKillWithAlly": 11, "playedChampSelectPosition": 1, "poroExplosions": 0, "quickCleanse": 0, "quickFirstTurret": 0, "quickSoloKills": 0, "riftHeraldTakedowns": 0, "saveAllyFromDeath": 0, "scuttleCrabKills": 0, "skillshotsDodged": 54, "skillshotsHit": 0, "snowballsHit": 0, "soloBaronKills": 0, "soloKills": 1, "soloTurretsLategame": 1, "stealthWardsPlaced": 4, "survivedSingleDigitHpCount": 0, "survivedThreeImmobilizesInFight": 4, "takedownOnFirstTurret": 1, "takedowns": 16, "takedownsAfterGainingLevelAdvantage": 0, "takedownsBeforeJungleMinionSpawn": 0, "takedownsFirstXMinutes": 2, "takedownsInAlcove": 1, "takedownsInEnemyFountain": 0, "teamBaronKills": 0, "teamDamagePercentage": 0.25814121372671833, "teamElderDragonKills": 0, "teamRiftHeraldKills": 1, "teleportTakedowns": 1, "tookLargeDamageSurvived": 0, "turretPlatesTaken": 6, "turretTakedowns": 7, "turretsTakenWithRiftHerald": 5, "twentyMinionsIn3SecondsCount": 0, "twoWardsOneSweeperCount": 0, "unseenRecalls": 0, "visionScoreAdvantageLaneOpponent": -0.38351279497146606, "visionScorePerMinute": 0.4677651164122179, "voidMonsterKill": 1, "wardTakedowns": 1, "wardTakedownsBefore20M": 0, "wardsGuarded": 1}, "champExperience": 13982, "champLevel": 15, "championId": 18, "championName": "Tristana", "championTransform": 0, "commandPings": 18, "consumablesPurchased": 2, "damageDealtToBuildings": 17853, "damageDealtToObjectives": 20373, "damageDealtToTurrets": 17853, "damageSelfMitigated": 13030, "dangerPings": 0, "deaths": 3, "detectorWardsPlaced": 1, "doubleKills": 0, "dragonKills": 0, "eligibleForProgression": true, "enemyMissingPings": 8, "enemyVisionPings": 0, "firstBloodAssist": false, "firstBloodKill": false, "firstTowerAssist": false, "firstTowerKill": true, "gameEndedInEarlySurrender": false, "gameEndedInSurrender": false, "getBackPings": 17, "goldEarned": 12939, "goldSpent": 11900, "holdPings": 0, "individualPosition": "MIDDLE", "inhibitorKills": 0, "inhibitorTakedowns": 1, "inhibitorsLost": 0, "item0": 6675, "item1": 3036, "item2": 3032, "item3": 1055, "item4": 1037, "item5": 3111, "item6": 3363, "itemsPurchased": 21, "killingSprees": 2, "kills": 5, "lane": "MIDDLE", "largestCriticalStrike": 423, "largestKillingSpree": 2, "largestMultiKill": 1, "longestTimeSpentLiving": 901, "magicDamageDealt": 20909, "magicDamageDealtToChampions": 2173, "magicDamageTaken": 11026, "missions": {"playerScore0": 0, "playerScore1": 0, "playerScore2": 0, "playerScore3": 0, "playerScore4": 0, "playerScore5": 0, "playerScore6": 0, "playerScore7": 0, "playerScore8": 0, "playerScore9": 0, "playerScore10": 0, "playerScore11": 0}, "needVisionPings": 0, "neutralMinionsKilled": 0, "nexusKills": 0, "nexusLost": 0, "nexusTakedowns": 1, "objectivesStolen": 0, "objectivesStolenAssists": 0, "onMyWayPings": 40, "participantId": 3, "pentaKills": 0, "perks": {"statPerks": {"defense": 5011, "flex": 5008, "offense": 5005}, "styles": [{"description": "primaryStyle", "selections": [{"perk": 8008, "var1": 934, "var2": 934, "var3": 0}, {"perk": 9111, "var1": 1490, "var2": 320, "var3": 0}, {"perk": 9103, "var1": 20, "var2": 10, "var3": 0}, {"perk": 8017, "var1": 1152, "var2": 0, "var3": 0}], "style": 8000}, {"description": "subStyle", "selections": [{"perk": 8446, "var1": 3179, "var2": 0, "var3": 0}, {"perk": 8429, "var1": 56, "var2": 10, "var3": 10}], "style": 8400}]}, "physicalDamageDealt": 109997, "physicalDamageDealtToChampions": 23162, "physicalDamageTaken": 10478, "placement": 0, "playerAugment1": 0, "playerAugment2": 0, "playerAugment3": 0, "playerAugment4": 0, "playerAugment5": 0, "playerAugment6": 0, "playerSubteamId": 0, "profileIcon": 5917, "pushPings": 1, "puuid": "7ryUBvQsJxNmEj0gaQPZNrT8w9SuMbuyV0YHTkODmMGKE8OPlf3zFs7skaLsv6i1dIfYXVGvH0BOvQ", "quadraKills": 0, "retreatPings": 0, "riotIdGameName": "Kenal", "riotIdTagline": "EUW", "role": "SOLO", "sightWardsBoughtInGame": 0, "spell1Casts": 54, "spell2Casts": 43, "spell3Casts": 51, "spell4Casts": 6, "subteamPlacement": 0, "summoner1Casts": 2, "summoner1Id": 4, "summoner2Casts": 5, "summoner2Id": 12, "summonerId": "aUZTePrvcK7cUprX4Q9grb0NXRsRhjLc_9qub5ujMCxDwS4", "summonerLevel": 885, "summonerName": "", "teamEarlySurrendered": false, "teamId": 100, "teamPosition": "MIDDLE", "timeCCingOthers": 4, "timePlayed": 1652, "totalAllyJungleMinionsKilled": 0, "totalDamageDealt": 131849, "totalDamageDealtToChampions": 25335, "totalDamageShieldedOnTeammates": 0, "totalDamageTaken": 22131, "totalEnemyJungleMinionsKilled": 0, "totalHeal": 8596, "totalHealsOnTeammates": 0, "totalMinionsKilled": 186, "totalTimeCCDealt": 69, "totalTimeSpentDead": 112, "totalUnitsHealed": 1, "tripleKills": 0, "trueDamageDealt": 942, "trueDamageDealtToChampions": 0, "trueDamageTaken": 627, "turretKills": 3, "turretTakedowns": 7, "turretsLost": 3, "unrealKills": 0, "visionClearedPings": 0, "visionScore": 12, "visionWardsBoughtInGame": 1, "wardsKilled": 1, "wardsPlaced": 9, "win": true}, {"PlayerScore0": 0, "PlayerScore1": 0, "PlayerScore10": 0, "PlayerScore11": 0, "PlayerScore2": 0, "PlayerScore3": 0, "PlayerScore4": 0, "PlayerScore5": 0, "PlayerScore6": 0, "PlayerScore7": 0, "PlayerScore8": 0, "PlayerScore9": 0, "allInPings": 0, "assistMePings": 0, "assists": 10, "baronKills": 0, "basicPings": 0, "challenges": {"12AssistStreakCount": 0, "HealFromMapSources": 496, "InfernalScalePickup": 0, "SWARM_DefeatAatrox": 0, "SWARM_DefeatBriar": 0, "SWARM_DefeatMiniBosses": 0, "SWARM_EvolveWeapon": 0, "SWARM_Have3Passives": 0, "SWARM_KillEnemy": 0, "SWARM_PickupGold": 0, "SWARM_ReachLevel50": 0, "SWARM_Survive15Min": 0, "SWARM_WinWith5EvolvedWeapons": 0, "abilityUses": 394, "acesBefore15Minutes": 0, "alliedJungleMonsterKills": 0, "baronTakedowns": 0, "blastConeOppositeOpponentCount": 0, "bountyGold": 0, "buffsStolen": 0, "completeSupportQuestInTime": 0, "controlWardTimeCoverageInRiverOrEnemyHalf": 0.08649199532472764, "controlWardsPlaced": 1, "damagePerMinute": 920.291887447365, "damageTakenOnTeamPercentage": 0.1175276911375163, "dancedWithRiftHerald": 0, "deathsByEnemyChamps": 3, "dodgeSkillShotsSmallWindow": 4, "doubleAces": 0, "dragonTakedowns": 1, "earliestDragonTakedown": 1474.5282599280001, "earlyLaningPhaseGoldExpAdvantage": 0, "effectiveHealAndShielding": 0, "elderDragonKillsWithOpposingSoul": 0, "elderDragonMultikills": 0, "enemyChampionImmobilizations": 1, "enemyJungleMonsterKills": 0, "epicMonsterKillsNearEnemyJungler": 0, "epicMonsterKillsWithin30SecondsOfSpawn": 0, "epicMonsterSteals": 0, "epicMonsterStolenWithoutSmite": 0, "firstTurretKilled": 1, "firstTurretKilledTime": 662.635772793, "fistBumpParticipation": 0, "flawlessAces": 0, "fullTeamTakedown": 7, "gameLength": 1653.095853474, "getTakedownsInAllLanesEarlyJungleAsLaner": 0, "goldPerMinute": 423.69168568059445, "hadOpenNexus": 0, "immobilizeAndKillWithAlly": 1, "initialBuffCount": 0, "initialCrabCount": 0, "jungleCsBefore10Minutes": 0, "junglerTakedownsNearDamagedEpicMonster": 0, "kTurretsDestroyedBeforePlatesFall": 0, "kda": 5.333333333333333, "killAfterHiddenWithAlly": 2, "killParticipation": 0.6153846153846154, "killedChampTookFullTeamDamageSurvived": 0, "killingSprees": 1, "killsNearEnemyTurret": 1, "killsOnOtherLanesEarlyJungleAsLaner": 0, "killsOnRecentlyHealedByAramPack": 0, "killsUnderOwnTurret": 0, "killsWithHelpFromEpicMonster": 0, "knockEnemyIntoTeamAndKill": 1, "landSkillShotsEarlyGame": 22, "laneMinionsFirst10Minutes": 64, "laningPhaseGoldExpAdvantage": 0, "legendaryCount": 0, "legendaryItemUsed": [3078, 3004, 3042, 6699], "lostAnInhibitor": 0, "maxCsAdvantageOnLaneOpponent": 23, "maxKillDeficit": 5, "maxLevelLeadLaneOpponent": 2, "mejaisFullStackInTime": 0, "moreEnemyJungleThanOpponent": 0, "multiKillOneSpell": 0, "multiTurretRiftHeraldCount": 0, "multikills": 1, "multikillsAfterAggressiveFlash": 0, "outerTurretExecutesBefore10Minutes": 0, "outnumberedKills": 1, "outnumberedNexusKill": 0, "perfectDragonSoulsTaken": 0, "perfectGame": 0, "pickKillWithAlly": 11, "playedChampSelectPosition": 1, "poroExplosions": 0, "quickCleanse": 1, "quickFirstTurret": 0, "quickSoloKills": 0, "riftHeraldTakedowns": 1, "saveAllyFromDeath": 0, "scuttleCrabKills": 0, "skillshotsDodged": 76, "skillshotsHit": 99, "snowballsHit": 0, "soloBaronKills": 0, "soloKills": 1, "stealthWardsPlaced": 4, "survivedSingleDigitHpCount": 0, "survivedThreeImmobilizesInFight": 2, "takedownOnFirstTurret": 0, "takedowns": 16, "takedownsAfterGainingLevelAdvantage": 0, "takedownsBeforeJungleMinionSpawn": 0, "takedownsFirstXMinutes": 4, "takedownsInAlcove": 0, "takedownsInEnemyFountain": 0, "teamBaronKills": 0, "teamDamagePercentage": 0.25834584828656815, "teamElderDragonKills": 0, "teamRiftHeraldKills": 1, "tookLargeDamageSurvived": 0, "turretPlatesTaken": 0, "turretTakedowns": 4, "turretsTakenWithRiftHerald": 5, "twentyMinionsIn3SecondsCount": 0, "twoWardsOneSweeperCount": 0, "unseenRecalls": 0, "visionScoreAdvantageLaneOpponent": -0.24456465244293213, "visionScorePerMinute": 0.6314833986770045, "voidMonsterKill": 1, "wardTakedowns": 6, "wardTakedownsBefore20M": 4, "wardsGuarded": 0}, "champExperience": 13662, "champLevel": 15, "championId": 81, "championName": "Ezreal", "championTransform": 0, "commandPings": 0, "consumablesPurchased": 2, "damageDealtToBuildings": 4887, "damageDealtToObjectives": 10631, "damageDealtToTurrets": 4887, "damageSelfMitigated": 5059, "dangerPings": 0, "deaths": 3, "detectorWardsPlaced": 1, "doubleKills": 1, "dragonKills": 0, "eligibleForProgression": true, "enemyMissingPings": 3, "enemyVisionPings": 8, "firstBloodAssist": false, "firstBloodKill": false, "firstTowerAssist": false, "firstTowerKill": false, "gameEndedInEarlySurrender": false, "gameEndedInSurrender": false, "getBackPings": 0, "goldEarned": 11673, "goldSpent": 10408, "holdPings": 0, "individualPosition": "BOTTOM", "inhibitorKills": 1, "inhibitorTakedowns": 1, "inhibitorsLost": 0, "item0": 0, "item1": 3042, "item2": 3078, "item3": 3158, "item4": 6699, "item5": 1055, "item6": 3363, "itemsPurchased": 21, "killingSprees": 1, "kills": 6, "lane": "BOTTOM", "largestCriticalStrike": 0, "largestKillingSpree": 4, "largestMultiKill": 2, "longestTimeSpentLiving": 481, "magicDamageDealt": 17047, "magicDamageDealtToChampions": 7417, "magicDamageTaken": 5638, "missions": {"playerScore0": 0, "playerScore1": 0, "playerScore2": 0, "playerScore3": 0, "playerScore4": 0, "playerScore5": 0, "playerScore6": 0, "playerScore7": 0, "playerScore8": 0, "playerScore9": 0, "playerScore10": 0, "playerScore11": 0}, "needVisionPings": 0, "neutralMinionsKilled": 0, "nexusKills": 1, "nexusLost": 0, "nexusTakedowns": 1, "objectivesStolen": 0, "objectivesStolenAssists": 0, "onMyWayPings": 3, "participantId": 4, "pentaKills": 0, "perks": {"statPerks": {"defense": 5011, "flex": 5008, "offense": 5005}, "styles": [{"description": "primaryStyle", "selections": [{"perk": 8005, "var1": 1236, "var2": 1236, "var3": 0}, {"perk": 8009, "var1": 4034, "var2": 0, "var3": 0}, {"perk": 9105, "var1": 15, "var2": 20, "var3": 0}, {"perk": 8017, "var1": 1114, "var2": 0, "var3": 0}], "style": 8000}, {"description": "subStyle", "selections": [{"perk": 8316, "var1": 8, "var2": 10, "var3": 0}, {"perk": 8304, "var1": 10, "var2": 3, "var3": 0}], "style": 8300}]}, "physicalDamageDealt": 130459, "physicalDamageDealtToChampions": 17494, "physicalDamageTaken": 8256, "placement": 0, "playerAugment1": 0, "playerAugment2": 0, "playerAugment3": 0, "playerAugment4": 0, "playerAugment5": 0, "playerAugment6": 0, "playerSubteamId": 0, "profileIcon": 22, "pushPings": 0, "puuid": "XPqCQDRzqrCoYYtERbi-u50g9bqO1Evdo7o5jRuZDU_U8qvCTllHH4rk1bpOXQBxXeqgXcgb27Brag", "quadraKills": 0, "retreatPings": 0, "riotIdGameName": "FEBIVEN", "riotIdTagline": "EUWW", "role": "CARRY", "sightWardsBoughtInGame": 0, "spell1Casts": 285, "spell2Casts": 56, "spell3Casts": 39, "spell4Casts": 14, "subteamPlacement": 0, "summoner1Casts": 3, "summoner1Id": 4, "summoner2Casts": 5, "summoner2Id": 1, "summonerId": "XqNI1pthcp_rT-vvP-iNzmruwOezlwxO315mMrl_Cny4QHo", "summonerLevel": 497, "summonerName": "", "teamEarlySurrendered": false, "teamId": 100, "teamPosition": "BOTTOM", "timeCCingOthers": 5, "timePlayed": 1652, "totalAllyJungleMinionsKilled": 0, "totalDamageDealt": 158941, "totalDamageDealtToChampions": 25355, "totalDamageShieldedOnTeammates": 0, "totalDamageTaken": 13958, "totalEnemyJungleMinionsKilled": 0, "totalHeal": 3231, "totalHealsOnTeammates": 0, "totalMinionsKilled": 228, "totalTimeCCDealt": 92, "totalTimeSpentDead": 68, "totalUnitsHealed": 1, "tripleKills": 0, "trueDamageDealt": 11433, "trueDamageDealtToChampions": 442, "trueDamageTaken": 64, "turretKills": 3, "turretTakedowns": 4, "turretsLost": 3, "unrealKills": 0, "visionClearedPings": 0, "visionScore": 17, "visionWardsBoughtInGame": 1, "wardsKilled": 6, "wardsPlaced": 10, "win": true}, {"PlayerScore0": 0, "PlayerScore1": 0, "PlayerScore10": 0, "PlayerScore11": 0, "PlayerScore2": 0, "PlayerScore3": 0, "PlayerScore4": 0, "PlayerScore5": 0, "PlayerScore6": 0, "PlayerScore7": 0, "PlayerScore8": 0, "PlayerScore9": 0, "allInPings": 2, "assistMePings": 5, "assists": 20, "baronKills": 0, "basicPings": 0, "challenges": {"12AssistStreakCount": 0, "HealFromMapSources": 750.6145935058594, "InfernalScalePickup": 0, "SWARM_DefeatAatrox": 0, "SWARM_DefeatBriar": 0, "SWARM_DefeatMiniBosses": 0, "SWARM_EvolveWeapon": 0, "SWARM_Have3Passives": 0, "SWARM_KillEnemy": 0, "SWARM_PickupGold": 0, "SWARM_ReachLevel50": 0, "SWARM_Survive15Min": 0, "SWARM_WinWith5EvolvedWeapons": 0, "abilityUses": 178, "acesBefore15Minutes": 0, "alliedJungleMonsterKills": 0, "baronTakedowns": 0, "blastConeOppositeOpponentCount": 0, "bountyGold": 0, "buffsStolen": 0, "completeSupportQuestInTime": 0, "controlWardTimeCoverageInRiverOrEnemyHalf": 0.22381255511558823, "controlWardsPlaced": 7, "damagePerMinute": 243.09807154738021, "damageTakenOnTeamPercentage": 0.19637176937756778, "dancedWithRiftHerald": 0, "deathsByEnemyChamps": 4, "dodgeSkillShotsSmallWindow": 5, "doubleAces": 0, "dragonTakedowns": 0, "earlyLaningPhaseGoldExpAdvantage": 0, "effectiveHealAndShielding": 14338.755859375, "elderDragonKillsWithOpposingSoul": 0, "elderDragonMultikills": 0, "enemyChampionImmobilizations": 33, "enemyJungleMonsterKills": 0, "epicMonsterKillsNearEnemyJungler": 0, "epicMonsterKillsWithin30SecondsOfSpawn": 0, "epicMonsterSteals": 0, "epicMonsterStolenWithoutSmite": 0, "firstTurretKilled": 1, "firstTurretKilledTime": 662.635772793, "fistBumpParticipation": 0, "flawlessAces": 0, "fullTeamTakedown": 7, "gameLength": 1653.095853474, "getTakedownsInAllLanesEarlyJungleAsLaner": 0, "goldPerMinute": 312.75065829955, "hadOpenNexus": 0, "highestWardKills": 1, "immobilizeAndKillWithAlly": 12, "initialBuffCount": 0, "initialCrabCount": 0, "jungleCsBefore10Minutes": 0, "junglerTakedownsNearDamagedEpicMonster": 1, "kTurretsDestroyedBeforePlatesFall": 0, "kda": 5.75, "killAfterHiddenWithAlly": 4, "killParticipation": 0.8846153846153846, "killedChampTookFullTeamDamageSurvived": 0, "killingSprees": 0, "killsNearEnemyTurret": 1, "killsOnOtherLanesEarlyJungleAsLaner": 0, "killsOnRecentlyHealedByAramPack": 0, "killsUnderOwnTurret": 0, "killsWithHelpFromEpicMonster": 0, "knockEnemyIntoTeamAndKill": 0, "landSkillShotsEarlyGame": 2, "laneMinionsFirst10Minutes": 12, "laningPhaseGoldExpAdvantage": 0, "legendaryCount": 0, "legendaryItemUsed": [3107, 3876, 3222], "lostAnInhibitor": 0, "maxCsAdvantageOnLaneOpponent": 5, "maxKillDeficit": 5, "maxLevelLeadLaneOpponent": 1, "mejaisFullStackInTime": 0, "moreEnemyJungleThanOpponent": 0, "multiKillOneSpell": 0, "multiTurretRiftHeraldCount": 0, "multikills": 0, "multikillsAfterAggressiveFlash": 0, "outerTurretExecutesBefore10Minutes": 0, "outnumberedKills": 0, "outnumberedNexusKill": 0, "perfectDragonSoulsTaken": 0, "perfectGame": 0, "pickKillWithAlly": 18, "playedChampSelectPosition": 1, "poroExplosions": 0, "quickCleanse": 0, "quickFirstTurret": 0, "quickSoloKills": 0, "riftHeraldTakedowns": 0, "saveAllyFromDeath": 1, "scuttleCrabKills": 0, "skillshotsDodged": 79, "skillshotsHit": 23, "snowballsHit": 0, "soloBaronKills": 0, "soloKills": 0, "stealthWardsPlaced": 29, "survivedSingleDigitHpCount": 0, "survivedThreeImmobilizesInFight": 11, "takedownOnFirstTurret": 0, "takedowns": 23, "takedownsAfterGainingLevelAdvantage": 0, "takedownsBeforeJungleMinionSpawn": 0, "takedownsFirstXMinutes": 5, "takedownsInAlcove": 0, "takedownsInEnemyFountain": 0, "teamBaronKills": 0, "teamDamagePercentage": 0.06824288942167682, "teamElderDragonKills": 0, "teamRiftHeraldKills": 1, "tookLargeDamageSurvived": 0, "turretPlatesTaken": 0, "turretTakedowns": 3, "turretsTakenWithRiftHerald": 5, "twentyMinionsIn3SecondsCount": 0, "twoWardsOneSweeperCount": 0, "unseenRecalls": 0, "visionScoreAdvantageLaneOpponent": 0.8190463781356812, "visionScorePerMinute": 2.8967078687774817, "voidMonsterKill": 0, "wardTakedowns": 11, "wardTakedownsBefore20M": 7, "wardsGuarded": 2}, "champExperience": 8967, "champLevel": 12, "championId": 497, "championName": "Rakan", "championTransform": 0, "commandPings": 9, "consumablesPurchased": 9, "damageDealtToBuildings": 700, "damageDealtToObjectives": 1986, "damageDealtToTurrets": 700, "damageSelfMitigated": 16375, "dangerPings": 0, "deaths": 4, "detectorWardsPlaced": 7, "doubleKills": 0, "dragonKills": 0, "eligibleForProgression": true, "enemyMissingPings": 13, "enemyVisionPings": 15, "firstBloodAssist": false, "firstBloodKill": false, "firstTowerAssist": false, "firstTowerKill": false, "gameEndedInEarlySurrender": false, "gameEndedInSurrender": false, "getBackPings": 10, "goldEarned": 8616, "goldSpent": 8075, "holdPings": 0, "individualPosition": "UTILITY", "inhibitorKills": 0, "inhibitorTakedowns": 0, "inhibitorsLost": 0, "item0": 3876, "item1": 3107, "item2": 3222, "item3": 0, "item4": 3067, "item5": 3111, "item6": 3364, "itemsPurchased": 25, "killingSprees": 0, "kills": 3, "lane": "BOTTOM", "largestCriticalStrike": 0, "largestKillingSpree": 0, "largestMultiKill": 1, "longestTimeSpentLiving": 437, "magicDamageDealt": 9253, "magicDamageDealtToChampions": 4039, "magicDamageTaken": 10580, "missions": {"playerScore0": 0, "playerScore1": 0, "playerScore2": 0, "playerScore3": 0, "playerScore4": 0, "playerScore5": 0, "playerScore6": 0, "playerScore7": 0, "playerScore8": 0, "playerScore9": 0, "playerScore10": 0, "playerScore11": 0}, "needVisionPings": 5, "neutralMinionsKilled": 0, "nexusKills": 0, "nexusLost": 0, "nexusTakedowns": 1, "objectivesStolen": 0, "objectivesStolenAssists": 0, "onMyWayPings": 29, "participantId": 5, "pentaKills": 0, "perks": {"statPerks": {"defense": 5011, "flex": 5008, "offense": 5007}, "styles": [{"description": "primaryStyle", "selections": [{"perk": 8360, "var1": 8, "var2": 0, "var3": 0}, {"perk": 8306, "var1": 5, "var2": 0, "var3": 0}, {"perk": 8345, "var1": 3, "var2": 0, "var3": 193}, {"perk": 8347, "var1": 0, "var2": 0, "var3": 0}], "style": 8300}, {"description": "subStyle", "selections": [{"perk": 8106, "var1": 5, "var2": 31, "var3": 0}, {"perk": 8141, "var1": 16, "var2": 0, "var3": 0}], "style": 8100}]}, "physicalDamageDealt": 6413, "physicalDamageDealtToChampions": 1572, "physicalDamageTaken": 11029, "placement": 0, "playerAugment1": 0, "playerAugment2": 0, "playerAugment3": 0, "playerAugment4": 0, "playerAugment5": 0, "playerAugment6": 0, "playerSubteamId": 0, "profileIcon": 6770, "pushPings": 8, "puuid": "g0JSrepvy1Htftm-j3Dewr1UoLf_IDxcQVTDnmr6A_hVGt9_arAPdT35V8q2NwsWVIAK73CKGtVf7A", "quadraKills": 0, "retreatPings": 4, "riotIdGameName": "Yoms", "riotIdTagline": "111", "role": "SUPPORT", "sightWardsBoughtInGame": 0, "spell1Casts": 47, "spell2Casts": 66, "spell3Casts": 56, "spell4Casts": 9, "subteamPlacement": 0, "summoner1Casts": 12, "summoner1Id": 4, "summoner2Casts": 11, "summoner2Id": 7, "summonerId": "ducQs4TLqFNTk_gD75kfly2zZXM2wMrES46rZllIpYLTUdM", "summonerLevel": 1001, "summonerName": "", "teamEarlySurrendered": false, "teamId": 100, "teamPosition": "UTILITY", "timeCCingOthers": 34, "timePlayed": 1652, "totalAllyJungleMinionsKilled": 0, "totalDamageDealt": 19527, "totalDamageDealtToChampions": 6697, "totalDamageShieldedOnTeammates": 2979, "totalDamageTaken": 23322, "totalEnemyJungleMinionsKilled": 0, "totalHeal": 21284, "totalHealsOnTeammates": 11359, "totalMinionsKilled": 28, "totalTimeCCDealt": 108, "totalTimeSpentDead": 69, "totalUnitsHealed": 12, "tripleKills": 0, "trueDamageDealt": 3860, "trueDamageDealtToChampions": 1086, "trueDamageTaken": 1712, "turretKills": 1, "turretTakedowns": 3, "turretsLost": 3, "unrealKills": 0, "visionClearedPings": 0, "visionScore": 79, "visionWardsBoughtInGame": 7, "wardsKilled": 11, "wardsPlaced": 36, "win": true}, {"PlayerScore0": 0, "PlayerScore1": 0, "PlayerScore10": 0, "PlayerScore11": 0, "PlayerScore2": 0, "PlayerScore3": 0, "PlayerScore4": 0, "PlayerScore5": 0, "PlayerScore6": 0, "PlayerScore7": 0, "PlayerScore8": 0, "PlayerScore9": 0, "allInPings": 0, "assistMePings": 3, "assists": 1, "baronKills": 0, "basicPings": 0, "challenges": {"12AssistStreakCount": 0, "HealFromMapSources": 0, "InfernalScalePickup": 0, "SWARM_DefeatAatrox": 0, "SWARM_DefeatBriar": 0, "SWARM_DefeatMiniBosses": 0, "SWARM_EvolveWeapon": 0, "SWARM_Have3Passives": 0, "SWARM_KillEnemy": 0, "SWARM_PickupGold": 0, "SWARM_ReachLevel50": 0, "SWARM_Survive15Min": 0, "SWARM_WinWith5EvolvedWeapons": 0, "abilityUses": 179, "acesBefore15Minutes": 0, "alliedJungleMonsterKills": 0, "baronTakedowns": 0, "blastConeOppositeOpponentCount": 0, "bountyGold": 0, "buffsStolen": 0, "completeSupportQuestInTime": 0, "controlWardsPlaced": 0, "damagePerMinute": 678.1788994307296, "damageTakenOnTeamPercentage": 0.31071398940230194, "dancedWithRiftHerald": 0, "deathsByEnemyChamps": 5, "dodgeSkillShotsSmallWindow": 0, "doubleAces": 0, "dragonTakedowns": 0, "earlyLaningPhaseGoldExpAdvantage": 0, "effectiveHealAndShielding": 732.311767578125, "elderDragonKillsWithOpposingSoul": 0, "elderDragonMultikills": 0, "enemyChampionImmobilizations": 28, "enemyJungleMonsterKills": 0, "epicMonsterKillsNearEnemyJungler": 0, "epicMonsterKillsWithin30SecondsOfSpawn": 0, "epicMonsterSteals": 0, "epicMonsterStolenWithoutSmite": 0, "firstTurretKilled": 0, "fistBumpParticipation": 0, "flawlessAces": 0, "fullTeamTakedown": 1, "gameLength": 1653.095853474, "getTakedownsInAllLanesEarlyJungleAsLaner": 0, "goldPerMinute": 336.1571319471222, "hadOpenNexus": 0, "immobilizeAndKillWithAlly": 2, "initialBuffCount": 0, "initialCrabCount": 0, "jungleCsBefore10Minutes": 0, "junglerTakedownsNearDamagedEpicMonster": 0, "kTurretsDestroyedBeforePlatesFall": 0, "kda": 1, "killAfterHiddenWithAlly": 0, "killParticipation": 0.29411764705882354, "killedChampTookFullTeamDamageSurvived": 0, "killingSprees": 0, "killsNearEnemyTurret": 1, "killsOnOtherLanesEarlyJungleAsLaner": 0, "killsOnRecentlyHealedByAramPack": 0, "killsUnderOwnTurret": 1, "killsWithHelpFromEpicMonster": 0, "knockEnemyIntoTeamAndKill": 1, "landSkillShotsEarlyGame": 7, "laneMinionsFirst10Minutes": 74, "laningPhaseGoldExpAdvantage": 0, "legendaryCount": 0, "legendaryItemUsed": [3084, 4633], "lostAnInhibitor": 0, "maxCsAdvantageOnLaneOpponent": 0, "maxKillDeficit": 0, "maxLevelLeadLaneOpponent": 1, "mejaisFullStackInTime": 0, "moreEnemyJungleThanOpponent": 0, "multiKillOneSpell": 0, "multiTurretRiftHeraldCount": 0, "multikills": 0, "multikillsAfterAggressiveFlash": 0, "outerTurretExecutesBefore10Minutes": 0, "outnumberedKills": 0, "outnumberedNexusKill": 0, "perfectDragonSoulsTaken": 0, "perfectGame": 0, "pickKillWithAlly": 4, "playedChampSelectPosition": 1, "poroExplosions": 0, "quickCleanse": 0, "quickFirstTurret": 0, "quickSoloKills": 0, "riftHeraldTakedowns": 0, "saveAllyFromDeath": 0, "scuttleCrabKills": 0, "skillshotsDodged": 10, "skillshotsHit": 34, "snowballsHit": 0, "soloBaronKills": 0, "soloKills": 1, "stealthWardsPlaced": 9, "survivedSingleDigitHpCount": 0, "survivedThreeImmobilizesInFight": 0, "takedownOnFirstTurret": 0, "takedowns": 5, "takedownsAfterGainingLevelAdvantage": 0, "takedownsBeforeJungleMinionSpawn": 0, "takedownsFirstXMinutes": 3, "takedownsInAlcove": 0, "takedownsInEnemyFountain": 0, "teamBaronKills": 0, "teamDamagePercentage": 0.20714971194666715, "teamElderDragonKills": 0, "teamRiftHeraldKills": 0, "tookLargeDamageSurvived": 0, "turretPlatesTaken": 1, "turretTakedowns": 1, "turretsTakenWithRiftHerald": 0, "twentyMinionsIn3SecondsCount": 0, "twoWardsOneSweeperCount": 0, "unseenRecalls": 0, "visionScoreAdvantageLaneOpponent": -0.38234132528305054, "visionScorePerMinute": 0.5088197477955935, "voidMonsterKill": 0, "wardTakedowns": 0, "wardTakedownsBefore20M": 0, "wardsGuarded": 1}, "champExperience": 12424, "champLevel": 14, "championId": 223, "championName": "TahmKench", "championTransform": 0, "commandPings": 1, "consumablesPurchased": 2, "damageDealtToBuildings": 2068, "damageDealtToObjectives": 3243, "damageDealtToTurrets": 2068, "damageSelfMitigated": 28104, "dangerPings": 0, "deaths": 5, "detectorWardsPlaced": 0, "doubleKills": 0, "dragonKills": 0, "eligibleForProgression": true, "enemyMissingPings": 4, "enemyVisionPings": 7, "firstBloodAssist": false, "firstBloodKill": false, "firstTowerAssist": false, "firstTowerKill": false, "gameEndedInEarlySurrender": false, "gameEndedInSurrender": false, "getBackPings": 5, "goldEarned": 9261, "goldSpent": 8850, "holdPings": 0, "individualPosition": "TOP", "inhibitorKills": 0, "inhibitorTakedowns": 0, "inhibitorsLost": 1, "item0": 1056, "item1": 3084, "item2": 1082, "item3": 4633, "item4": 3009, "item5": 1011, "item6": 3340, "itemsPurchased": 20, "killingSprees": 1, "kills": 4, "lane": "TOP", "largestCriticalStrike": 0, "largestKillingSpree": 2, "largestMultiKill": 1, "longestTimeSpentLiving": 739, "magicDamageDealt": 60800, "magicDamageDealtToChampions": 14436, "magicDamageTaken": 17947, "missions": {"playerScore0": 0, "playerScore1": 0, "playerScore2": 0, "playerScore3": 0, "playerScore4": 0, "playerScore5": 0, "playerScore6": 0, "playerScore7": 0, "playerScore8": 0, "playerScore9": 0, "playerScore10": 0, "playerScore11": 0}, "needVisionPings": 1, "neutralMinionsKilled": 0, "nexusKills": 0, "nexusLost": 1, "nexusTakedowns": 0, "objectivesStolen": 0, "objectivesStolenAssists": 0, "onMyWayPings": 6, "participantId": 6, "pentaKills": 0, "perks": {"statPerks": {"defense": 5013, "flex": 5001, "offense": 5005}, "styles": [{"description": "primaryStyle", "selections": [{"perk": 8437, "var1": 1218, "var2": 741, "var3": 0}, {"perk": 8401, "var1": 1164, "var2": 0, "var3": 0}, {"perk": 8444, "var1": 1692, "var2": 0, "var3": 0}, {"perk": 8451, "var1": 250, "var2": 0, "var3": 0}], "style": 8400}, {"description": "subStyle", "selections": [{"perk": 8345, "var1": 3, "var2": 0, "var3": 249}, {"perk": 8410, "var1": 59, "var2": 0, "var3": 0}], "style": 8300}]}, "physicalDamageDealt": 15735, "physicalDamageDealtToChampions": 4063, "physicalDamageTaken": 14000, "placement": 0, "playerAugment1": 0, "playerAugment2": 0, "playerAugment3": 0, "playerAugment4": 0, "playerAugment5": 0, "playerAugment6": 0, "playerSubteamId": 0, "profileIcon": 534, "pushPings": 0, "puuid": "F2ZZk4IKZrMtIGmOngEo2AsWu5UBSgnmibqiUZSscE9Eca39vExkRW-tbqfYTZd6YGqIeEisAUIoRQ", "quadraKills": 0, "retreatPings": 0, "riotIdGameName": "H A C H E", "riotIdTagline": "EUW49", "role": "SOLO", "sightWardsBoughtInGame": 0, "spell1Casts": 112, "spell2Casts": 24, "spell3Casts": 21, "spell4Casts": 22, "subteamPlacement": 0, "summoner1Casts": 4, "summoner1Id": 6, "summoner2Casts": 2, "summoner2Id": 12, "summonerId": "7gVKNAkuSuErpr1L9Bx3Rf5m7VWDkcuWKsN63-14edlsZLP8kR2Wf6NekA", "summonerLevel": 144, "summonerName": "", "teamEarlySurrendered": false, "teamId": 200, "teamPosition": "TOP", "timeCCingOthers": 30, "timePlayed": 1652, "totalAllyJungleMinionsKilled": 0, "totalDamageDealt": 77420, "totalDamageDealtToChampions": 18684, "totalDamageShieldedOnTeammates": 732, "totalDamageTaken": 33438, "totalEnemyJungleMinionsKilled": 0, "totalHeal": 7169, "totalHealsOnTeammates": 0, "totalMinionsKilled": 162, "totalTimeCCDealt": 325, "totalTimeSpentDead": 140, "totalUnitsHealed": 1, "tripleKills": 0, "trueDamageDealt": 884, "trueDamageDealtToChampions": 184, "trueDamageTaken": 1489, "turretKills": 1, "turretTakedowns": 1, "turretsLost": 9, "unrealKills": 0, "visionClearedPings": 0, "visionScore": 14, "visionWardsBoughtInGame": 0, "wardsKilled": 0, "wardsPlaced": 9, "win": false}, {"PlayerScore0": 0, "PlayerScore1": 0, "PlayerScore10": 0, "PlayerScore11": 0, "PlayerScore2": 0, "PlayerScore3": 0, "PlayerScore4": 0, "PlayerScore5": 0, "PlayerScore6": 0, "PlayerScore7": 0, "PlayerScore8": 0, "PlayerScore9": 0, "allInPings": 2, "assistMePings": 5, "assists": 9, "baronKills": 0, "basicPings": 0, "challenges": {"12AssistStreakCount": 0, "HealFromMapSources": 0, "InfernalScalePickup": 0, "SWARM_DefeatAatrox": 0, "SWARM_DefeatBriar": 0, "SWARM_DefeatMiniBosses": 0, "SWARM_EvolveWeapon": 0, "SWARM_Have3Passives": 0, "SWARM_KillEnemy": 0, "SWARM_PickupGold": 0, "SWARM_ReachLevel50": 0, "SWARM_Survive15Min": 0, "SWARM_WinWith5EvolvedWeapons": 0, "abilityUses": 556, "acesBefore15Minutes": 0, "alliedJungleMonsterKills": 73, "baronTakedowns": 0, "blastConeOppositeOpponentCount": 0, "bountyGold": 0, "buffsStolen": 1, "completeSupportQuestInTime": 0, "controlWardsPlaced": 1, "damagePerMinute": 282.1653600657866, "damageTakenOnTeamPercentage": 0.14248955006511843, "dancedWithRiftHerald": 0, "deathsByEnemyChamps": 5, "dodgeSkillShotsSmallWindow": 0, "doubleAces": 0, "dragonTakedowns": 3, "earliestDragonTakedown": 453.61451607000004, "earlyLaningPhaseGoldExpAdvantage": 0, "effectiveHealAndShielding": 11776.5400390625, "elderDragonKillsWithOpposingSoul": 0, "elderDragonMultikills": 0, "enemyChampionImmobilizations": 19, "enemyJungleMonsterKills": 1, "epicMonsterKillsNearEnemyJungler": 0, "epicMonsterKillsWithin30SecondsOfSpawn": 0, "epicMonsterSteals": 0, "epicMonsterStolenWithoutSmite": 0, "firstTurretKilled": 0, "fistBumpParticipation": 0, "flawlessAces": 0, "fullTeamTakedown": 1, "gameLength": 1653.095853474, "goldPerMinute": 308.02266851234265, "hadOpenNexus": 0, "immobilizeAndKillWithAlly": 2, "initialBuffCount": 2, "initialCrabCount": 2, "jungleCsBefore10Minutes": 59.50000008940697, "junglerKillsEarlyJungle": 0, "junglerTakedownsNearDamagedEpicMonster": 0, "kTurretsDestroyedBeforePlatesFall": 0, "kda": 1.8, "killAfterHiddenWithAlly": 0, "killParticipation": 0.5294117647058824, "killedChampTookFullTeamDamageSurvived": 0, "killingSprees": 0, "killsNearEnemyTurret": 0, "killsOnLanersEarlyJungleAsJungler": 0, "killsOnRecentlyHealedByAramPack": 0, "killsUnderOwnTurret": 0, "killsWithHelpFromEpicMonster": 0, "knockEnemyIntoTeamAndKill": 0, "landSkillShotsEarlyGame": 2, "laneMinionsFirst10Minutes": 1, "laningPhaseGoldExpAdvantage": 0, "legendaryCount": 0, "legendaryItemUsed": [3107, 6617], "lostAnInhibitor": 0, "maxCsAdvantageOnLaneOpponent": 15.500000029802322, "maxKillDeficit": 0, "maxLevelLeadLaneOpponent": 1, "mejaisFullStackInTime": 0, "moreEnemyJungleThanOpponent": -51.500000059604645, "multiKillOneSpell": 0, "multiTurretRiftHeraldCount": 0, "multikills": 0, "multikillsAfterAggressiveFlash": 0, "outerTurretExecutesBefore10Minutes": 0, "outnumberedKills": 0, "outnumberedNexusKill": 0, "perfectDragonSoulsTaken": 0, "perfectGame": 0, "pickKillWithAlly": 9, "playedChampSelectPosition": 1, "poroExplosions": 0, "quickCleanse": 0, "quickFirstTurret": 0, "quickSoloKills": 0, "riftHeraldTakedowns": 0, "saveAllyFromDeath": 2, "scuttleCrabKills": 3, "skillshotsDodged": 16, "skillshotsHit": 12, "snowballsHit": 0, "soloBaronKills": 0, "soloKills": 0, "stealthWardsPlaced": 2, "survivedSingleDigitHpCount": 0, "survivedThreeImmobilizesInFight": 0, "takedownOnFirstTurret": 0, "takedowns": 9, "takedownsAfterGainingLevelAdvantage": 0, "takedownsBeforeJungleMinionSpawn": 0, "takedownsFirstXMinutes": 3, "takedownsInAlcove": 0, "takedownsInEnemyFountain": 0, "teamBaronKills": 0, "teamDamagePercentage": 0.0861873955500816, "teamElderDragonKills": 0, "teamRiftHeraldKills": 0, "tookLargeDamageSurvived": 0, "turretPlatesTaken": 0, "turretTakedowns": 0, "turretsTakenWithRiftHerald": 0, "twentyMinionsIn3SecondsCount": 0, "twoWardsOneSweeperCount": 0, "unseenRecalls": 0, "visionScoreAdvantageLaneOpponent": -0.09538024663925171, "visionScorePerMinute": 0.9182065578225794, "voidMonsterKill": 0, "wardTakedowns": 6, "wardTakedownsBefore20M": 5, "wardsGuarded": 0}, "champExperience": 10860, "champLevel": 13, "championId": 427, "championName": "Ivern", "championTransform": 0, "commandPings": 6, "consumablesPurchased": 1, "damageDealtToBuildings": 0, "damageDealtToObjectives": 13272, "damageDealtToTurrets": 0, "damageSelfMitigated": 8618, "dangerPings": 0, "deaths": 5, "detectorWardsPlaced": 1, "doubleKills": 0, "dragonKills": 3, "eligibleForProgression": true, "enemyMissingPings": 3, "enemyVisionPings": 6, "firstBloodAssist": false, "firstBloodKill": false, "firstTowerAssist": false, "firstTowerKill": false, "gameEndedInEarlySurrender": false, "gameEndedInSurrender": false, "getBackPings": 0, "goldEarned": 8486, "goldSpent": 8725, "holdPings": 0, "individualPosition": "JUNGLE", "inhibitorKills": 0, "inhibitorTakedowns": 0, "inhibitorsLost": 1, "item0": 6617, "item1": 3107, "item2": 1026, "item3": 3158, "item4": 3114, "item5": 3114, "item6": 3364, "itemsPurchased": 18, "killingSprees": 0, "kills": 0, "lane": "JUNGLE", "largestCriticalStrike": 0, "largestKillingSpree": 0, "largestMultiKill": 0, "longestTimeSpentLiving": 648, "magicDamageDealt": 9601, "magicDamageDealtToChampions": 3234, "magicDamageTaken": 7611, "missions": {"playerScore0": 0, "playerScore1": 0, "playerScore2": 0, "playerScore3": 0, "playerScore4": 0, "playerScore5": 0, "playerScore6": 0, "playerScore7": 0, "playerScore8": 0, "playerScore9": 0, "playerScore10": 0, "playerScore11": 0}, "needVisionPings": 0, "neutralMinionsKilled": 129, "nexusKills": 0, "nexusLost": 1, "nexusTakedowns": 0, "objectivesStolen": 0, "objectivesStolenAssists": 0, "onMyWayPings": 24, "participantId": 7, "pentaKills": 0, "perks": {"statPerks": {"defense": 5001, "flex": 5010, "offense": 5007}, "styles": [{"description": "primaryStyle", "selections": [{"perk": 8214, "var1": 729, "var2": 865, "var3": 0}, {"perk": 8275, "var1": 20, "var2": 0, "var3": 0}, {"perk": 8210, "var1": 8, "var2": 0, "var3": 0}, {"perk": 8232, "var1": 4, "var2": 0, "var3": 0}], "style": 8200}, {"description": "subStyle", "selections": [{"perk": 8321, "var1": 270, "var2": 0, "var3": 0}, {"perk": 8347, "var1": 0, "var2": 0, "var3": 0}], "style": 8300}]}, "physicalDamageDealt": 7677, "physicalDamageDealtToChampions": 2698, "physicalDamageTaken": 7623, "placement": 0, "playerAugment1": 0, "playerAugment2": 0, "playerAugment3": 0, "playerAugment4": 0, "playerAugment5": 0, "playerAugment6": 0, "playerSubteamId": 0, "profileIcon": 23, "pushPings": 0, "puuid": "WNHwMTvZysb2c0kqMCLie9_WDwqmZ-Fjb_DVX6efItpah86pCih_7Hk96ngqc41Z9iL1dbtdSHGhQw", "quadraKills": 0, "retreatPings": 4, "riotIdGameName": "turkish taliyah", "riotIdTagline": "EUW", "role": "NONE", "sightWardsBoughtInGame": 0, "spell1Casts": 102, "spell2Casts": 60, "spell3Casts": 68, "spell4Casts": 326, "subteamPlacement": 0, "summoner1Casts": 2, "summoner1Id": 4, "summoner2Casts": 18, "summoner2Id": 11, "summonerId": "44k5Q-fixOyYgPofUWhhTqEK-RRxcdYVx_4XCePUtDdzHt9FpEt2HjmL5w", "summonerLevel": 178, "summonerName": "", "teamEarlySurrendered": false, "teamId": 200, "teamPosition": "JUNGLE", "timeCCingOthers": 32, "timePlayed": 1653, "totalAllyJungleMinionsKilled": 101, "totalDamageDealt": 164215, "totalDamageDealtToChampions": 7774, "totalDamageShieldedOnTeammates": 9208, "totalDamageTaken": 15334, "totalEnemyJungleMinionsKilled": 4, "totalHeal": 7262, "totalHealsOnTeammates": 2568, "totalMinionsKilled": 10, "totalTimeCCDealt": 235, "totalTimeSpentDead": 173, "totalUnitsHealed": 5, "tripleKills": 0, "trueDamageDealt": 146936, "trueDamageDealtToChampions": 1841, "trueDamageTaken": 98, "turretKills": 0, "turretTakedowns": 0, "turretsLost": 9, "unrealKills": 0, "visionClearedPings": 0, "visionScore": 25, "visionWardsBoughtInGame": 1, "wardsKilled": 6, "wardsPlaced": 3, "win": false}, {"PlayerScore0": 0, "PlayerScore1": 0, "PlayerScore10": 0, "PlayerScore11": 0, "PlayerScore2": 0, "PlayerScore3": 0, "PlayerScore4": 0, "PlayerScore5": 0, "PlayerScore6": 0, "PlayerScore7": 0, "PlayerScore8": 0, "PlayerScore9": 0, "allInPings": 1, "assistMePings": 1, "assists": 8, "baronKills": 0, "basicPings": 0, "challenges": {"12AssistStreakCount": 0, "HealFromMapSources": 642, "InfernalScalePickup": 0, "SWARM_DefeatAatrox": 0, "SWARM_DefeatBriar": 0, "SWARM_DefeatMiniBosses": 0, "SWARM_EvolveWeapon": 0, "SWARM_Have3Passives": 0, "SWARM_KillEnemy": 0, "SWARM_PickupGold": 0, "SWARM_ReachLevel50": 0, "SWARM_Survive15Min": 0, "SWARM_WinWith5EvolvedWeapons": 0, "abilityUses": 287, "acesBefore15Minutes": 0, "alliedJungleMonsterKills": 0, "baronTakedowns": 0, "blastConeOppositeOpponentCount": 0, "bountyGold": 0, "buffsStolen": 0, "completeSupportQuestInTime": 0, "controlWardsPlaced": 0, "damagePerMinute": 630.9212609303203, "damageTakenOnTeamPercentage": 0.1467848325801253, "dancedWithRiftHerald": 0, "deathsByEnemyChamps": 6, "dodgeSkillShotsSmallWindow": 0, "doubleAces": 0, "dragonTakedowns": 0, "earlyLaningPhaseGoldExpAdvantage": 0, "effectiveHealAndShielding": 0, "elderDragonKillsWithOpposingSoul": 0, "elderDragonMultikills": 0, "enemyChampionImmobilizations": 26, "enemyJungleMonsterKills": 0, "epicMonsterKillsNearEnemyJungler": 0, "epicMonsterKillsWithin30SecondsOfSpawn": 0, "epicMonsterSteals": 0, "epicMonsterStolenWithoutSmite": 0, "firstTurretKilled": 0, "fistBumpParticipation": 0, "flawlessAces": 0, "fullTeamTakedown": 1, "gameLength": 1653.095853474, "getTakedownsInAllLanesEarlyJungleAsLaner": 0, "goldPerMinute": 361.8636579620508, "hadOpenNexus": 0, "immobilizeAndKillWithAlly": 8, "initialBuffCount": 0, "initialCrabCount": 0, "jungleCsBefore10Minutes": 0, "junglerTakedownsNearDamagedEpicMonster": 0, "kTurretsDestroyedBeforePlatesFall": 0, "kda": 2, "killAfterHiddenWithAlly": 1, "killParticipation": 0.7058823529411765, "killedChampTookFullTeamDamageSurvived": 0, "killingSprees": 0, "killsNearEnemyTurret": 2, "killsOnOtherLanesEarlyJungleAsLaner": 1, "killsOnRecentlyHealedByAramPack": 0, "killsUnderOwnTurret": 1, "killsWithHelpFromEpicMonster": 0, "knockEnemyIntoTeamAndKill": 0, "landSkillShotsEarlyGame": 4, "laneMinionsFirst10Minutes": 79, "laningPhaseGoldExpAdvantage": 0, "legendaryCount": 0, "legendaryItemUsed": [2065, 3094], "lostAnInhibitor": 0, "maxCsAdvantageOnLaneOpponent": 3, "maxKillDeficit": 0, "maxLevelLeadLaneOpponent": 1, "mejaisFullStackInTime": 0, "moreEnemyJungleThanOpponent": 0, "multiKillOneSpell": 0, "multiTurretRiftHeraldCount": 0, "multikills": 0, "multikillsAfterAggressiveFlash": 0, "outerTurretExecutesBefore10Minutes": 0, "outnumberedKills": 0, "outnumberedNexusKill": 0, "perfectDragonSoulsTaken": 0, "perfectGame": 0, "pickKillWithAlly": 10, "playedChampSelectPosition": 1, "poroExplosions": 0, "quickCleanse": 0, "quickFirstTurret": 0, "quickSoloKills": 0, "riftHeraldTakedowns": 0, "saveAllyFromDeath": 0, "scuttleCrabKills": 0, "skillshotsDodged": 7, "skillshotsHit": 42, "snowballsHit": 0, "soloBaronKills": 0, "soloKills": 2, "stealthWardsPlaced": 4, "survivedSingleDigitHpCount": 0, "survivedThreeImmobilizesInFight": 0, "takedownOnFirstTurret": 1, "takedowns": 12, "takedownsAfterGainingLevelAdvantage": 0, "takedownsBeforeJungleMinionSpawn": 0, "takedownsFirstXMinutes": 8, "takedownsInAlcove": 1, "takedownsInEnemyFountain": 0, "teamBaronKills": 0, "teamDamagePercentage": 0.19271486855820893, "teamElderDragonKills": 0, "teamRiftHeraldKills": 0, "tookLargeDamageSurvived": 0, "turretPlatesTaken": 2, "turretTakedowns": 2, "turretsTakenWithRiftHerald": 0, "twentyMinionsIn3SecondsCount": 0, "twoWardsOneSweeperCount": 0, "unseenRecalls": 0, "visionScoreAdvantageLaneOpponent": 0.622093677520752, "visionScorePerMinute": 0.7587588272821955, "voidMonsterKill": 0, "wardTakedowns": 3, "wardTakedownsBefore20M": 0, "wardsGuarded": 0}, "champExperience": 10711, "champLevel": 13, "championId": 4, "championName": "TwistedFate", "championTransform": 0, "commandPings": 5, "consumablesPurchased": 3, "damageDealtToBuildings": 2481, "damageDealtToObjectives": 3227, "damageDealtToTurrets": 2481, "damageSelfMitigated": 7372, "dangerPings": 0, "deaths": 6, "detectorWardsPlaced": 0, "doubleKills": 0, "dragonKills": 0, "eligibleForProgression": true, "enemyMissingPings": 0, "enemyVisionPings": 0, "firstBloodAssist": false, "firstBloodKill": false, "firstTowerAssist": false, "firstTowerKill": false, "gameEndedInEarlySurrender": false, "gameEndedInSurrender": false, "getBackPings": 0, "goldEarned": 9969, "goldSpent": 8150, "holdPings": 0, "individualPosition": "MIDDLE", "inhibitorKills": 0, "inhibitorTakedowns": 0, "inhibitorsLost": 1, "item0": 2065, "item1": 1056, "item2": 1082, "item3": 3094, "item4": 3170, "item5": 3057, "item6": 3363, "itemsPurchased": 19, "killingSprees": 1, "kills": 4, "lane": "MIDDLE", "largestCriticalStrike": 138, "largestKillingSpree": 2, "largestMultiKill": 1, "longestTimeSpentLiving": 403, "magicDamageDealt": 99431, "magicDamageDealtToChampions": 14564, "magicDamageTaken": 6871, "missions": {"playerScore0": 0, "playerScore1": 0, "playerScore2": 0, "playerScore3": 0, "playerScore4": 0, "playerScore5": 0, "playerScore6": 0, "playerScore7": 0, "playerScore8": 0, "playerScore9": 0, "playerScore10": 0, "playerScore11": 0}, "needVisionPings": 0, "neutralMinionsKilled": 0, "nexusKills": 0, "nexusLost": 1, "nexusTakedowns": 0, "objectivesStolen": 0, "objectivesStolenAssists": 0, "onMyWayPings": 21, "participantId": 8, "pentaKills": 0, "perks": {"statPerks": {"defense": 5011, "flex": 5008, "offense": 5005}, "styles": [{"description": "primaryStyle", "selections": [{"perk": 8112, "var1": 1224, "var2": 0, "var3": 0}, {"perk": 8139, "var1": 677, "var2": 0, "var3": 0}, {"perk": 8140, "var1": 12, "var2": 0, "var3": 0}, {"perk": 8105, "var1": 40, "var2": 5, "var3": 0}], "style": 8100}, {"description": "subStyle", "selections": [{"perk": 8233, "var1": 17, "var2": 30, "var3": 0}, {"perk": 8237, "var1": 442, "var2": 0, "var3": 0}], "style": 8200}]}, "physicalDamageDealt": 12348, "physicalDamageDealtToChampions": 1956, "physicalDamageTaken": 8593, "placement": 0, "playerAugment1": 0, "playerAugment2": 0, "playerAugment3": 0, "playerAugment4": 0, "playerAugment5": 0, "playerAugment6": 0, "playerSubteamId": 0, "profileIcon": 3366, "pushPings": 0, "puuid": "Sn5PWtYnswgZSMwWlk8oWqREX44q8wAvpwhnF8Ot7rS8clgVuy7txbRoI94214hUUzVpSiv3C1pMdQ", "quadraKills": 0, "retreatPings": 0, "riotIdGameName": "crossman", "riotIdTagline": "001", "role": "SOLO", "sightWardsBoughtInGame": 0, "spell1Casts": 89, "spell2Casts": 186, "spell3Casts": 0, "spell4Casts": 12, "subteamPlacement": 0, "summoner1Casts": 4, "summoner1Id": 14, "summoner2Casts": 4, "summoner2Id": 4, "summonerId": "2z0twqf1Rz2MJzGeylKgzPmtbLBW_rxPdUsG_1G83-FD6HE", "summonerLevel": 1083, "summonerName": "", "teamEarlySurrendered": false, "teamId": 200, "teamPosition": "MIDDLE", "timeCCingOthers": 32, "timePlayed": 1653, "totalAllyJungleMinionsKilled": 0, "totalDamageDealt": 117391, "totalDamageDealtToChampions": 17382, "totalDamageShieldedOnTeammates": 0, "totalDamageTaken": 15796, "totalEnemyJungleMinionsKilled": 0, "totalHeal": 1939, "totalHealsOnTeammates": 0, "totalMinionsKilled": 149, "totalTimeCCDealt": 133, "totalTimeSpentDead": 186, "totalUnitsHealed": 1, "tripleKills": 0, "trueDamageDealt": 5612, "trueDamageDealtToChampions": 862, "trueDamageTaken": 331, "turretKills": 0, "turretTakedowns": 2, "turretsLost": 9, "unrealKills": 0, "visionClearedPings": 0, "visionScore": 20, "visionWardsBoughtInGame": 0, "wardsKilled": 3, "wardsPlaced": 9, "win": false}, {"PlayerScore0": 0, "PlayerScore1": 0, "PlayerScore10": 0, "PlayerScore11": 0, "PlayerScore2": 0, "PlayerScore3": 0, "PlayerScore4": 0, "PlayerScore5": 0, "PlayerScore6": 0, "PlayerScore7": 0, "PlayerScore8": 0, "PlayerScore9": 0, "allInPings": 0, "assistMePings": 0, "assists": 1, "baronKills": 0, "basicPings": 0, "challenges": {"12AssistStreakCount": 0, "HealFromMapSources": 74, "InfernalScalePickup": 0, "SWARM_DefeatAatrox": 0, "SWARM_DefeatBriar": 0, "SWARM_DefeatMiniBosses": 0, "SWARM_EvolveWeapon": 0, "SWARM_Have3Passives": 0, "SWARM_KillEnemy": 0, "SWARM_PickupGold": 0, "SWARM_ReachLevel50": 0, "SWARM_Survive15Min": 0, "SWARM_WinWith5EvolvedWeapons": 0, "abilityUses": 285, "acesBefore15Minutes": 0, "alliedJungleMonsterKills": 1, "baronTakedowns": 0, "blastConeOppositeOpponentCount": 0, "bountyGold": 206.568115234375, "buffsStolen": 0, "completeSupportQuestInTime": 0, "controlWardTimeCoverageInRiverOrEnemyHalf": 0.801394768237398, "controlWardsPlaced": 3, "damagePerMinute": 1119.107065759207, "damageTakenOnTeamPercentage": 0.1140479540425279, "dancedWithRiftHerald": 0, "deathsByEnemyChamps": 3, "dodgeSkillShotsSmallWindow": 0, "doubleAces": 0, "dragonTakedowns": 2, "earliestDragonTakedown": 794.991137254, "earlyLaningPhaseGoldExpAdvantage": 1, "effectiveHealAndShielding": 0, "elderDragonKillsWithOpposingSoul": 0, "elderDragonMultikills": 0, "enemyChampionImmobilizations": 4, "enemyJungleMonsterKills": 0, "epicMonsterKillsNearEnemyJungler": 0, "epicMonsterKillsWithin30SecondsOfSpawn": 0, "epicMonsterSteals": 0, "epicMonsterStolenWithoutSmite": 0, "firstTurretKilled": 0, "fistBumpParticipation": 0, "flawlessAces": 0, "fullTeamTakedown": 1, "gameLength": 1653.095853474, "getTakedownsInAllLanesEarlyJungleAsLaner": 0, "goldPerMinute": 441.91505754704855, "hadOpenNexus": 0, "highestChampionDamage": 1, "immobilizeAndKillWithAlly": 1, "initialBuffCount": 0, "initialCrabCount": 0, "jungleCsBefore10Minutes": 0, "junglerTakedownsNearDamagedEpicMonster": 0, "kTurretsDestroyedBeforePlatesFall": 0, "kda": 3.3333333333333335, "killAfterHiddenWithAlly": 1, "killParticipation": 0.5882352941176471, "killedChampTookFullTeamDamageSurvived": 0, "killingSprees": 2, "killsNearEnemyTurret": 1, "killsOnOtherLanesEarlyJungleAsLaner": 0, "killsOnRecentlyHealedByAramPack": 0, "killsUnderOwnTurret": 0, "killsWithHelpFromEpicMonster": 0, "knockEnemyIntoTeamAndKill": 0, "landSkillShotsEarlyGame": 11, "laneMinionsFirst10Minutes": 73, "laningPhaseGoldExpAdvantage": 0, "legendaryCount": 0, "legendaryItemUsed": [6676, 3031, 3036], "lostAnInhibitor": 0, "maxCsAdvantageOnLaneOpponent": 16, "maxKillDeficit": 0, "maxLevelLeadLaneOpponent": 1, "mejaisFullStackInTime": 0, "moreEnemyJungleThanOpponent": 0, "multiKillOneSpell": 0, "multiTurretRiftHeraldCount": 0, "multikills": 3, "multikillsAfterAggressiveFlash": 0, "outerTurretExecutesBefore10Minutes": 0, "outnumberedKills": 2, "outnumberedNexusKill": 0, "perfectDragonSoulsTaken": 0, "perfectGame": 0, "pickKillWithAlly": 10, "playedChampSelectPosition": 1, "poroExplosions": 0, "quickCleanse": 0, "quickFirstTurret": 0, "quickSoloKills": 0, "riftHeraldTakedowns": 0, "saveAllyFromDeath": 0, "scuttleCrabKills": 0, "skillshotsDodged": 18, "skillshotsHit": 58, "snowballsHit": 0, "soloBaronKills": 0, "soloKills": 0, "stealthWardsPlaced": 5, "survivedSingleDigitHpCount": 0, "survivedThreeImmobilizesInFight": 0, "takedownOnFirstTurret": 1, "takedowns": 10, "takedownsAfterGainingLevelAdvantage": 0, "takedownsBeforeJungleMinionSpawn": 0, "takedownsFirstXMinutes": 6, "takedownsInAlcove": 0, "takedownsInEnemyFountain": 0, "teamBaronKills": 0, "teamDamagePercentage": 0.3418311989713835, "teamElderDragonKills": 0, "teamRiftHeraldKills": 0, "tookLargeDamageSurvived": 0, "turretPlatesTaken": 2, "turretTakedowns": 2, "turretsTakenWithRiftHerald": 0, "twentyMinionsIn3SecondsCount": 0, "twoWardsOneSweeperCount": 0, "unseenRecalls": 0, "visionScoreAdvantageLaneOpponent": 0.32374000549316406, "visionScorePerMinute": 0.8359198630744114, "voidMonsterKill": 0, "wardTakedowns": 5, "wardTakedownsBefore20M": 3, "wardsGuarded": 0}, "champExperience": 10082, "champLevel": 13, "championId": 523, "championName": "Aphelios", "championTransform": 0, "commandPings": 0, "consumablesPurchased": 6, "damageDealtToBuildings": 3570, "damageDealtToObjectives": 14134, "damageDealtToTurrets": 3570, "damageSelfMitigated": 9895, "dangerPings": 0, "deaths": 3, "detectorWardsPlaced": 3, "doubleKills": 3, "dragonKills": 0, "eligibleForProgression": true, "enemyMissingPings": 2, "enemyVisionPings": 6, "firstBloodAssist": false, "firstBloodKill": true, "firstTowerAssist": false, "firstTowerKill": false, "gameEndedInEarlySurrender": false, "gameEndedInSurrender": false, "getBackPings": 7, "goldEarned": 12175, "goldSpent": 11975, "holdPings": 0, "individualPosition": "BOTTOM", "inhibitorKills": 0, "inhibitorTakedowns": 0, "inhibitorsLost": 1, "item0": 1055, "item1": 6676, "item2": 3036, "item3": 0, "item4": 3172, "item5": 3031, "item6": 3363, "itemsPurchased": 28, "killingSprees": 2, "kills": 9, "lane": "BOTTOM", "largestCriticalStrike": 729, "largestKillingSpree": 6, "largestMultiKill": 2, "longestTimeSpentLiving": 665, "magicDamageDealt": 3830, "magicDamageDealtToChampions": 488, "magicDamageTaken": 5521, "missions": {"playerScore0": 0, "playerScore1": 0, "playerScore2": 0, "playerScore3": 0, "playerScore4": 0, "playerScore5": 0, "playerScore6": 0, "playerScore7": 0, "playerScore8": 0, "playerScore9": 0, "playerScore10": 0, "playerScore11": 0}, "needVisionPings": 0, "neutralMinionsKilled": 2, "nexusKills": 0, "nexusLost": 1, "nexusTakedowns": 0, "objectivesStolen": 0, "objectivesStolenAssists": 0, "onMyWayPings": 1, "participantId": 9, "pentaKills": 0, "perks": {"statPerks": {"defense": 5011, "flex": 5008, "offense": 5005}, "styles": [{"description": "primaryStyle", "selections": [{"perk": 8005, "var1": 1148, "var2": 1148, "var3": 0}, {"perk": 9101, "var1": 604, "var2": 0, "var3": 0}, {"perk": 9104, "var1": 14, "var2": 0, "var3": 0}, {"perk": 8017, "var1": 1456, "var2": 0, "var3": 0}], "style": 8000}, {"description": "subStyle", "selections": [{"perk": 8233, "var1": 18, "var2": 30, "var3": 0}, {"perk": 8236, "var1": 14, "var2": 0, "var3": 0}], "style": 8200}]}, "physicalDamageDealt": 153647, "physicalDamageDealtToChampions": 30026, "physicalDamageTaken": 6536, "placement": 0, "playerAugment1": 0, "playerAugment2": 0, "playerAugment3": 0, "playerAugment4": 0, "playerAugment5": 0, "playerAugment6": 0, "playerSubteamId": 0, "profileIcon": 10, "pushPings": 0, "puuid": "aGaeDIsXm3Uj0j38I3Oi4ekB5c3X2gZIEQzpnXqz2O8rNaKaHw72HxjZDeRjpw6Vt4U_c7fWoOBjkA", "quadraKills": 0, "retreatPings": 0, "riotIdGameName": "Hans Zimmer", "riotIdTagline": "GOAT", "role": "CARRY", "sightWardsBoughtInGame": 0, "spell1Casts": 65, "spell2Casts": 215, "spell3Casts": 0, "spell4Casts": 5, "subteamPlacement": 0, "summoner1Casts": 6, "summoner1Id": 21, "summoner2Casts": 4, "summoner2Id": 4, "summonerId": "5BnAYJljfa8wVxVHD1gDutOEOwGhwf-c4BLlzgZxt8IOYhGDAFBqCpqKOA", "summonerLevel": 133, "summonerName": "", "teamEarlySurrendered": false, "teamId": 200, "teamPosition": "BOTTOM", "timeCCingOthers": 8, "timePlayed": 1652, "totalAllyJungleMinionsKilled": 2, "totalDamageDealt": 157935, "totalDamageDealtToChampions": 30833, "totalDamageShieldedOnTeammates": 0, "totalDamageTaken": 12273, "totalEnemyJungleMinionsKilled": 0, "totalHeal": 3538, "totalHealsOnTeammates": 0, "totalMinionsKilled": 218, "totalTimeCCDealt": 87, "totalTimeSpentDead": 103, "totalUnitsHealed": 1, "tripleKills": 0, "trueDamageDealt": 457, "trueDamageDealtToChampions": 317, "trueDamageTaken": 215, "turretKills": 1, "turretTakedowns": 2, "turretsLost": 9, "unrealKills": 0, "visionClearedPings": 0, "visionScore": 23, "visionWardsBoughtInGame": 3, "wardsKilled": 5, "wardsPlaced": 10, "win": false}, {"PlayerScore0": 0, "PlayerScore1": 0, "PlayerScore10": 0, "PlayerScore11": 0, "PlayerScore2": 0, "PlayerScore3": 0, "PlayerScore4": 0, "PlayerScore5": 0, "PlayerScore6": 0, "PlayerScore7": 0, "PlayerScore8": 0, "PlayerScore9": 0, "allInPings": 1, "assistMePings": 3, "assists": 9, "baronKills": 0, "basicPings": 0, "challenges": {"12AssistStreakCount": 0, "HealFromMapSources": 698.0029220581055, "InfernalScalePickup": 0, "SWARM_DefeatAatrox": 0, "SWARM_DefeatBriar": 0, "SWARM_DefeatMiniBosses": 0, "SWARM_EvolveWeapon": 0, "SWARM_Have3Passives": 0, "SWARM_KillEnemy": 0, "SWARM_PickupGold": 0, "SWARM_ReachLevel50": 0, "SWARM_Survive15Min": 0, "SWARM_WinWith5EvolvedWeapons": 0, "abilityUses": 123, "acesBefore15Minutes": 0, "alliedJungleMonsterKills": 5, "baronTakedowns": 0, "blastConeOppositeOpponentCount": 0, "bountyGold": 0, "buffsStolen": 0, "completeSupportQuestInTime": 1, "controlWardsPlaced": 0, "damagePerMinute": 563.4861754681067, "damageTakenOnTeamPercentage": 0.28596367390992644, "dancedWithRiftHerald": 0, "deathsByEnemyChamps": 7, "dodgeSkillShotsSmallWindow": 0, "doubleAces": 0, "dragonTakedowns": 0, "earlyLaningPhaseGoldExpAdvantage": 0, "effectiveHealAndShielding": 1886.148193359375, "elderDragonKillsWithOpposingSoul": 0, "elderDragonMultikills": 0, "enemyChampionImmobilizations": 101, "enemyJungleMonsterKills": 0, "epicMonsterKillsNearEnemyJungler": 0, "epicMonsterKillsWithin30SecondsOfSpawn": 0, "epicMonsterSteals": 0, "epicMonsterStolenWithoutSmite": 0, "fasterSupportQuestCompletion": 1, "firstTurretKilled": 0, "fistBumpParticipation": 0, "flawlessAces": 0, "fullTeamTakedown": 1, "gameLength": 1653.095853474, "getTakedownsInAllLanesEarlyJungleAsLaner": 0, "goldPerMinute": 238.0380874851756, "hadOpenNexus": 0, "highestCrowdControlScore": 1, "immobilizeAndKillWithAlly": 6, "initialBuffCount": 0, "initialCrabCount": 0, "jungleCsBefore10Minutes": 0, "junglerTakedownsNearDamagedEpicMonster": 0, "kTurretsDestroyedBeforePlatesFall": 0, "kda": 1.2857142857142858, "killAfterHiddenWithAlly": 0, "killParticipation": 0.5294117647058824, "killedChampTookFullTeamDamageSurvived": 0, "killingSprees": 0, "killsNearEnemyTurret": 0, "killsOnOtherLanesEarlyJungleAsLaner": 0, "killsOnRecentlyHealedByAramPack": 0, "killsUnderOwnTurret": 0, "killsWithHelpFromEpicMonster": 0, "knockEnemyIntoTeamAndKill": 5, "landSkillShotsEarlyGame": 4, "laneMinionsFirst10Minutes": 10, "laningPhaseGoldExpAdvantage": 0, "legendaryCount": 0, "legendaryItemUsed": [3869, 3107, 3190], "lostAnInhibitor": 0, "maxCsAdvantageOnLaneOpponent": 6, "maxKillDeficit": 0, "maxLevelLeadLaneOpponent": 1, "mejaisFullStackInTime": 0, "moreEnemyJungleThanOpponent": 0, "multiKillOneSpell": 0, "multiTurretRiftHeraldCount": 0, "multikills": 0, "multikillsAfterAggressiveFlash": 0, "outerTurretExecutesBefore10Minutes": 0, "outnumberedKills": 0, "outnumberedNexusKill": 0, "perfectDragonSoulsTaken": 0, "perfectGame": 0, "pickKillWithAlly": 9, "playedChampSelectPosition": 1, "poroExplosions": 0, "quickCleanse": 0, "quickFirstTurret": 0, "quickSoloKills": 0, "riftHeraldTakedowns": 0, "saveAllyFromDeath": 0, "scuttleCrabKills": 0, "skillshotsDodged": 57, "skillshotsHit": 34, "snowballsHit": 0, "soloBaronKills": 0, "soloKills": 0, "stealthWardsPlaced": 22, "survivedSingleDigitHpCount": 0, "survivedThreeImmobilizesInFight": 2, "takedownOnFirstTurret": 0, "takedowns": 9, "takedownsAfterGainingLevelAdvantage": 0, "takedownsBeforeJungleMinionSpawn": 0, "takedownsFirstXMinutes": 6, "takedownsInAlcove": 0, "takedownsInEnemyFountain": 0, "teamBaronKills": 0, "teamDamagePercentage": 0.1721168249736588, "teamElderDragonKills": 0, "teamRiftHeraldKills": 0, "tookLargeDamageSurvived": 0, "turretPlatesTaken": 2, "turretTakedowns": 1, "turretsTakenWithRiftHerald": 0, "twentyMinionsIn3SecondsCount": 0, "twoWardsOneSweeperCount": 0, "unseenRecalls": 0, "visionScoreAdvantageLaneOpponent": -0.4502614140510559, "visionScorePerMinute": 1.5924321647112853, "voidMonsterKill": 0, "wardTakedowns": 4, "wardTakedownsBefore20M": 3, "wardsGuarded": 0}, "champExperience": 7316, "champLevel": 11, "championId": 57, "championName": "Maokai", "championTransform": 0, "commandPings": 8, "consumablesPurchased": 2, "damageDealtToBuildings": 609, "damageDealtToObjectives": 1165, "damageDealtToTurrets": 609, "damageSelfMitigated": 23190, "dangerPings": 0, "deaths": 7, "detectorWardsPlaced": 0, "doubleKills": 0, "dragonKills": 0, "eligibleForProgression": true, "enemyMissingPings": 2, "enemyVisionPings": 0, "firstBloodAssist": true, "firstBloodKill": false, "firstTowerAssist": false, "firstTowerKill": false, "gameEndedInEarlySurrender": false, "gameEndedInSurrender": false, "getBackPings": 0, "goldEarned": 6558, "goldSpent": 6150, "holdPings": 0, "individualPosition": "UTILITY", "inhibitorKills": 0, "inhibitorTakedowns": 0, "inhibitorsLost": 1, "item0": 3190, "item1": 3107, "item2": 3869, "item3": 3009, "item4": 0, "item5": 0, "item6": 3364, "itemsPurchased": 17, "killingSprees": 0, "kills": 0, "lane": "BOTTOM", "largestCriticalStrike": 0, "largestKillingSpree": 0, "largestMultiKill": 0, "longestTimeSpentLiving": 653, "magicDamageDealt": 26145, "magicDamageDealtToChampions": 12949, "magicDamageTaken": 14541, "missions": {"playerScore0": 0, "playerScore1": 0, "playerScore2": 0, "playerScore3": 0, "playerScore4": 0, "playerScore5": 0, "playerScore6": 0, "playerScore7": 0, "playerScore8": 0, "playerScore9": 0, "playerScore10": 0, "playerScore11": 0}, "needVisionPings": 0, "neutralMinionsKilled": 2, "nexusKills": 0, "nexusLost": 1, "nexusTakedowns": 0, "objectivesStolen": 0, "objectivesStolenAssists": 0, "onMyWayPings": 8, "participantId": 10, "pentaKills": 0, "perks": {"statPerks": {"defense": 5001, "flex": 5001, "offense": 5008}, "styles": [{"description": "primaryStyle", "selections": [{"perk": 8439, "var1": 744, "var2": 1762, "var3": 0}, {"perk": 8463, "var1": 941, "var2": 0, "var3": 0}, {"perk": 8473, "var1": 501, "var2": 0, "var3": 0}, {"perk": 8242, "var1": 82, "var2": 0, "var3": 0}], "style": 8400}, {"description": "subStyle", "selections": [{"perk": 8345, "var1": 3, "var2": 0, "var3": 222}, {"perk": 8347, "var1": 0, "var2": 0, "var3": 0}], "style": 8300}]}, "physicalDamageDealt": 4648, "physicalDamageDealtToChampions": 1713, "physicalDamageTaken": 15892, "placement": 0, "playerAugment1": 0, "playerAugment2": 0, "playerAugment3": 0, "playerAugment4": 0, "playerAugment5": 0, "playerAugment6": 0, "playerSubteamId": 0, "profileIcon": 4419, "pushPings": 1, "puuid": "iACkqLCsGK9PPWlheNqZ9L2S8iksZ-HNxoJarmwLCc6QkIT3c7uSK2_cgbHec4BN80Kdaq3UOPRwVw", "quadraKills": 0, "retreatPings": 0, "riotIdGameName": "TwTv Lathyrus", "riotIdTagline": "Brad", "role": "SUPPORT", "sightWardsBoughtInGame": 0, "spell1Casts": 43, "spell2Casts": 24, "spell3Casts": 50, "spell4Casts": 6, "subteamPlacement": 0, "summoner1Casts": 5, "summoner1Id": 7, "summoner2Casts": 4, "summoner2Id": 4, "summonerId": "JzXAbt4RJ_JudWrbUaFG3TnH36aiG42donzecFL8OKpj2-k", "summonerLevel": 158, "summonerName": "", "teamEarlySurrendered": false, "teamId": 200, "teamPosition": "UTILITY", "timeCCingOthers": 69, "timePlayed": 1653, "totalAllyJungleMinionsKilled": 2, "totalDamageDealt": 33250, "totalDamageDealtToChampions": 15524, "totalDamageShieldedOnTeammates": 309, "totalDamageTaken": 30774, "totalEnemyJungleMinionsKilled": 0, "totalHeal": 8920, "totalHealsOnTeammates": 1576, "totalMinionsKilled": 29, "totalTimeCCDealt": 229, "totalTimeSpentDead": 202, "totalUnitsHealed": 7, "tripleKills": 0, "trueDamageDealt": 2457, "trueDamageDealtToChampions": 861, "trueDamageTaken": 341, "turretKills": 1, "turretTakedowns": 1, "turretsLost": 9, "unrealKills": 0, "visionClearedPings": 0, "visionScore": 43, "visionWardsBoughtInGame": 0, "wardsKilled": 4, "wardsPlaced": 22, "win": false}], "platformId": "EUW1", "queueId": 420, "teams": [{"bans": [{"championId": 126, "pickTurn": 1}, {"championId": 432, "pickTurn": 2}, {"championId": 30, "pickTurn": 3}, {"championId": 804, "pickTurn": 4}, {"championId": 107, "pickTurn": 5}], "feats": {"EPIC_MONSTER_KILL": {"featState": 1001}, "FIRST_BLOOD": {"featState": 1001}, "FIRST_TURRET": {"featState": 1}}, "objectives": {"atakhan": {"first": true, "kills": 1}, "baron": {"first": false, "kills": 0}, "champion": {"first": false, "kills": 26}, "dragon": {"first": false, "kills": 1}, "horde": {"first": true, "kills": 3}, "inhibitor": {"first": true, "kills": 1}, "riftHerald": {"first": true, "kills": 1}, "tower": {"first": true, "kills": 9}}, "teamId": 100, "win": true}, {"bans": [{"championId": 37, "pickTurn": 6}, {"championId": 897, "pickTurn": 7}, {"championId": 238, "pickTurn": 8}, {"championId": 166, "pickTurn": 9}, {"championId": 30, "pickTurn": 10}], "feats": {"EPIC_MONSTER_KILL": {"featState": 3}, "FIRST_BLOOD": {"featState": 3}, "FIRST_TURRET": {"featState": 1001}}, "objectives": {"atakhan": {"first": false, "kills": 0}, "baron": {"first": false, "kills": 0}, "champion": {"first": true, "kills": 17}, "dragon": {"first": true, "kills": 3}, "horde": {"first": false, "kills": 0}, "inhibitor": {"first": false, "kills": 0}, "riftHerald": {"first": false, "kills": 0}, "tower": {"first": false, "kills": 3}}, "teamId": 200, "win": false}], "tournamentCode": ""}}